{"version": 0.6, "generator": "Overpass API 0.7.62.5 1bd436f1", "osm3s": {"timestamp_osm_base": "2025-03-10T20:07:34Z", "copyright": "The data included in this document is from www.openstreetmap.org. The data is made available under ODbL."}, "elements": [{"type": "node", "id": 2832365499, "lat": -3.3985274, "lon": -57.7120198}, {"type": "node", "id": 2832537388, "lat": -3.3987864, "lon": -57.7104628}, {"type": "node", "id": 2832537398, "lat": -3.3994542, "lon": -57.7069136}, {"type": "node", "id": 2832539831, "lat": -3.3982697, "lon": -57.7135406}, {"type": "node", "id": 2832539841, "lat": -3.3994252, "lon": -57.7071482}, {"type": "node", "id": 2832539846, "lat": -3.3981363, "lon": -57.714413}, {"type": "node", "id": 2832539852, "lat": -3.3989873, "lon": -57.7092927}, {"type": "node", "id": 2832539853, "lat": -3.3993606, "lon": -57.7074604}, {"type": "node", "id": 2838010083, "lat": -3.4151853, "lon": -57.6819053}, {"type": "node", "id": 2838010084, "lat": -3.4015289, "lon": -57.6927321}, {"type": "node", "id": 2838010085, "lat": -3.4129657, "lon": -57.684601}, {"type": "node", "id": 2838010086, "lat": -3.4080708, "lon": -57.6914112}, {"type": "node", "id": 2838010087, "lat": -3.4009572, "lon": -57.6969847}, {"type": "node", "id": 2838010088, "lat": -3.4029653, "lon": -57.6925322}, {"type": "node", "id": 2838010090, "lat": -3.4132334, "lon": -57.6845098}, {"type": "node", "id": 2838010091, "lat": -3.4018931, "lon": -57.6949643}, {"type": "node", "id": 2838010092, "lat": -3.4054929, "lon": -57.6858616}, {"type": "node", "id": 2838010093, "lat": -3.3984056, "lon": -57.6956463}, {"type": "node", "id": 2838010094, "lat": -3.3991955, "lon": -57.6972183}, {"type": "node", "id": 2838010095, "lat": -3.412868, "lon": -57.6937996}, {"type": "node", "id": 2838010096, "lat": -3.4034259, "lon": -57.6922989}, {"type": "node", "id": 2838010098, "lat": -3.3996328, "lon": -57.6960327}, {"type": "node", "id": 2838010099, "lat": -3.3996894, "lon": -57.6942502}, {"type": "node", "id": 2838010100, "lat": -3.3993625, "lon": -57.7064435}, {"type": "node", "id": 2838013901, "lat": -3.4101503, "lon": -57.6971054}, {"type": "node", "id": 2838013902, "lat": -3.4137009, "lon": -57.6959726}, {"type": "node", "id": 2838013903, "lat": -3.41752, "lon": -57.6801726}, {"type": "node", "id": 2838013904, "lat": -3.4138506, "lon": -57.6967339}, {"type": "node", "id": 2838013905, "lat": -3.4037845, "lon": -57.6934042}, {"type": "node", "id": 2838013906, "lat": -3.410062, "lon": -57.6968412}, {"type": "node", "id": 2838013907, "lat": -3.4112026, "lon": -57.691863}, {"type": "node", "id": 2838013908, "lat": -3.4009679, "lon": -57.6957616}, {"type": "node", "id": 2838013909, "lat": -3.4061743, "lon": -57.6916015}, {"type": "node", "id": 2838013911, "lat": -3.4084301, "lon": -57.6960459}, {"type": "node", "id": 2838013912, "lat": -3.4099562, "lon": -57.691521}, {"type": "node", "id": 2838013914, "lat": -3.3993748, "lon": -57.692543}, {"type": "node", "id": 2838013915, "lat": -3.4100098, "lon": -57.6967044}, {"type": "node", "id": 2838013916, "lat": -3.3977938, "lon": -57.6974581}, {"type": "node", "id": 2838013918, "lat": -3.4020153, "lon": -57.6955513}, {"type": "node", "id": 2838013919, "lat": -3.3994401, "lon": -57.706699}, {"type": "node", "id": 2838013920, "lat": -3.3985903, "lon": -57.6950736}, {"type": "node", "id": 2838013921, "lat": -3.4008341, "lon": -57.6797086}, {"type": "node", "id": 2838013922, "lat": -3.3949469, "lon": -57.6998211}, {"type": "node", "id": 2838013924, "lat": -3.4006734, "lon": -57.6784802}, {"type": "node", "id": 2838013925, "lat": -3.4048717, "lon": -57.6917812}, {"type": "node", "id": 2838013926, "lat": -3.4148479, "lon": -57.6978081}, {"type": "node", "id": 2838013927, "lat": -3.3973957, "lon": -57.7000774}, {"type": "node", "id": 2838013928, "lat": -3.3981872, "lon": -57.6963083}, {"type": "node", "id": 2838013929, "lat": -3.4036253, "lon": -57.6961626}, {"type": "node", "id": 2838013930, "lat": -3.4057651, "lon": -57.6930334}, {"type": "node", "id": 2838013931, "lat": -3.4030396, "lon": -57.6953346}, {"type": "node", "id": 2838013932, "lat": -3.398989, "lon": -57.6961548}, {"type": "node", "id": 2838013933, "lat": -3.4055103, "lon": -57.6917075}, {"type": "node", "id": 2838013934, "lat": -3.4117595, "lon": -57.6923941}, {"type": "node", "id": 2838013935, "lat": -3.3901381, "lon": -57.7029258}, {"type": "node", "id": 2838013936, "lat": -3.4089302, "lon": -57.6935436}, {"type": "node", "id": 2838013937, "lat": -3.4005824, "lon": -57.6770532}, {"type": "node", "id": 2838013938, "lat": -3.4018943, "lon": -57.6726008}, {"type": "node", "id": 2838013939, "lat": -3.4098049, "lon": -57.6962283}, {"type": "node", "id": 2838013940, "lat": -3.4321811, "lon": -57.6738025}, {"type": "node", "id": 2838013941, "lat": -3.4008755, "lon": -57.69516}, {"type": "node", "id": 2838013942, "lat": -3.4046147, "lon": -57.6862612}, {"type": "node", "id": 2838013943, "lat": -3.4162643, "lon": -57.681106}, {"type": "node", "id": 2838013945, "lat": -3.402128, "lon": -57.6960921}, {"type": "node", "id": 2838013946, "lat": -3.4095519, "lon": -57.6850677}, {"type": "node", "id": 2838013947, "lat": -3.4029294, "lon": -57.6947593}, {"type": "node", "id": 2838013949, "lat": -3.4073189, "lon": -57.691513}, {"type": "node", "id": 2838013950, "lat": -3.4006004, "lon": -57.693704}, {"type": "node", "id": 2838013951, "lat": -3.3877049, "lon": -57.6997581}, {"type": "node", "id": 2838013952, "lat": -3.4143205, "lon": -57.697721}, {"type": "node", "id": 2838013953, "lat": -3.3973346, "lon": -57.6996072}, {"type": "node", "id": 2838013954, "lat": -3.4162482, "lon": -57.699054}, {"type": "node", "id": 2838013955, "lat": -3.4099442, "lon": -57.6963826}, {"type": "node", "id": 2838013956, "lat": -3.3988019, "lon": -57.6944339}, {"type": "node", "id": 2838013957, "lat": -3.4020711, "lon": -57.6832652}, {"type": "node", "id": 2838013958, "lat": -3.4076188, "lon": -57.6853037}, {"type": "node", "id": 2838013959, "lat": -3.3983734, "lon": -57.7046625}, {"type": "node", "id": 2838013960, "lat": -3.3869427, "lon": -57.6954506}, {"type": "node", "id": 2838013961, "lat": -3.4063184, "lon": -57.6959133}, {"type": "node", "id": 2838013962, "lat": -3.4008019, "lon": -57.6753634}, {"type": "node", "id": 2838013963, "lat": -3.4102092, "lon": -57.6974058}, {"type": "node", "id": 2838013964, "lat": -3.4151411, "lon": -57.6980925}, {"type": "node", "id": 2838013965, "lat": -3.4154249, "lon": -57.6983754}, {"type": "node", "id": 2838013966, "lat": -3.4057968, "lon": -57.6959574}, {"type": "node", "id": 2838013967, "lat": -3.4274581, "lon": -57.6757981}, {"type": "node", "id": 2838013968, "lat": -3.3879406, "lon": -57.7004971}, {"type": "node", "id": 2838013969, "lat": -3.3981228, "lon": -57.7040942}, {"type": "node", "id": 2838013970, "lat": -3.4022023, "lon": -57.6965529}, {"type": "node", "id": 2838013971, "lat": -3.4020711, "lon": -57.6836005}, {"type": "node", "id": 2838013972, "lat": -3.4192095, "lon": -57.6794001}, {"type": "node", "id": 2838013973, "lat": -3.4010603, "lon": -57.696294}, {"type": "node", "id": 2838013974, "lat": -3.4090017, "lon": -57.6912837}, {"type": "node", "id": 2838013975, "lat": -3.388219, "lon": -57.7009879}, {"type": "node", "id": 2838013976, "lat": -3.4014606, "lon": -57.673443}, {"type": "node", "id": 2838013977, "lat": -3.4077607, "lon": -57.6914339}, {"type": "node", "id": 2838013978, "lat": -3.4016545, "lon": -57.6938192}, {"type": "node", "id": 2838013979, "lat": -3.4020175, "lon": -57.6838177}, {"type": "node", "id": 2838013980, "lat": -3.4134289, "lon": -57.684373}, {"type": "node", "id": 2838013981, "lat": -3.4145052, "lon": -57.6828146}, {"type": "node", "id": 2838013982, "lat": -3.4066677, "lon": -57.6958588}, {"type": "node", "id": 2838013984, "lat": -3.3998809, "lon": -57.6953781}, {"type": "node", "id": 2838013985, "lat": -3.4059809, "lon": -57.694157}, {"type": "node", "id": 2838013986, "lat": -3.4207195, "lon": -57.6785848}, {"type": "node", "id": 2838013987, "lat": -3.3975582, "lon": -57.6981803}, {"type": "node", "id": 2838013988, "lat": -3.4106283, "lon": -57.6916109}, {"type": "node", "id": 2838013989, "lat": -3.4031378, "lon": -57.6958819}, {"type": "node", "id": 2838013990, "lat": -3.4006783, "lon": -57.6940371}, {"type": "node", "id": 2838013991, "lat": -3.3991031, "lon": -57.6966937}, {"type": "node", "id": 2838013992, "lat": -3.4184062, "lon": -57.6797757}, {"type": "node", "id": 2838013993, "lat": -3.4235063, "lon": -57.6773859}, {"type": "node", "id": 2838013994, "lat": -3.3866346, "lon": -57.6962256}, {"type": "node", "id": 2838013995, "lat": -3.4015115, "lon": -57.6968533}, {"type": "node", "id": 2838013996, "lat": -3.407762, "lon": -57.6959816}, {"type": "node", "id": 2838013997, "lat": -3.4007859, "lon": -57.6878089}, {"type": "node", "id": 2838013998, "lat": -3.4038422, "lon": -57.6918577}, {"type": "node", "id": 2838013999, "lat": -3.3979877, "lon": -57.6969294}, {"type": "node", "id": 2838014000, "lat": -3.3988675, "lon": -57.6955685}, {"type": "node", "id": 2838014001, "lat": -3.4041627, "lon": -57.6951011}, {"type": "node", "id": 2838014002, "lat": -3.4000978, "lon": -57.6964912}, {"type": "node", "id": 2838016511, "lat": -3.4103752, "lon": -57.7013889}, {"type": "node", "id": 2838016512, "lat": -3.4135488, "lon": -57.6989844}, {"type": "node", "id": 2838016513, "lat": -3.4098853, "lon": -57.7007961}, {"type": "node", "id": 2838016515, "lat": -3.4097782, "lon": -57.7003683}, {"type": "node", "id": 2838016516, "lat": -3.4108628, "lon": -57.6936337}, {"type": "node", "id": 2838016517, "lat": -3.4083163, "lon": -57.698476}, {"type": "node", "id": 2838016518, "lat": -3.4088076, "lon": -57.6929439}, {"type": "node", "id": 2838016519, "lat": -3.4061609, "lon": -57.6962283}, {"type": "node", "id": 2838016520, "lat": -3.4059882, "lon": -57.6961358}, {"type": "node", "id": 2838016521, "lat": -3.40915, "lon": -57.6946693}, {"type": "node", "id": 2838016522, "lat": -3.4119964, "lon": -57.6953512}, {"type": "node", "id": 2838016523, "lat": -3.4084381, "lon": -57.6987094}, {"type": "node", "id": 2838016524, "lat": -3.4114663, "lon": -57.6947317}, {"type": "node", "id": 2838016525, "lat": -3.4085152, "lon": -57.6915882}, {"type": "node", "id": 2838016526, "lat": -3.4074876, "lon": -57.6973455}, {"type": "node", "id": 2838016527, "lat": -3.4090534, "lon": -57.694139}, {"type": "node", "id": 2838016528, "lat": -3.4106925, "lon": -57.6932833}, {"type": "node", "id": 2838016529, "lat": -3.4130473, "lon": -57.6963986}, {"type": "node", "id": 2838016530, "lat": -3.4104435, "lon": -57.7015297}, {"type": "node", "id": 2838016531, "lat": -3.4061919, "lon": -57.6952548}, {"type": "node", "id": 2838016532, "lat": -3.4091364, "lon": -57.6946822}, {"type": "node", "id": 2838016533, "lat": -3.4058814, "lon": -57.6936388}, {"type": "node", "id": 2838016534, "lat": -3.4087179, "lon": -57.6991881}, {"type": "node", "id": 2838016535, "lat": -3.4095921, "lon": -57.6999579}, {"type": "node", "id": 2838016536, "lat": -3.4088611, "lon": -57.699329}, {"type": "node", "id": 2838016537, "lat": -3.4099616, "lon": -57.692425}, {"type": "node", "id": 2838016538, "lat": -3.4131129, "lon": -57.6966508}, {"type": "node", "id": 2838016539, "lat": -3.4104248, "lon": -57.6929078}, {"type": "node", "id": 2838016540, "lat": -3.4087, "lon": -57.6922937}, {"type": "node", "id": 2838016541, "lat": -3.4060988, "lon": -57.6947706}, {"type": "node", "id": 2838016542, "lat": -3.4124275, "lon": -57.6956423}, {"type": "node", "id": 2838016543, "lat": -3.4039544, "lon": -57.6941202}, {"type": "node", "id": 2838063152, "lat": -3.3876862, "lon": -57.6799379}, {"type": "node", "id": 2838063154, "lat": -3.3728064, "lon": -57.7060566}, {"type": "node", "id": 2838063160, "lat": -3.3874974, "lon": -57.6808935}, {"type": "node", "id": 2838063161, "lat": -3.3441996, "lon": -57.6908062}, {"type": "node", "id": 2838063168, "lat": -3.3431258, "lon": -57.6908961}, {"type": "node", "id": 2838063169, "lat": -3.3743507, "lon": -57.699856}, {"type": "node", "id": 2838063170, "lat": -3.3407374, "lon": -57.6915787}, {"type": "node", "id": 2838063175, "lat": -3.349587, "lon": -57.6944044}, {"type": "node", "id": 2838063176, "lat": -3.387484, "lon": -57.6821736}, {"type": "node", "id": 2838063180, "lat": -3.3748173, "lon": -57.6947249}, {"type": "node", "id": 2838063184, "lat": -3.3487141, "lon": -57.6928943}, {"type": "node", "id": 2838063185, "lat": -3.3587899, "lon": -57.7022016}, {"type": "node", "id": 2838063188, "lat": -3.3696168, "lon": -57.6874213}, {"type": "node", "id": 2838063190, "lat": -3.35635, "lon": -57.7004723}, {"type": "node", "id": 2838063191, "lat": -3.374176, "lon": -57.6983815}, {"type": "node", "id": 2838063197, "lat": -3.3878375, "lon": -57.6842389}, {"type": "node", "id": 2838063701, "lat": -3.3881347, "lon": -57.6852232}, {"type": "node", "id": 2838063705, "lat": -3.3717742, "lon": -57.7059674}, {"type": "node", "id": 2838063711, "lat": -3.3694902, "lon": -57.7059647}, {"type": "node", "id": 2838063712, "lat": -3.390357, "lon": -57.6859528}, {"type": "node", "id": 2838063727, "lat": -3.3389139, "lon": -57.6901558}, {"type": "node", "id": 2838063728, "lat": -3.3503635, "lon": -57.6955926}, {"type": "node", "id": 2838063730, "lat": -3.3870074, "lon": -57.6743442}, {"type": "node", "id": 2838063736, "lat": -3.3539823, "lon": -57.6980831}, {"type": "node", "id": 2838063737, "lat": -3.3885476, "lon": -57.692535}, {"type": "node", "id": 2838063741, "lat": -3.374911, "lon": -57.6951152}, {"type": "node", "id": 2838063743, "lat": -3.3401938, "lon": -57.6912971}, {"type": "node", "id": 2838063744, "lat": -3.390938, "lon": -57.6869237}, {"type": "node", "id": 2838063746, "lat": -3.3888415, "lon": -57.6854834}, {"type": "node", "id": 2838063747, "lat": -3.3469401, "lon": -57.6905984}, {"type": "node", "id": 2838063748, "lat": -3.3907854, "lon": -57.6876479}, {"type": "node", "id": 2838063750, "lat": -3.3462988, "lon": -57.6904026}, {"type": "node", "id": 2838063751, "lat": -3.3878133, "lon": -57.6936464}, {"type": "node", "id": 2838063752, "lat": -3.3454474, "lon": -57.690585}, {"type": "node", "id": 2838063763, "lat": -3.3729999, "lon": -57.6933879}, {"type": "node", "id": 2838063765, "lat": -3.3722783, "lon": -57.6926945}, {"type": "node", "id": 2838063769, "lat": -3.3647918, "lon": -57.7051225}, {"type": "node", "id": 2838063770, "lat": -3.373599, "lon": -57.7063282}, {"type": "node", "id": 2838063771, "lat": -3.3728827, "lon": -57.7044875}, {"type": "node", "id": 2838063774, "lat": -3.3709649, "lon": -57.6912461}, {"type": "node", "id": 2838063778, "lat": -3.3500007, "lon": -57.695244}, {"type": "node", "id": 2838063783, "lat": -3.3632374, "lon": -57.7048771}, {"type": "node", "id": 2838063784, "lat": -3.3732435, "lon": -57.7056657}, {"type": "node", "id": 2838063786, "lat": -3.3666259, "lon": -57.7053384}, {"type": "node", "id": 2838063788, "lat": -3.3873502, "lon": -57.6778042}, {"type": "node", "id": 2838063789, "lat": -3.3607754, "lon": -57.7037378}, {"type": "node", "id": 2838063791, "lat": -3.3729831, "lon": -57.7024886}, {"type": "node", "id": 2838063795, "lat": -3.339594, "lon": -57.6908572}, {"type": "node", "id": 2838063801, "lat": -3.3898162, "lon": -57.6899493}, {"type": "node", "id": 2838106335, "lat": -3.3903488, "lon": -57.70277}, {"type": "node", "id": 2838106340, "lat": -3.398674, "lon": -57.7051923}, {"type": "node", "id": 2838106354, "lat": -3.397618, "lon": -57.7015154}, {"type": "node", "id": 2838106356, "lat": -3.4034178, "lon": -57.7027032}, {"type": "node", "id": 2838106399, "lat": -3.3978433, "lon": -57.7028507}, {"type": "node", "id": 2838108031, "lat": -3.3982329, "lon": -57.7043903}, {"type": "node", "id": 2838108048, "lat": -3.3921041, "lon": -57.7016551}, {"type": "node", "id": 2844358211, "lat": -3.405081, "lon": -57.6943144}, {"type": "node", "id": 2844358212, "lat": -3.404977, "lon": -57.693871}, {"type": "node", "id": 2844358213, "lat": -3.4054841, "lon": -57.6954107}, {"type": "node", "id": 2844358214, "lat": -3.4055746, "lon": -57.6959697}, {"type": "node", "id": 2844358215, "lat": -3.405216, "lon": -57.6948894}, {"type": "node", "id": 2844358216, "lat": -3.4048166, "lon": -57.6931877}, {"type": "node", "id": 2844429461, "lat": -3.3994498, "lon": -57.693117}, {"type": "node", "id": 2844429462, "lat": -3.3996105, "lon": -57.6939163}, {"type": "node", "id": 2844429463, "lat": -3.401565, "lon": -57.6934917}, {"type": "node", "id": 2844429464, "lat": -3.4004387, "lon": -57.6929645}, {"type": "node", "id": 2844429465, "lat": -3.4011862, "lon": -57.69272}, {"type": "node", "id": 2844429466, "lat": -3.3992067, "lon": -57.693147}, {"type": "node", "id": 3226745041, "lat": -3.3973755, "lon": -57.6990943}, {"type": "node", "id": 3226745043, "lat": -3.3973406, "lon": -57.6993511}, {"type": "node", "id": 3226830418, "lat": -3.3678074, "lon": -57.7056469}, {"type": "node", "id": 3226830420, "lat": -3.3726571, "lon": -57.7060258}, {"type": "node", "id": 3226830422, "lat": -3.3728191, "lon": -57.7041784}, {"type": "node", "id": 3226830423, "lat": -3.3574826, "lon": -57.7012548}, {"type": "node", "id": 3226830425, "lat": -3.3728406, "lon": -57.7035729}, {"type": "node", "id": 3226830426, "lat": -3.3636176, "lon": -57.7049696}, {"type": "node", "id": 3226830427, "lat": -3.361333, "lon": -57.7040268}, {"type": "node", "id": 3226830430, "lat": -3.3658414, "lon": -57.705203}, {"type": "node", "id": 3226830432, "lat": -3.3730581, "lon": -57.7022439}, {"type": "node", "id": 3226830433, "lat": -3.3722562, "lon": -57.7059808}, {"type": "node", "id": 3226830434, "lat": -3.3583508, "lon": -57.701865}, {"type": "node", "id": 3226830435, "lat": -3.367067, "lon": -57.7054524}, {"type": "node", "id": 3226830437, "lat": -3.3623016, "lon": -57.7044895}, {"type": "node", "id": 3226830438, "lat": -3.3743065, "lon": -57.6992009}, {"type": "node", "id": 3226830439, "lat": -3.3706563, "lon": -57.7059849}, {"type": "node", "id": 3226830440, "lat": -3.3743674, "lon": -57.6995241}, {"type": "node", "id": 3226830441, "lat": -3.3688122, "lon": -57.7058762}, {"type": "node", "id": 3226830442, "lat": -3.3730133, "lon": -57.7023666}, {"type": "node", "id": 3226830446, "lat": -3.3638948, "lon": -57.7050126}, {"type": "node", "id": 3226830451, "lat": -3.3549161, "lon": -57.6989843}, {"type": "node", "id": 3228008457, "lat": -3.3876152, "lon": -57.6829514}, {"type": "node", "id": 3228008458, "lat": -3.3905498, "lon": -57.6861593}, {"type": "node", "id": 3228008459, "lat": -3.3891843, "lon": -57.6914218}, {"type": "node", "id": 3228008460, "lat": -3.3906917, "lon": -57.6863202}, {"type": "node", "id": 3228010561, "lat": -3.3908604, "lon": -57.686677}, {"type": "node", "id": 3228010562, "lat": -3.3877371, "lon": -57.6792164}, {"type": "node", "id": 3228010563, "lat": -3.3907934, "lon": -57.6865187}, {"type": "node", "id": 3228010564, "lat": -3.3874974, "lon": -57.6818866}, {"type": "node", "id": 3228010565, "lat": -3.3901241, "lon": -57.6857945}, {"type": "node", "id": 3228010566, "lat": -3.3896609, "lon": -57.6856524}, {"type": "node", "id": 3228010567, "lat": -3.3908952, "lon": -57.6873797}, {"type": "node", "id": 3228010568, "lat": -3.3883382, "lon": -57.6853547}, {"type": "node", "id": 3228010569, "lat": -3.3877464, "lon": -57.6794618}, {"type": "node", "id": 3228010570, "lat": -3.3909354, "lon": -57.6871571}, {"type": "node", "id": 3228010571, "lat": -3.3872149, "lon": -57.6770398}, {"type": "node", "id": 3228010572, "lat": -3.3866301, "lon": -57.6966269}, {"type": "node", "id": 3228010573, "lat": -3.3879874, "lon": -57.6850569}, {"type": "node", "id": 3228010574, "lat": -3.3894547, "lon": -57.69088}, {"type": "node", "id": 3228010575, "lat": -3.3878294, "lon": -57.6837641}, {"type": "node", "id": 3228010576, "lat": -3.3885283, "lon": -57.6854137}, {"type": "node", "id": 3228010577, "lat": -3.3889593, "lon": -57.6918402}, {"type": "node", "id": 3228010578, "lat": -3.3874894, "lon": -57.6810417}, {"type": "node", "id": 3228010579, "lat": -3.3866065, "lon": -57.6964543}, {"type": "node", "id": 3228025606, "lat": -3.3880905, "lon": -57.700823}, {"type": "node", "id": 3228025609, "lat": -3.3866185, "lon": -57.696289}, {"type": "node", "id": 3228025625, "lat": -3.3871815, "lon": -57.6764846}, {"type": "node", "id": 3228025630, "lat": -3.3878442, "lon": -57.7002047}, {"type": "node", "id": 3228068474, "lat": -3.3866681, "lon": -57.6961049}, {"type": "node", "id": 3228183459, "lat": -3.387039, "lon": -57.6952334}, {"type": "node", "id": 3228211352, "lat": -3.3874613, "lon": -57.6781985}, {"type": "node", "id": 3228213762, "lat": -3.3904427, "lon": -57.6884231}, {"type": "node", "id": 3692623985, "lat": -3.3999947, "lon": -57.6959494}, {"type": "node", "id": 4477281014, "lat": -3.4132361, "lon": -57.6665041}, {"type": "node", "id": 4477281015, "lat": -3.413544, "lon": -57.6666462}, {"type": "node", "id": 4477281016, "lat": -3.4137261, "lon": -57.6668313}, {"type": "node", "id": 4477281017, "lat": -3.4139189, "lon": -57.6672685}, {"type": "node", "id": 4477281018, "lat": -3.4141143, "lon": -57.6676199}, {"type": "node", "id": 4477281019, "lat": -3.4145079, "lon": -57.6684058}, {"type": "node", "id": 4477281020, "lat": -3.4146873, "lon": -57.6690736}, {"type": "node", "id": 4477281021, "lat": -3.4147569, "lon": -57.6697442}, {"type": "node", "id": 4477281022, "lat": -3.4148426, "lon": -57.6703718}, {"type": "node", "id": 4477281023, "lat": -3.4150193, "lon": -57.6707849}, {"type": "node", "id": 4477281024, "lat": -3.4160581, "lon": -57.6718658}, {"type": "node", "id": 4477281025, "lat": -3.4182483, "lon": -57.6749343}, {"type": "node", "id": 4477281026, "lat": -3.4189538, "lon": -57.6809591}, {"type": "node", "id": 4477281027, "lat": -3.4192751, "lon": -57.6815385}, {"type": "node", "id": 4477281028, "lat": -3.4195107, "lon": -57.6819033}, {"type": "node", "id": 4477281029, "lat": -3.4202604, "lon": -57.6823753}, {"type": "node", "id": 4477281030, "lat": -3.4212243, "lon": -57.6829976}, {"type": "node", "id": 4477281031, "lat": -3.4215241, "lon": -57.6834482}, {"type": "node", "id": 4477281032, "lat": -3.4216312, "lon": -57.683813}, {"type": "node", "id": 4477281033, "lat": -3.4217169, "lon": -57.6869244}, {"type": "node", "id": 4477281034, "lat": -3.4217598, "lon": -57.6843494}, {"type": "node", "id": 4477281035, "lat": -3.421824, "lon": -57.6866454}, {"type": "node", "id": 4477281036, "lat": -3.421824, "lon": -57.6872033}, {"type": "node", "id": 4477281037, "lat": -3.4222096, "lon": -57.686109}, {"type": "node", "id": 4477281038, "lat": -3.4222952, "lon": -57.6851863}, {"type": "node", "id": 4477281039, "lat": -3.4223167, "lon": -57.6856584}, {"type": "node", "id": 4477281040, "lat": -3.426729, "lon": -57.6914948}, {"type": "node", "id": 4477281041, "lat": -3.4333904, "lon": -57.6728052}, {"type": "node", "id": 4477281042, "lat": -3.4350183, "lon": -57.6710671}, {"type": "node", "id": 4477281043, "lat": -3.4358108, "lon": -57.670638}, {"type": "node", "id": 4477281044, "lat": -3.4362713, "lon": -57.6692325}, {"type": "node", "id": 4477281045, "lat": -3.4369032, "lon": -57.6705736}, {"type": "node", "id": 4477281046, "lat": -3.4369995, "lon": -57.6680523}, {"type": "node", "id": 4477281047, "lat": -3.4373851, "lon": -57.6675159}, {"type": "node", "id": 4477281048, "lat": -3.4378349, "lon": -57.6673442}, {"type": "node", "id": 4477281049, "lat": -3.438124, "lon": -57.6706594}, {"type": "node", "id": 4477281050, "lat": -3.4392593, "lon": -57.6708955}, {"type": "node", "id": 4477281051, "lat": -3.4397519, "lon": -57.6709813}, {"type": "node", "id": 4477281052, "lat": -3.4400732, "lon": -57.6708955}, {"type": "node", "id": 4477281053, "lat": -3.4402552, "lon": -57.6670224}, {"type": "node", "id": 4477281054, "lat": -3.4408121, "lon": -57.6666576}, {"type": "node", "id": 4477281055, "lat": -3.4412619, "lon": -57.6585251}, {"type": "node", "id": 4477281056, "lat": -3.4413048, "lon": -57.657817}, {"type": "node", "id": 4477281057, "lat": -3.4413476, "lon": -57.659362}, {"type": "node", "id": 4477281058, "lat": -3.4414119, "lon": -57.6657134}, {"type": "node", "id": 4477281059, "lat": -3.4415404, "lon": -57.6636535}, {"type": "node", "id": 4477281060, "lat": -3.4415618, "lon": -57.657302}, {"type": "node", "id": 4477281061, "lat": -3.4415618, "lon": -57.6628381}, {"type": "node", "id": 4477281062, "lat": -3.4415832, "lon": -57.6647264}, {"type": "node", "id": 4477281063, "lat": -3.4416261, "lon": -57.6604992}, {"type": "node", "id": 4477281064, "lat": -3.4416689, "lon": -57.6617867}, {"type": "node", "id": 4477281065, "lat": -3.4417653, "lon": -57.6703161}, {"type": "node", "id": 4477281066, "lat": -3.4428362, "lon": -57.6701015}, {"type": "node", "id": 4477281067, "lat": -3.4435538, "lon": -57.6530749}, {"type": "node", "id": 4477281068, "lat": -3.4439393, "lon": -57.6525384}, {"type": "node", "id": 4477281069, "lat": -3.44395, "lon": -57.6700157}, {"type": "node", "id": 4477281070, "lat": -3.4443677, "lon": -57.6522595}, {"type": "node", "id": 4477281071, "lat": -3.4476126, "lon": -57.6696938}, {"type": "node", "id": 4477281072, "lat": -3.4486836, "lon": -57.6697153}, {"type": "node", "id": 4477281073, "lat": -3.4501186, "lon": -57.6697797}, {"type": "node", "id": 4477281074, "lat": -3.4508469, "lon": -57.6697797}, {"type": "node", "id": 4477281075, "lat": -3.4521106, "lon": -57.6694793}, {"type": "node", "id": 4477281076, "lat": -3.4536956, "lon": -57.6692003}, {"type": "node", "id": 4477281077, "lat": -3.4539419, "lon": -57.6513368}, {"type": "node", "id": 4477281078, "lat": -3.4563086, "lon": -57.6690716}, {"type": "node", "id": 4477281079, "lat": -3.4565014, "lon": -57.6239032}, {"type": "node", "id": 4477281080, "lat": -3.4565228, "lon": -57.623474}, {"type": "node", "id": 4477281081, "lat": -3.4567156, "lon": -57.6241821}, {"type": "node", "id": 4477281082, "lat": -3.456994, "lon": -57.6223153}, {"type": "node", "id": 4477281083, "lat": -3.4574224, "lon": -57.6689643}, {"type": "node", "id": 4477281084, "lat": -3.4586004, "lon": -57.6256842}, {"type": "node", "id": 4477281085, "lat": -3.4586433, "lon": -57.6687068}, {"type": "node", "id": 4477281086, "lat": -3.4591895, "lon": -57.6511008}, {"type": "node", "id": 4477281087, "lat": -3.4595643, "lon": -57.6685995}, {"type": "node", "id": 4477281088, "lat": -3.4602497, "lon": -57.6270145}, {"type": "node", "id": 4477281089, "lat": -3.4608173, "lon": -57.6512081}, {"type": "node", "id": 4477281090, "lat": -3.461342, "lon": -57.6278514}, {"type": "node", "id": 4477281091, "lat": -3.4616419, "lon": -57.628302}, {"type": "node", "id": 4477281092, "lat": -3.4618668, "lon": -57.6514226}, {"type": "node", "id": 4477281093, "lat": -3.4624772, "lon": -57.6527637}, {"type": "node", "id": 4477281094, "lat": -3.4625415, "lon": -57.6516265}, {"type": "node", "id": 4477281095, "lat": -3.46267, "lon": -57.6536864}, {"type": "node", "id": 4477281096, "lat": -3.4627342, "lon": -57.6289457}, {"type": "node", "id": 4477281097, "lat": -3.4628841, "lon": -57.650854}, {"type": "node", "id": 4477281098, "lat": -3.4632483, "lon": -57.6602739}, {"type": "node", "id": 4477281099, "lat": -3.4632911, "lon": -57.6609177}, {"type": "node", "id": 4477281100, "lat": -3.4633125, "lon": -57.6555962}, {"type": "node", "id": 4477281101, "lat": -3.4633554, "lon": -57.6581282}, {"type": "node", "id": 4477281102, "lat": -3.4633768, "lon": -57.6573986}, {"type": "node", "id": 4477281103, "lat": -3.4633982, "lon": -57.6564545}, {"type": "node", "id": 4477281104, "lat": -3.4634196, "lon": -57.6294607}, {"type": "node", "id": 4477281105, "lat": -3.4634196, "lon": -57.6596087}, {"type": "node", "id": 4477281106, "lat": -3.4634624, "lon": -57.6589865}, {"type": "node", "id": 4477281107, "lat": -3.4638908, "lon": -57.6682133}, {"type": "node", "id": 4477281108, "lat": -3.4640193, "lon": -57.6489014}, {"type": "node", "id": 4477281109, "lat": -3.4640836, "lon": -57.6463694}, {"type": "node", "id": 4477281110, "lat": -3.4641264, "lon": -57.6304692}, {"type": "node", "id": 4477281111, "lat": -3.4641264, "lon": -57.6456613}, {"type": "node", "id": 4477281112, "lat": -3.4642978, "lon": -57.6680845}, {"type": "node", "id": 4477281113, "lat": -3.4643406, "lon": -57.6448244}, {"type": "node", "id": 4477281114, "lat": -3.4644691, "lon": -57.6484293}, {"type": "node", "id": 4477281115, "lat": -3.4646833, "lon": -57.6435369}, {"type": "node", "id": 4477281116, "lat": -3.4647047, "lon": -57.6311559}, {"type": "node", "id": 4477281117, "lat": -3.4652188, "lon": -57.6482791}, {"type": "node", "id": 4477281118, "lat": -3.4653259, "lon": -57.6314563}, {"type": "node", "id": 4477281119, "lat": -3.4654115, "lon": -57.6425499}, {"type": "node", "id": 4477281120, "lat": -3.4656685, "lon": -57.6316494}, {"type": "node", "id": 4477281121, "lat": -3.4662683, "lon": -57.641713}, {"type": "node", "id": 4477281122, "lat": -3.4665681, "lon": -57.6410908}, {"type": "node", "id": 4477281123, "lat": -3.466611, "lon": -57.6317781}, {"type": "node", "id": 4477281124, "lat": -3.4672535, "lon": -57.6399535}, {"type": "node", "id": 4477281125, "lat": -3.4675534, "lon": -57.6320356}, {"type": "node", "id": 4477281126, "lat": -3.4676605, "lon": -57.6393742}, {"type": "node", "id": 4477281127, "lat": -3.4683887, "lon": -57.6480645}, {"type": "node", "id": 4477281128, "lat": -3.4686243, "lon": -57.632851}, {"type": "node", "id": 4477281129, "lat": -3.4689027, "lon": -57.6376575}, {"type": "node", "id": 4477281130, "lat": -3.4690741, "lon": -57.6335377}, {"type": "node", "id": 4477281131, "lat": -3.4690955, "lon": -57.6366705}, {"type": "node", "id": 4477281132, "lat": -3.4692026, "lon": -57.6347608}, {"type": "node", "id": 4477281133, "lat": -3.4695453, "lon": -57.6480645}, {"type": "node", "id": 4477281134, "lat": -3.4704877, "lon": -57.6482791}, {"type": "node", "id": 4477281135, "lat": -3.471323, "lon": -57.6481933}, {"type": "node", "id": 4477281136, "lat": -3.4718585, "lon": -57.6480645}, {"type": "node", "id": 4477281137, "lat": -3.4731221, "lon": -57.6473993}, {"type": "node", "id": 4477281138, "lat": -3.4738289, "lon": -57.6472062}, {"type": "node", "id": 4477281139, "lat": -3.4756709, "lon": -57.6468843}, {"type": "node", "id": 4477281140, "lat": -3.4764634, "lon": -57.6469058}, {"type": "node", "id": 4477281141, "lat": -3.4781554, "lon": -57.6470775}, {"type": "node", "id": 4477281142, "lat": -3.483617, "lon": -57.6468629}, {"type": "node", "id": 4477281143, "lat": -3.484538, "lon": -57.6470345}, {"type": "node", "id": 4477281144, "lat": -3.4856517, "lon": -57.647571}, {"type": "node", "id": 4477281145, "lat": -3.4866584, "lon": -57.6478285}, {"type": "node", "id": 4477281146, "lat": -3.4878364, "lon": -57.6478285}, {"type": "node", "id": 4477281147, "lat": -3.4883718, "lon": -57.6476568}, {"type": "node", "id": 4477281148, "lat": -3.4890572, "lon": -57.647056}, {"type": "node", "id": 4477281149, "lat": -3.4895712, "lon": -57.6467127}, {"type": "node", "id": 4477281150, "lat": -3.4920771, "lon": -57.6458973}, {"type": "node", "id": 4477281151, "lat": -3.492634, "lon": -57.6458973}, {"type": "node", "id": 4477281152, "lat": -3.4932979, "lon": -57.6460046}, {"type": "node", "id": 4477281153, "lat": -3.4938119, "lon": -57.6461548}, {"type": "node", "id": 4477281154, "lat": -3.4957181, "lon": -57.6473564}, {"type": "node", "id": 4477281155, "lat": -3.4967676, "lon": -57.6476568}, {"type": "node", "id": 4477281156, "lat": -3.4973459, "lon": -57.6479787}, {"type": "node", "id": 4477281157, "lat": -3.4977956, "lon": -57.648322}, {"type": "node", "id": 4477281158, "lat": -3.4998946, "lon": -57.6504034}, {"type": "node", "id": 4895889171, "lat": -3.4013508, "lon": -57.6969163}, {"type": "node", "id": 4895889172, "lat": -3.4008176, "lon": -57.6946304}, {"type": "node", "id": 4895889173, "lat": -3.401779, "lon": -57.694417}, {"type": "node", "id": 4895889174, "lat": -3.4081222, "lon": -57.6960191}, {"type": "node", "id": 4895889175, "lat": -3.4081783, "lon": -57.6948635}, {"type": "node", "id": 4895889176, "lat": -3.408067, "lon": -57.6943148}, {"type": "node", "id": 4895889177, "lat": -3.407952, "lon": -57.6937478}, {"type": "node", "id": 4895889178, "lat": -3.4078335, "lon": -57.6931636}, {"type": "node", "id": 4895889179, "lat": -3.4077104, "lon": -57.6925566}, {"type": "node", "id": 4895889180, "lat": -3.4071487, "lon": -57.6950608}, {"type": "node", "id": 4895889181, "lat": -3.4070446, "lon": -57.6945299}, {"type": "node", "id": 4895889182, "lat": -3.4069304, "lon": -57.6939472}, {"type": "node", "id": 4895889183, "lat": -3.4068234, "lon": -57.6934011}, {"type": "node", "id": 4895889184, "lat": -3.4067099, "lon": -57.6928221}, {"type": "node", "id": 4895889185, "lat": -3.4035428, "lon": -57.6925114}, {"type": "node", "id": 4895889186, "lat": -3.4040461, "lon": -57.694546}, {"type": "node", "id": 4895889187, "lat": -3.4042623, "lon": -57.6955347}, {"type": "node", "id": 4895889188, "lat": -3.4040624, "lon": -57.6951245}, {"type": "node", "id": 4895889189, "lat": -3.4042586, "lon": -57.6960728}, {"type": "node", "id": 4895889190, "lat": -3.4042428, "lon": -57.6954522}, {"type": "node", "id": 4895889191, "lat": -3.405294, "lon": -57.6952218}, {"type": "node", "id": 4895889192, "lat": -3.4051365, "lon": -57.6945506}, {"type": "node", "id": 4895889193, "lat": -3.4041005, "lon": -57.6947999}, {"type": "node", "id": 4895889194, "lat": -3.4040185, "lon": -57.6944396}, {"type": "node", "id": 4895889195, "lat": -3.4050507, "lon": -57.6941851}, {"type": "node", "id": 4895889196, "lat": -3.4038702, "lon": -57.6937656}, {"type": "node", "id": 4895889197, "lat": -3.4048987, "lon": -57.6935375}, {"type": "node", "id": 4895889198, "lat": -3.4037162, "lon": -57.6930934}, {"type": "node", "id": 4895889199, "lat": -3.404679, "lon": -57.6928688}, {"type": "node", "id": 4895889200, "lat": -3.4036516, "lon": -57.6927735}, {"type": "node", "id": 4895889201, "lat": -3.4045937, "lon": -57.6925532}, {"type": "node", "id": 4895889202, "lat": -3.4034366, "lon": -57.6934469}, {"type": "node", "id": 4895889203, "lat": -3.4041268, "lon": -57.6933428}, {"type": "node", "id": 4895889204, "lat": -3.4020737, "lon": -57.6937124}, {"type": "node", "id": 4895889205, "lat": -3.4018852, "lon": -57.6929093}, {"type": "node", "id": 4895889206, "lat": -3.4019951, "lon": -57.6933775}, {"type": "node", "id": 4895889207, "lat": -3.4028015, "lon": -57.6931988}, {"type": "node", "id": 4895889208, "lat": -3.4019182, "lon": -57.69305}, {"type": "node", "id": 4895889209, "lat": -3.4036175, "lon": -57.6926806}, {"type": "node", "id": 4895889210, "lat": -3.4010428, "lon": -57.6939552}, {"type": "node", "id": 4895889211, "lat": -3.4011691, "lon": -57.6945521}, {"type": "node", "id": 4895889212, "lat": -3.3995422, "lon": -57.6935931}, {"type": "node", "id": 4895889213, "lat": -3.4005267, "lon": -57.6933531}, {"type": "node", "id": 4895889214, "lat": -3.4014923, "lon": -57.6931727}, {"type": "node", "id": 4895889215, "lat": -3.4000184, "lon": -57.6941835}, {"type": "node", "id": 4895889216, "lat": -3.4001051, "lon": -57.6946375}, {"type": "node", "id": 4895889217, "lat": -3.400345, "lon": -57.6941097}, {"type": "node", "id": 4895889218, "lat": -3.4004476, "lon": -57.6945778}, {"type": "node", "id": 4895889254, "lat": -3.3990586, "lon": -57.7058839}, {"type": "node", "id": 4895889258, "lat": -3.3989659, "lon": -57.705726}, {"type": "node", "id": 4895889259, "lat": -3.390021, "lon": -57.702791}, {"type": "node", "id": 4895889261, "lat": -3.3978099, "lon": -57.7026822}, {"type": "node", "id": 4895889262, "lat": -3.3974588, "lon": -57.6982001}, {"type": "node", "id": 5092999244, "lat": -3.3466965, "lon": -57.6904294}, {"type": "node", "id": 5092999245, "lat": -3.3478184, "lon": -57.6916713}, {"type": "node", "id": 5092999246, "lat": -3.3552783, "lon": -57.6834878}, {"type": "node", "id": 5092999247, "lat": -3.3553479, "lon": -57.6836367}, {"type": "node", "id": 5092999248, "lat": -3.3556022, "lon": -57.6845044}, {"type": "node", "id": 5092999249, "lat": -3.3555996, "lon": -57.6847525}, {"type": "node", "id": 5092999250, "lat": -3.3554965, "lon": -57.6850703}, {"type": "node", "id": 5092999251, "lat": -3.3553372, "lon": -57.6852353}, {"type": "node", "id": 5092999252, "lat": -3.3551417, "lon": -57.6853077}, {"type": "node", "id": 5092999253, "lat": -3.3543331, "lon": -57.6851468}, {"type": "node", "id": 5092999254, "lat": -3.3541644, "lon": -57.6852232}, {"type": "node", "id": 5092999255, "lat": -3.3541028, "lon": -57.6853815}, {"type": "node", "id": 5092999256, "lat": -3.3541068, "lon": -57.6856457}, {"type": "node", "id": 5092999257, "lat": -3.3541617, "lon": -57.6859863}, {"type": "node", "id": 5092999258, "lat": -3.3542219, "lon": -57.6865375}, {"type": "node", "id": 5092999259, "lat": -3.3542889, "lon": -57.6868419}, {"type": "node", "id": 5092999260, "lat": -3.3542929, "lon": -57.6871987}, {"type": "node", "id": 5092999261, "lat": -3.3541818, "lon": -57.6876399}, {"type": "node", "id": 5092999262, "lat": -3.3541577, "lon": -57.6881026}, {"type": "node", "id": 5092999263, "lat": -3.3541965, "lon": -57.6888657}, {"type": "node", "id": 5092999264, "lat": -3.3540251, "lon": -57.689099}, {"type": "node", "id": 5092999265, "lat": -3.3537627, "lon": -57.6892439}, {"type": "node", "id": 5092999266, "lat": -3.3534026, "lon": -57.689496}, {"type": "node", "id": 5092999267, "lat": -3.3520865, "lon": -57.6904428}, {"type": "node", "id": 5092999268, "lat": -3.350314, "lon": -57.6917101}, {"type": "node", "id": 5092999269, "lat": -3.349022, "lon": -57.6926342}, {"type": "node", "id": 6947015961, "lat": -3.3980508, "lon": -57.7149233}, {"type": "node", "id": 6976289992, "lat": -3.4078839, "lon": -57.6978752}, {"type": "node", "id": 6976289993, "lat": -3.4081061, "lon": -57.6981327}, {"type": "node", "id": 6976289994, "lat": -3.4085358, "lon": -57.6989467}, {"type": "node", "id": 6976289995, "lat": -3.4086188, "lon": -57.6990795}, {"type": "node", "id": 6976289996, "lat": -3.4090405, "lon": -57.6994926}, {"type": "node", "id": 6976289997, "lat": -3.4094555, "lon": -57.699789}, {"type": "node", "id": 6976289998, "lat": -3.4095171, "lon": -57.6998466}, {"type": "node", "id": 6976289999, "lat": -3.4096751, "lon": -57.7001001}, {"type": "node", "id": 6976290000, "lat": -3.4097434, "lon": -57.7002288}, {"type": "node", "id": 6976290001, "lat": -3.4097608, "lon": -57.7005507}, {"type": "node", "id": 6976290002, "lat": -3.4097728, "lon": -57.7006124}, {"type": "node", "id": 6976290003, "lat": -3.4098023, "lon": -57.7006862}, {"type": "node", "id": 6976290004, "lat": -3.4101718, "lon": -57.7010925}, {"type": "node", "id": 6976290005, "lat": -3.4103137, "lon": -57.7012655}, {"type": "node", "id": 6976849298, "lat": -3.4030698, "lon": -57.6968399}, {"type": "node", "id": 6976849299, "lat": -3.4028623, "lon": -57.6973401}, {"type": "node", "id": 6976849300, "lat": -3.4027645, "lon": -57.6975922}, {"type": "node", "id": 6976849301, "lat": -3.4027297, "lon": -57.6980616}, {"type": "node", "id": 6976849302, "lat": -3.4027471, "lon": -57.6981394}, {"type": "node", "id": 6976849303, "lat": -3.4036642, "lon": -57.6991519}, {"type": "node", "id": 6976849304, "lat": -3.4037003, "lon": -57.6993075}, {"type": "node", "id": 6976849305, "lat": -3.4036401, "lon": -57.6994108}, {"type": "node", "id": 6976849306, "lat": -3.4034901, "lon": -57.6995596}, {"type": "node", "id": 6976849307, "lat": -3.4032692, "lon": -57.6997353}, {"type": "node", "id": 6976849308, "lat": -3.4032197, "lon": -57.6998051}, {"type": "node", "id": 6976849309, "lat": -3.4032023, "lon": -57.6998641}, {"type": "node", "id": 6976849310, "lat": -3.4032144, "lon": -57.6999271}, {"type": "node", "id": 6976849311, "lat": -3.4032518, "lon": -57.6999767}, {"type": "node", "id": 6976849312, "lat": -3.4038168, "lon": -57.7002959}, {"type": "node", "id": 6976849313, "lat": -3.4041126, "lon": -57.7004863}, {"type": "node", "id": 6976849314, "lat": -3.4041649, "lon": -57.7005279}, {"type": "node", "id": 6976849315, "lat": -3.4042064, "lon": -57.7005816}, {"type": "node", "id": 6976849316, "lat": -3.4041943, "lon": -57.7006446}, {"type": "node", "id": 6976849317, "lat": -3.4041568, "lon": -57.7007251}, {"type": "node", "id": 6976849318, "lat": -3.404035, "lon": -57.7008337}, {"type": "node", "id": 6976849319, "lat": -3.4039694, "lon": -57.7009209}, {"type": "node", "id": 6976849320, "lat": -3.4039386, "lon": -57.7010188}, {"type": "node", "id": 6976849321, "lat": -3.4039399, "lon": -57.7011944}, {"type": "node", "id": 6976849322, "lat": -3.4039761, "lon": -57.7015632}, {"type": "node", "id": 6976849323, "lat": -3.4039908, "lon": -57.7016772}, {"type": "node", "id": 6976849324, "lat": -3.4039721, "lon": -57.7017792}, {"type": "node", "id": 6976849325, "lat": -3.4039172, "lon": -57.7019173}, {"type": "node", "id": 6976849326, "lat": -3.4037994, "lon": -57.7020782}, {"type": "node", "id": 6976849327, "lat": -3.4036294, "lon": -57.7023706}, {"type": "node", "id": 6976849328, "lat": -3.4028931, "lon": -57.6983124}, {"type": "node", "id": 6976849329, "lat": -3.403703, "lon": -57.6992351}, {"type": "node", "id": 6976849330, "lat": -3.4027297, "lon": -57.6979101}, {"type": "node", "id": 6976849331, "lat": -3.4027926, "lon": -57.6982065}, {"type": "node", "id": 6976850124, "lat": -3.4140474, "lon": -57.6976258}, {"type": "node", "id": 6976850125, "lat": -3.4140902, "lon": -57.697666}, {"type": "node", "id": 6976850126, "lat": -3.4141411, "lon": -57.6976942}, {"type": "node", "id": 6976850127, "lat": -3.414607, "lon": -57.6977558}, {"type": "node", "id": 6976850128, "lat": -3.4147074, "lon": -57.6977719}, {"type": "node", "id": 6976850129, "lat": -3.4149309, "lon": -57.6978725}, {"type": "node", "id": 6976850130, "lat": -3.4150086, "lon": -57.6979449}, {"type": "node", "id": 6976850131, "lat": -3.4152375, "lon": -57.6982065}, {"type": "node", "id": 6976850132, "lat": -3.4157837, "lon": -57.6986812}, {"type": "node", "id": 6978454767, "lat": -3.359861, "lon": -57.7002409}, {"type": "node", "id": 6978454768, "lat": -3.3596608, "lon": -57.7011388}, {"type": "node", "id": 6978454769, "lat": -3.3594453, "lon": -57.7016216}, {"type": "node", "id": 6978454770, "lat": -3.3594085, "lon": -57.7019931}, {"type": "node", "id": 6978454771, "lat": -3.3598998, "lon": -57.7001511}, {"type": "node", "id": 6978454772, "lat": -3.3598764, "lon": -57.700206}, {"type": "node", "id": 6978454773, "lat": -3.3598536, "lon": -57.7002805}, {"type": "node", "id": 6978454774, "lat": -3.3598469, "lon": -57.7003153}, {"type": "node", "id": 6978454775, "lat": -3.3598396, "lon": -57.7003831}, {"type": "node", "id": 6978454776, "lat": -3.3598268, "lon": -57.7004669}, {"type": "node", "id": 6978454777, "lat": -3.3597853, "lon": -57.7006902}, {"type": "node", "id": 6978454778, "lat": -3.3597311, "lon": -57.7009061}, {"type": "node", "id": 6978454779, "lat": -3.3596802, "lon": -57.7010804}, {"type": "node", "id": 6978454780, "lat": -3.3596314, "lon": -57.7011985}, {"type": "node", "id": 6978454781, "lat": -3.3595678, "lon": -57.7013185}, {"type": "node", "id": 6978454782, "lat": -3.3594875, "lon": -57.7014935}, {"type": "node", "id": 6978454783, "lat": -3.3594567, "lon": -57.7015813}, {"type": "node", "id": 6978454784, "lat": -3.3594379, "lon": -57.7016678}, {"type": "node", "id": 6978472385, "lat": -3.3594306, "lon": -57.7017463}, {"type": "node", "id": 6978472386, "lat": -3.3594285, "lon": -57.701818}, {"type": "node", "id": 6978472387, "lat": -3.3594225, "lon": -57.7019005}, {"type": "node", "id": 6978472388, "lat": -3.3593797, "lon": -57.7020869}, {"type": "node", "id": 6978472389, "lat": -3.3593184, "lon": -57.7023122}, {"type": "node", "id": 6978472390, "lat": -3.3592763, "lon": -57.7024608}, {"type": "node", "id": 6978472391, "lat": -3.3606997, "lon": -57.6983714}, {"type": "node", "id": 6978472392, "lat": -3.360681, "lon": -57.6985102}, {"type": "node", "id": 6978472393, "lat": -3.3606489, "lon": -57.6986135}, {"type": "node", "id": 6978472394, "lat": -3.3606281, "lon": -57.6986785}, {"type": "node", "id": 6978472395, "lat": -3.3606054, "lon": -57.6987758}, {"type": "node", "id": 6978472396, "lat": -3.360596, "lon": -57.698871}, {"type": "node", "id": 6978472397, "lat": -3.3605859, "lon": -57.6989897}, {"type": "node", "id": 6978472398, "lat": -3.3605612, "lon": -57.6990775}, {"type": "node", "id": 6978472399, "lat": -3.3605337, "lon": -57.6991325}, {"type": "node", "id": 6978472400, "lat": -3.3604922, "lon": -57.699213}, {"type": "node", "id": 6978472401, "lat": -3.360438, "lon": -57.6992988}, {"type": "node", "id": 6978472402, "lat": -3.3603838, "lon": -57.6993866}, {"type": "node", "id": 6978472403, "lat": -3.3603423, "lon": -57.6994497}, {"type": "node", "id": 6978472404, "lat": -3.3602526, "lon": -57.6995663}, {"type": "node", "id": 6978472405, "lat": -3.3601796, "lon": -57.6996736}, {"type": "node", "id": 6978472406, "lat": -3.3601093, "lon": -57.6998198}, {"type": "node", "id": 6978472407, "lat": -3.3600303, "lon": -57.6999613}, {"type": "node", "id": 6978472408, "lat": -3.359936, "lon": -57.7000954}, {"type": "node", "id": 6978472409, "lat": -3.3607272, "lon": -57.6982366}, {"type": "node", "id": 6978472410, "lat": -3.3609032, "lon": -57.6975916}, {"type": "node", "id": 6978472411, "lat": -3.3608832, "lon": -57.6977042}, {"type": "node", "id": 6978472412, "lat": -3.3608437, "lon": -57.6978772}, {"type": "node", "id": 6978472413, "lat": -3.3607935, "lon": -57.6980428}, {"type": "node", "id": 6978472414, "lat": -3.360916, "lon": -57.6974454}, {"type": "node", "id": 6978472415, "lat": -3.3609173, "lon": -57.6972791}, {"type": "node", "id": 6978472416, "lat": -3.3609139, "lon": -57.6971725}, {"type": "node", "id": 6978472417, "lat": -3.3609079, "lon": -57.6970296}, {"type": "node", "id": 6978472418, "lat": -3.3608985, "lon": -57.696974}, {"type": "node", "id": 6978472419, "lat": -3.3535472, "lon": -57.6977545}, {"type": "node", "id": 6978472420, "lat": -3.3532393, "lon": -57.6975426}, {"type": "node", "id": 6978472421, "lat": -3.3537775, "lon": -57.6979141}, {"type": "node", "id": 6978472422, "lat": -3.3541804, "lon": -57.6982427}, {"type": "node", "id": 6978472423, "lat": -3.3542996, "lon": -57.6983526}, {"type": "node", "id": 6978472424, "lat": -3.3545386, "lon": -57.6986021}, {"type": "node", "id": 6978472425, "lat": -3.3547427, "lon": -57.6988026}, {"type": "node", "id": 6978472426, "lat": -3.3550661, "lon": -57.6991425}, {"type": "node", "id": 6978472427, "lat": -3.3554818, "lon": -57.6995724}, {"type": "node", "id": 6978472428, "lat": -3.3559082, "lon": -57.7000498}, {"type": "node", "id": 6978472429, "lat": -3.3561719, "lon": -57.7003086}, {"type": "node", "id": 6978472430, "lat": -3.3565863, "lon": -57.7006607}, {"type": "node", "id": 6978472431, "lat": -3.3568734, "lon": -57.7008471}, {"type": "node", "id": 6978472432, "lat": -3.3571566, "lon": -57.7010389}, {"type": "node", "id": 6978472433, "lat": -3.3578508, "lon": -57.701521}, {"type": "node", "id": 6978472434, "lat": -3.3592321, "lon": -57.7025691}, {"type": "node", "id": 6978472435, "lat": -3.3597184, "lon": -57.7029707}, {"type": "node", "id": 6978472436, "lat": -3.3600852, "lon": -57.7032544}, {"type": "node", "id": 6978472437, "lat": -3.3604099, "lon": -57.7034978}, {"type": "node", "id": 6978472438, "lat": -3.3606187, "lon": -57.7036493}, {"type": "node", "id": 6978472439, "lat": -3.3609762, "lon": -57.7038478}, {"type": "node", "id": 6978472440, "lat": -3.3618478, "lon": -57.7042669}, {"type": "node", "id": 6978472441, "lat": -3.362649, "lon": -57.7046605}, {"type": "node", "id": 6978472442, "lat": -3.3629529, "lon": -57.7047946}, {"type": "node", "id": 6978472443, "lat": -3.3634777, "lon": -57.7049408}, {"type": "node", "id": 6978472444, "lat": -3.3640822, "lon": -57.7050461}, {"type": "node", "id": 6978472445, "lat": -3.364273, "lon": -57.7050722}, {"type": "node", "id": 6978472446, "lat": -3.3659886, "lon": -57.7052188}, {"type": "node", "id": 6978481183, "lat": -3.3390531, "lon": -57.6903234}, {"type": "node", "id": 6978481184, "lat": -3.3391509, "lon": -57.690479}, {"type": "node", "id": 6978481347, "lat": -3.350662, "lon": -57.6958139}, {"type": "node", "id": 6978481348, "lat": -3.3513944, "lon": -57.6962954}, {"type": "node", "id": 6978481349, "lat": -3.350978, "lon": -57.6960178}, {"type": "node", "id": 6978481350, "lat": -3.3517505, "lon": -57.6965395}, {"type": "node", "id": 6978481351, "lat": -3.3525324, "lon": -57.6970598}, {"type": "node", "id": 6978481352, "lat": -3.3487676, "lon": -57.692842}, {"type": "node", "id": 6978481353, "lat": -3.3488694, "lon": -57.6927562}, {"type": "node", "id": 6978481354, "lat": -3.3492161, "lon": -57.6925041}, {"type": "node", "id": 6978481355, "lat": -3.3494518, "lon": -57.6923364}, {"type": "node", "id": 6978481356, "lat": -3.3499458, "lon": -57.6919784}, {"type": "node", "id": 6978481357, "lat": -3.3504719, "lon": -57.6916203}, {"type": "node", "id": 6978481358, "lat": -3.3506567, "lon": -57.6914915}, {"type": "node", "id": 6978481359, "lat": -3.3510623, "lon": -57.6911992}, {"type": "node", "id": 6978481360, "lat": -3.3516153, "lon": -57.6907942}, {"type": "node", "id": 6978481361, "lat": -3.3525524, "lon": -57.690125}, {"type": "node", "id": 6978481362, "lat": -3.3529742, "lon": -57.6898313}, {"type": "node", "id": 6978481363, "lat": -3.3535686, "lon": -57.6893686}, {"type": "node", "id": 6978481364, "lat": -3.3538939, "lon": -57.6891714}, {"type": "node", "id": 6978481365, "lat": -3.3541148, "lon": -57.6890185}, {"type": "node", "id": 6978481366, "lat": -3.354159, "lon": -57.6889448}, {"type": "node", "id": 6978481367, "lat": -3.3542099, "lon": -57.6887745}, {"type": "node", "id": 6978481368, "lat": -3.3542112, "lon": -57.6886149}, {"type": "node", "id": 6978481369, "lat": -3.3541965, "lon": -57.6884459}, {"type": "node", "id": 6978481370, "lat": -3.354147, "lon": -57.6879363}, {"type": "node", "id": 6978481371, "lat": -3.3541537, "lon": -57.6878008}, {"type": "node", "id": 6978481372, "lat": -3.3542059, "lon": -57.6875433}, {"type": "node", "id": 6978481373, "lat": -3.3542608, "lon": -57.6873609}, {"type": "node", "id": 6978481374, "lat": -3.3543103, "lon": -57.6870418}, {"type": "node", "id": 6978481375, "lat": -3.3542608, "lon": -57.6867092}, {"type": "node", "id": 6978481376, "lat": -3.3541938, "lon": -57.6863444}, {"type": "node", "id": 6978481377, "lat": -3.3541229, "lon": -57.6857637}, {"type": "node", "id": 6978481378, "lat": -3.3540907, "lon": -57.6854955}, {"type": "node", "id": 6978481379, "lat": -3.3541336, "lon": -57.6852782}, {"type": "node", "id": 6978481380, "lat": -3.3542313, "lon": -57.6851763}, {"type": "node", "id": 6978481381, "lat": -3.3544361, "lon": -57.6851521}, {"type": "node", "id": 6978481382, "lat": -3.3545218, "lon": -57.6851669}, {"type": "node", "id": 6978481383, "lat": -3.3546637, "lon": -57.6851991}, {"type": "node", "id": 6978481384, "lat": -3.354799, "lon": -57.6852554}, {"type": "node", "id": 6978488385, "lat": -3.3392553, "lon": -57.6905809}, {"type": "node", "id": 6978488386, "lat": -3.3394374, "lon": -57.6907405}, {"type": "node", "id": 6978488387, "lat": -3.3398323, "lon": -57.6910128}, {"type": "node", "id": 6978488388, "lat": -3.3400091, "lon": -57.6911308}, {"type": "node", "id": 6978488389, "lat": -3.3403987, "lon": -57.6914594}, {"type": "node", "id": 6978488390, "lat": -3.340562, "lon": -57.6915492}, {"type": "node", "id": 6978488391, "lat": -3.3406517, "lon": -57.6915747}, {"type": "node", "id": 6978488392, "lat": -3.3408378, "lon": -57.6915693}, {"type": "node", "id": 6978488393, "lat": -3.3410118, "lon": -57.6915412}, {"type": "node", "id": 6978488394, "lat": -3.3413921, "lon": -57.6914084}, {"type": "node", "id": 6978488395, "lat": -3.3419343, "lon": -57.6912528}, {"type": "node", "id": 6978488396, "lat": -3.3423774, "lon": -57.6911107}, {"type": "node", "id": 6978488397, "lat": -3.3428393, "lon": -57.6909712}, {"type": "node", "id": 6978488398, "lat": -3.3434016, "lon": -57.6908599}, {"type": "node", "id": 6978488399, "lat": -3.3437993, "lon": -57.6908277}, {"type": "node", "id": 6978488400, "lat": -3.34447, "lon": -57.6907741}, {"type": "node", "id": 6978488401, "lat": -3.3447378, "lon": -57.6907338}, {"type": "node", "id": 6978488402, "lat": -3.34496, "lon": -57.6907124}, {"type": "node", "id": 6978488403, "lat": -3.3451528, "lon": -57.6906775}, {"type": "node", "id": 6978488404, "lat": -3.3457124, "lon": -57.6905112}, {"type": "node", "id": 6978488405, "lat": -3.3460391, "lon": -57.6904388}, {"type": "node", "id": 6978488406, "lat": -3.3464408, "lon": -57.6903945}, {"type": "node", "id": 6978488407, "lat": -3.3465532, "lon": -57.6904066}, {"type": "node", "id": 6978488408, "lat": -3.3468076, "lon": -57.6904924}, {"type": "node", "id": 6978488409, "lat": -3.3471303, "lon": -57.6908197}, {"type": "node", "id": 6978488410, "lat": -3.3473645, "lon": -57.6910973}, {"type": "node", "id": 6978488411, "lat": -3.3482147, "lon": -57.6921956}, {"type": "node", "id": 6978488412, "lat": -3.3489323, "lon": -57.6932766}, {"type": "node", "id": 6978488413, "lat": -3.3493393, "lon": -57.6939525}, {"type": "node", "id": 6978488414, "lat": -3.3497476, "lon": -57.6947464}, {"type": "node", "id": 6978488415, "lat": -3.3499418, "lon": -57.6951487}, {"type": "node", "id": 6978488416, "lat": -3.3499016, "lon": -57.6950736}, {"type": "node", "id": 6978488417, "lat": -3.3500997, "lon": -57.6953714}, {"type": "node", "id": 6978488418, "lat": -3.3501868, "lon": -57.6954599}, {"type": "node", "id": 6978489113, "lat": -3.3870824, "lon": -57.6751944}, {"type": "node", "id": 6978489114, "lat": -3.3872497, "lon": -57.6773268}, {"type": "node", "id": 6978489115, "lat": -3.3876808, "lon": -57.67892}, {"type": "node", "id": 6978489116, "lat": -3.387729, "lon": -57.6796845}, {"type": "node", "id": 6978489117, "lat": -3.3875175, "lon": -57.6807044}, {"type": "node", "id": 6978493185, "lat": -3.3549369, "lon": -57.6853091}, {"type": "node", "id": 6978493186, "lat": -3.35504, "lon": -57.6853158}, {"type": "node", "id": 6978493187, "lat": -3.3552354, "lon": -57.6852809}, {"type": "node", "id": 6978493188, "lat": -3.3554202, "lon": -57.6851669}, {"type": "node", "id": 6978493189, "lat": -3.3555447, "lon": -57.6849496}, {"type": "node", "id": 6978493190, "lat": -3.3556116, "lon": -57.6846305}, {"type": "node", "id": 6978493191, "lat": -3.3555835, "lon": -57.6844145}, {"type": "node", "id": 6978493192, "lat": -3.3555313, "lon": -57.6842093}, {"type": "node", "id": 6978493193, "lat": -3.3554188, "lon": -57.6838097}, {"type": "node", "id": 6978512788, "lat": -3.4136002, "lon": -57.684204}, {"type": "node", "id": 6978512789, "lat": -3.4138037, "lon": -57.6839384}, {"type": "node", "id": 6978512790, "lat": -3.4139831, "lon": -57.6836394}, {"type": "node", "id": 6978512791, "lat": -3.4146926, "lon": -57.6824981}, {"type": "node", "id": 6978512792, "lat": -3.414947, "lon": -57.6821548}, {"type": "node", "id": 6978512793, "lat": -3.415445, "lon": -57.6816666}, {"type": "node", "id": 6978512794, "lat": -3.4157716, "lon": -57.681444}, {"type": "node", "id": 6978512795, "lat": -3.4167489, "lon": -57.6807761}, {"type": "node", "id": 6978512796, "lat": -3.417113, "lon": -57.6804784}, {"type": "node", "id": 6978512797, "lat": -3.4176994, "lon": -57.6800573}, {"type": "node", "id": 6978512798, "lat": -3.4178975, "lon": -57.6799607}, {"type": "node", "id": 6978512799, "lat": -3.4197021, "lon": -57.6791239}, {"type": "node", "id": 6978512800, "lat": -3.4133941, "lon": -57.6665685}, {"type": "node", "id": 6978512801, "lat": -3.4136458, "lon": -57.6667213}, {"type": "node", "id": 6978512802, "lat": -3.413785, "lon": -57.6669493}, {"type": "node", "id": 6978512803, "lat": -3.4138251, "lon": -57.6670513}, {"type": "node", "id": 6978512804, "lat": -3.4140179, "lon": -57.6674563}, {"type": "node", "id": 6978512805, "lat": -3.4142857, "lon": -57.6678881}, {"type": "node", "id": 6978512806, "lat": -3.4144088, "lon": -57.6681188}, {"type": "node", "id": 6978512807, "lat": -3.4146016, "lon": -57.6687437}, {"type": "node", "id": 6978512808, "lat": -3.4147167, "lon": -57.6694143}, {"type": "node", "id": 6978512809, "lat": -3.4147917, "lon": -57.6700285}, {"type": "node", "id": 6978512810, "lat": -3.4148988, "lon": -57.6705274}, {"type": "node", "id": 6978512811, "lat": -3.4149416, "lon": -57.6706508}, {"type": "node", "id": 6978512812, "lat": -3.4151424, "lon": -57.6709351}, {"type": "node", "id": 6978512813, "lat": -3.4153165, "lon": -57.6711121}, {"type": "node", "id": 6978512814, "lat": -3.4155655, "lon": -57.6713723}, {"type": "node", "id": 6978512815, "lat": -3.4168506, "lon": -57.6728529}, {"type": "node", "id": 6978512816, "lat": -3.4174558, "lon": -57.6737112}, {"type": "node", "id": 6978512817, "lat": -3.4189658, "lon": -57.6760823}, {"type": "node", "id": 6978512818, "lat": -3.4197102, "lon": -57.6770639}, {"type": "node", "id": 6978512819, "lat": -3.4206365, "lon": -57.6783085}, {"type": "node", "id": 6978512820, "lat": -3.420508, "lon": -57.67811}, {"type": "node", "id": 6978512821, "lat": -3.4017016, "lon": -57.672928}, {"type": "node", "id": 6978512822, "lat": -3.4012999, "lon": -57.6738453}, {"type": "node", "id": 6978512823, "lat": -3.401059, "lon": -57.6745802}, {"type": "node", "id": 6978512824, "lat": -3.4007002, "lon": -57.6757819}, {"type": "node", "id": 6978512825, "lat": -3.4006574, "lon": -57.6763344}, {"type": "node", "id": 6978512826, "lat": -3.4006199, "lon": -57.6778203}, {"type": "node", "id": 6978512827, "lat": -3.4007377, "lon": -57.6791829}, {"type": "node", "id": 6978512828, "lat": -3.4009626, "lon": -57.6800948}, {"type": "node", "id": 6978512829, "lat": -3.4012303, "lon": -57.6808029}, {"type": "node", "id": 6978512830, "lat": -3.4016487, "lon": -57.6819275}, {"type": "node", "id": 6978512831, "lat": -3.4019854, "lon": -57.6828682}, {"type": "node", "id": 6978512832, "lat": -3.4019211, "lon": -57.6840967}, {"type": "node", "id": 6978512833, "lat": -3.4016641, "lon": -57.6848584}, {"type": "node", "id": 6978512834, "lat": -3.4011768, "lon": -57.6865375}, {"type": "node", "id": 6978514351, "lat": -3.3696917, "lon": -57.6876278}, {"type": "node", "id": 6978514352, "lat": -3.3698323, "lon": -57.6880369}, {"type": "node", "id": 6978514353, "lat": -3.3700224, "lon": -57.6886269}, {"type": "node", "id": 6978514354, "lat": -3.3702554, "lon": -57.6893418}, {"type": "node", "id": 6978514355, "lat": -3.3704776, "lon": -57.690023}, {"type": "node", "id": 6978514356, "lat": -3.3706624, "lon": -57.6905756}, {"type": "node", "id": 6978514357, "lat": -3.3707761, "lon": -57.6908612}, {"type": "node", "id": 6978514358, "lat": -3.3708739, "lon": -57.6910745}, {"type": "node", "id": 6978514359, "lat": -3.3710359, "lon": -57.6913534}, {"type": "node", "id": 6978514360, "lat": -3.3712206, "lon": -57.6915371}, {"type": "node", "id": 6978514361, "lat": -3.3717361, "lon": -57.6920857}, {"type": "node", "id": 6978514362, "lat": -3.3724992, "lon": -57.692956}, {"type": "node", "id": 6978514363, "lat": -3.3727067, "lon": -57.6931545}, {"type": "node", "id": 6978514364, "lat": -3.3731967, "lon": -57.6935448}, {"type": "node", "id": 6978514365, "lat": -3.3734778, "lon": -57.6937594}, {"type": "node", "id": 6978514366, "lat": -3.3737683, "lon": -57.6939719}, {"type": "node", "id": 6978514367, "lat": -3.3741593, "lon": -57.6942274}, {"type": "node", "id": 6978514368, "lat": -3.3744598, "lon": -57.6944098}, {"type": "node", "id": 6978514369, "lat": -3.3746486, "lon": -57.6945513}, {"type": "node", "id": 6978514370, "lat": -3.3747517, "lon": -57.6946498}, {"type": "node", "id": 6978514371, "lat": -3.3748581, "lon": -57.694796}, {"type": "node", "id": 6978514372, "lat": -3.3748882, "lon": -57.6948644}, {"type": "node", "id": 6978514373, "lat": -3.374907, "lon": -57.6949442}, {"type": "node", "id": 6978514374, "lat": -3.3749177, "lon": -57.6950528}, {"type": "node", "id": 6978514375, "lat": -3.3749016, "lon": -57.6951776}, {"type": "node", "id": 6978514376, "lat": -3.3748936, "lon": -57.6952151}, {"type": "node", "id": 6978514377, "lat": -3.3748655, "lon": -57.6953231}, {"type": "node", "id": 6978514378, "lat": -3.3748025, "lon": -57.6955497}, {"type": "node", "id": 6978514379, "lat": -3.3747222, "lon": -57.6958293}, {"type": "node", "id": 6978514380, "lat": -3.3746325, "lon": -57.6962008}, {"type": "node", "id": 6978514381, "lat": -3.3745468, "lon": -57.6965321}, {"type": "node", "id": 6978514382, "lat": -3.3744585, "lon": -57.6968573}, {"type": "node", "id": 6978514383, "lat": -3.3743842, "lon": -57.6971483}, {"type": "node", "id": 6978514384, "lat": -3.3743179, "lon": -57.6974199}, {"type": "node", "id": 6978525385, "lat": -3.374265, "lon": -57.6976667}, {"type": "node", "id": 6978525386, "lat": -3.3742295, "lon": -57.6978672}, {"type": "node", "id": 6978525387, "lat": -3.374186, "lon": -57.6980623}, {"type": "node", "id": 6978525388, "lat": -3.374174, "lon": -57.6982474}, {"type": "node", "id": 6978525389, "lat": -3.374178, "lon": -57.6985109}, {"type": "node", "id": 6978525390, "lat": -3.374186, "lon": -57.6986249}, {"type": "node", "id": 6978525391, "lat": -3.3742081, "lon": -57.698759}, {"type": "node", "id": 6978525392, "lat": -3.3742409, "lon": -57.6989152}, {"type": "node", "id": 6978525393, "lat": -3.3743487, "lon": -57.6993927}, {"type": "node", "id": 6978525394, "lat": -3.3743708, "lon": -57.6995979}, {"type": "node", "id": 6978525395, "lat": -3.3743688, "lon": -57.6996998}, {"type": "node", "id": 6978525396, "lat": -3.3743698, "lon": -57.6997749}, {"type": "node", "id": 6978525397, "lat": -3.3743212, "lon": -57.699917}, {"type": "node", "id": 6978525398, "lat": -3.3742255, "lon": -57.7001021}, {"type": "node", "id": 6978626250, "lat": -3.3728158, "lon": -57.7037499}, {"type": "node", "id": 6978626251, "lat": -3.3728914, "lon": -57.7032222}, {"type": "node", "id": 6978626252, "lat": -3.3729564, "lon": -57.7027045}, {"type": "node", "id": 6978626253, "lat": -3.3731023, "lon": -57.7021386}, {"type": "node", "id": 6978626254, "lat": -3.3733198, "lon": -57.7017322}, {"type": "node", "id": 6978626255, "lat": -3.3739035, "lon": -57.7007398}, {"type": "node", "id": 6978626256, "lat": -3.3743651, "lon": -57.6998121}, {"type": "node", "id": 6978626257, "lat": -3.3728017, "lon": -57.7039531}, {"type": "node", "id": 6978626258, "lat": -3.372961, "lon": -57.7048369}, {"type": "node", "id": 6978626259, "lat": -3.3731023, "lon": -57.7053478}, {"type": "node", "id": 6978626260, "lat": -3.3730246, "lon": -57.7061351}, {"type": "node", "id": 6978626261, "lat": -3.3732904, "lon": -57.706237}, {"type": "node", "id": 6978626262, "lat": -3.3724503, "lon": -57.7059909}, {"type": "node", "id": 6978626263, "lat": -3.371157, "lon": -57.7059842}, {"type": "node", "id": 6978626264, "lat": -3.370333, "lon": -57.7059862}, {"type": "node", "id": 6978626265, "lat": -3.3698658, "lon": -57.7059788}, {"type": "node", "id": 6978626266, "lat": -3.3691388, "lon": -57.7059319}, {"type": "node", "id": 6978626267, "lat": -3.368452, "lon": -57.7058025}, {"type": "node", "id": 6978626268, "lat": -3.3681682, "lon": -57.7057327}, {"type": "node", "id": 6978626269, "lat": -3.367539, "lon": -57.7055852}, {"type": "node", "id": 6978626270, "lat": -3.3662845, "lon": -57.7052761}, {"type": "node", "id": 6978841415, "lat": -3.4002825, "lon": -57.689496}, {"type": "node", "id": 6978841416, "lat": -3.3998621, "lon": -57.6910812}, {"type": "node", "id": 6978841417, "lat": -3.3878, "lon": -57.6835656}, {"type": "node", "id": 6978841418, "lat": -3.3879098, "lon": -57.684837}, {"type": "node", "id": 6979772179, "lat": -3.4013776, "lon": -57.6811972}, {"type": "node", "id": 6979772180, "lat": -3.4020483, "lon": -57.68306}, {"type": "node", "id": 6979772181, "lat": -3.4020818, "lon": -57.6834315}, {"type": "node", "id": 6979772182, "lat": -3.4005422, "lon": -57.688635}, {"type": "node", "id": 6979772183, "lat": -3.4078705, "lon": -57.6852594}, {"type": "node", "id": 6979772184, "lat": -3.4108344, "lon": -57.6849067}, {"type": "node", "id": 6979780820, "lat": -3.4033964, "lon": -57.6962096}, {"type": "node", "id": 6979780821, "lat": -3.4035263, "lon": -57.6962847}, {"type": "node", "id": 6979780822, "lat": -3.4048784, "lon": -57.6960942}, {"type": "node", "id": 6979780823, "lat": -3.4048235, "lon": -57.6961304}, {"type": "node", "id": 6979780824, "lat": -3.4047579, "lon": -57.6961599}, {"type": "node", "id": 6979780825, "lat": -3.4045959, "lon": -57.6961854}, {"type": "node", "id": 6979780826, "lat": -3.4044058, "lon": -57.6961868}, {"type": "node", "id": 6979780827, "lat": -3.4041515, "lon": -57.6962189}, {"type": "node", "id": 6979780828, "lat": -3.403632, "lon": -57.6962565}, {"type": "node", "id": 6979780829, "lat": -3.4035638, "lon": -57.6962619}, {"type": "node", "id": 6979780830, "lat": -3.4034901, "lon": -57.6963048}, {"type": "node", "id": 6979780831, "lat": -3.4034352, "lon": -57.6963745}, {"type": "node", "id": 6979780832, "lat": -3.4031528, "lon": -57.6967044}, {"type": "node", "id": 6979780833, "lat": -3.4049654, "lon": -57.6960174}, {"type": "node", "id": 6979780834, "lat": -3.4073604, "lon": -57.6959051}, {"type": "node", "id": 6979780835, "lat": -3.4069682, "lon": -57.6958515}, {"type": "node", "id": 6979780836, "lat": -3.406845, "lon": -57.6958488}, {"type": "node", "id": 6979780837, "lat": -3.4072011, "lon": -57.6958823}, {"type": "node", "id": 6979780838, "lat": -3.4097353, "lon": -57.6961988}, {"type": "node", "id": 6979780839, "lat": -3.409082, "lon": -57.6961251}, {"type": "node", "id": 6979780840, "lat": -3.4098558, "lon": -57.6962632}, {"type": "node", "id": 6979780841, "lat": -3.4099, "lon": -57.6963168}, {"type": "node", "id": 6979780842, "lat": -3.4099924, "lon": -57.6964737}, {"type": "node", "id": 6979780843, "lat": -3.4100044, "lon": -57.696573}, {"type": "node", "id": 6979780844, "lat": -3.4011821, "lon": -57.6969552}, {"type": "node", "id": 6979780845, "lat": -3.3996615, "lon": -57.6971586}, {"type": "node", "id": 6979780846, "lat": -3.4002004, "lon": -57.6970824}, {"type": "node", "id": 6979780847, "lat": -3.4031126, "lon": -57.6962739}, {"type": "node", "id": 6979782634, "lat": -3.4041677, "lon": -57.6956723}, {"type": "node", "id": 6979782635, "lat": -3.4011955, "lon": -57.6928108}, {"type": "node", "id": 6979782636, "lat": -3.4014683, "lon": -57.692982}, {"type": "node", "id": 6979782637, "lat": -3.4015314, "lon": -57.6929983}, {"type": "node", "id": 6979782638, "lat": -3.401524, "lon": -57.6929835}, {"type": "node", "id": 6979782639, "lat": -3.4015128, "lon": -57.692975}, {"type": "node", "id": 6979782640, "lat": -3.4014954, "lon": -57.6929711}, {"type": "node", "id": 6979782641, "lat": -3.4014812, "lon": -57.6929745}, {"type": "node", "id": 6979782642, "lat": -3.4015746, "lon": -57.6931534}, {"type": "node", "id": 6979782643, "lat": -3.4016443, "lon": -57.6934788}, {"type": "node", "id": 6979782644, "lat": -3.4017237, "lon": -57.693791}, {"type": "node", "id": 6979782645, "lat": -3.4014613, "lon": -57.6929996}, {"type": "node", "id": 6979782646, "lat": -3.4008849, "lon": -57.694615}, {"type": "node", "id": 6979782651, "lat": -3.4039172, "lon": -57.6933905}, {"type": "node", "id": 6979782652, "lat": -3.4091516, "lon": -57.6946187}, {"type": "node", "id": 6979782653, "lat": -3.409153, "lon": -57.6946515}, {"type": "node", "id": 6979782654, "lat": -3.408256, "lon": -57.6914634}, {"type": "node", "id": 6979782655, "lat": -3.4083779, "lon": -57.691505}, {"type": "node", "id": 6979782656, "lat": -3.4043951, "lon": -57.6917531}, {"type": "node", "id": 6979782657, "lat": -3.404213, "lon": -57.6917249}, {"type": "node", "id": 6979782658, "lat": -3.4040765, "lon": -57.6917276}, {"type": "node", "id": 6979782659, "lat": -3.4039948, "lon": -57.6917517}, {"type": "node", "id": 6979782660, "lat": -3.4039185, "lon": -57.6917933}, {"type": "node", "id": 6979782661, "lat": -3.4045852, "lon": -57.6917866}, {"type": "node", "id": 6979782662, "lat": -3.4065317, "lon": -57.6915894}, {"type": "node", "id": 6979782663, "lat": -3.4058356, "lon": -57.6916337}, {"type": "node", "id": 6979782664, "lat": -3.4069253, "lon": -57.6915573}, {"type": "node", "id": 6979782665, "lat": -3.4087594, "lon": -57.6912864}, {"type": "node", "id": 6979782666, "lat": -3.4088946, "lon": -57.6912756}, {"type": "node", "id": 6979782667, "lat": -3.4092467, "lon": -57.691348}, {"type": "node", "id": 6979782668, "lat": -3.4095412, "lon": -57.6914473}, {"type": "node", "id": 6979782669, "lat": -3.4097407, "lon": -57.6914956}, {"type": "node", "id": 6979782670, "lat": -3.4104515, "lon": -57.691576}, {"type": "node", "id": 6979782671, "lat": -3.4108237, "lon": -57.6916699}, {"type": "node", "id": 6979782672, "lat": -3.4110152, "lon": -57.6917504}, {"type": "node", "id": 6979782673, "lat": -3.4113967, "lon": -57.6920226}, {"type": "node", "id": 6979782674, "lat": -3.4122615, "lon": -57.6929051}, {"type": "node", "id": 6979782675, "lat": -3.412635, "lon": -57.6933745}, {"type": "node", "id": 6979782676, "lat": -3.4132589, "lon": -57.6947585}, {"type": "node", "id": 6979782677, "lat": -3.4135547, "lon": -57.6955175}, {"type": "node", "id": 6979782678, "lat": -3.4140179, "lon": -57.6975386}, {"type": "node", "id": 6979782679, "lat": -3.4122347, "lon": -57.6955216}, {"type": "node", "id": 6979782680, "lat": -3.4125868, "lon": -57.6957683}, {"type": "node", "id": 6979782681, "lat": -3.4127943, "lon": -57.6959842}, {"type": "node", "id": 6979782682, "lat": -3.4129576, "lon": -57.6961988}, {"type": "node", "id": 6979782683, "lat": -3.4112628, "lon": -57.6944178}, {"type": "node", "id": 6979782684, "lat": -3.4117314, "lon": -57.6950321}, {"type": "node", "id": 6979787185, "lat": -3.4091021, "lon": -57.6919046}, {"type": "node", "id": 6979787186, "lat": -3.4097152, "lon": -57.6922667}, {"type": "node", "id": 6979787187, "lat": -3.410149, "lon": -57.6926047}, {"type": "node", "id": 6979787188, "lat": -3.4058905, "lon": -57.6960781}, {"type": "node", "id": 6979787189, "lat": -3.4064461, "lon": -57.6964308}, {"type": "node", "id": 6979787190, "lat": -3.406936, "lon": -57.6967956}, {"type": "node", "id": 6979787191, "lat": -3.4072346, "lon": -57.6970571}, {"type": "node", "id": 6979800664, "lat": -3.4146096, "lon": -57.6840766}, {"type": "node", "id": 6979800665, "lat": -3.4153138, "lon": -57.6846546}, {"type": "node", "id": 6979800666, "lat": -3.4158426, "lon": -57.6851253}, {"type": "node", "id": 6979800667, "lat": -3.4162281, "lon": -57.6854633}, {"type": "node", "id": 6979800668, "lat": -3.4165012, "lon": -57.6856993}, {"type": "node", "id": 6979800669, "lat": -3.4166806, "lon": -57.6859058}, {"type": "node", "id": 6979800670, "lat": -3.4170394, "lon": -57.6864409}, {"type": "node", "id": 6979801786, "lat": -3.4005487, "lon": -57.6934766}, {"type": "node", "id": 6979803300, "lat": -3.4000255, "lon": -57.6926154}, {"type": "node", "id": 6979803301, "lat": -3.4006841, "lon": -57.6926838}, {"type": "node", "id": 6979803302, "lat": -3.402051, "lon": -57.6927079}, {"type": "node", "id": 6979803303, "lat": -3.4024566, "lon": -57.6926543}, {"type": "node", "id": 6979803304, "lat": -3.402711, "lon": -57.6926087}, {"type": "node", "id": 6979803305, "lat": -3.4031461, "lon": -57.6924585}, {"type": "node", "id": 6979811785, "lat": -3.412556, "lon": -57.6846895}, {"type": "node", "id": 6979811786, "lat": -3.407011, "lon": -57.6854324}, {"type": "node", "id": 6979811787, "lat": -3.4059588, "lon": -57.6857328}, {"type": "node", "id": 6979811788, "lat": -3.401565, "lon": -57.6875326}, {"type": "node", "id": 6979811789, "lat": -3.4030617, "lon": -57.6869506}, {"type": "node", "id": 6992437943, "lat": -3.3983042, "lon": -57.7045304}, {"type": "node", "id": 6992437944, "lat": -3.3981646, "lon": -57.704232}, {"type": "node", "id": 6992473196, "lat": -3.3974327, "lon": -57.6982086}, {"type": "node", "id": 6992473197, "lat": -3.396038, "lon": -57.6991244}, {"type": "node", "id": 6992473198, "lat": -3.3936544, "lon": -57.7006774}, {"type": "node", "id": 6992473199, "lat": -3.3974139, "lon": -57.698215}, {"type": "node", "id": 6992473200, "lat": -3.3973798, "lon": -57.6982329}, {"type": "node", "id": 6992473201, "lat": -3.3973185, "lon": -57.6982692}, {"type": "node", "id": 6992473202, "lat": -3.3902514, "lon": -57.7028458}, {"type": "node", "id": 6992473203, "lat": -3.3900739, "lon": -57.7028561}, {"type": "node", "id": 6992955892, "lat": -3.3881434, "lon": -57.7008997}, {"type": "node", "id": 6992955893, "lat": -3.399334, "lon": -57.7063781}, {"type": "node", "id": 6992955894, "lat": -3.3992992, "lon": -57.7063161}, {"type": "node", "id": 6992955895, "lat": -3.397355, "lon": -57.6992244}, {"type": "node", "id": 6992955896, "lat": -3.3973306, "lon": -57.6994745}, {"type": "node", "id": 6993245743, "lat": -3.397358, "lon": -57.6998198}, {"type": "node", "id": 7307453508, "lat": -3.4050752, "lon": -57.6920468}, {"type": "node", "id": 7307453509, "lat": -3.4046254, "lon": -57.692138}, {"type": "node", "id": 7307453510, "lat": -3.4048797, "lon": -57.6926529}, {"type": "node", "id": 7307453511, "lat": -3.405665, "lon": -57.6925128}, {"type": "node", "id": 11023555736, "lat": -3.4095062, "lon": -57.6959849}, {"type": "node", "id": 11023555737, "lat": -3.4083581, "lon": -57.6955472}, {"type": "node", "id": 11023555738, "lat": -3.4079983, "lon": -57.6956116}, {"type": "node", "id": 11023555739, "lat": -3.4070807, "lon": -57.6958664}, {"type": "node", "id": 11023673305, "lat": -3.396389, "lon": -57.69889}, {"type": "way", "id": 278978310, "nodes": [6947015961, 2832539846, 2832539831, 2832365499, 2832537388, 2832539852, 2832539853, 2832539841, 2832537398, 2838013919, 2838010100, 6992955893, 6992955894, 4895889254, 4895889258, 2838106340, 2838013959, 6992437943, 2838108031, 6992437944, 2838013969, 2838106399, 4895889261, 2838106354, 2838013927, 6993245743, 2838013953, 6992955896, 3226745043, 6992955895, 3226745041, 2838013987], "tags": {"highway": "residential", "name": "Estrada dos Moraes", "oneway": "no"}}, {"type": "way", "id": 279578962, "nodes": [4895889172, 2838013990, 2838013950, 6979801786, 4895889213], "tags": {"highway": "residential", "name": "Rua Japiim", "oneway": "no"}}, {"type": "way", "id": 279578964, "nodes": [2838013928, 2838013932, 2838010098, 3692623985, 2838013908, 2838013918, 2838013931, 4895889188, 2838014001, 2844358215], "tags": {"highway": "residential", "name": "Rua Acau\u00e3", "oneway": "no"}}, {"type": "way", "id": 279578965, "nodes": [2838013989, 2838013931, 2838013947], "tags": {"highway": "residential"}}, {"type": "way", "id": 279578966, "nodes": [2838013961, 2838016531, 2838016541, 2838013985, 2838016533, 2838013930, 7307453511, 2838013933], "tags": {"highway": "residential", "name": "Rua Bem-te-vi", "oneway": "no"}}, {"type": "way", "id": 279578967, "nodes": [2838013991, 2838013932, 2838014000], "tags": {"highway": "residential", "name": "Rua Curi\u00f3", "oneway": "no"}}, {"type": "way", "id": 279578968, "nodes": [2838013935, 6992473203, 4895889259, 2838013975, 6992955892, 3228025606, 2838013968, 3228025630, 2838013951, 3228010572, 3228010579, 3228025609, 2838013994, 3228068474, 2838013960, 3228183459, 2838063751, 2838063737, 3228010577, 3228008459, 3228010574, 2838063801, 3228213762, 2838063748, 3228010567, 3228010570, 2838063744, 3228010561, 3228010563, 3228008460, 3228008458, 2838063712, 3228010565, 3228010566, 2838063746, 3228010576, 3228010568, 2838063701, 3228010573, 6978841418, 2838063197, 3228010575, 6978841417, 3228008457, 2838063176, 3228010564, 3228010578, 2838063160, 6978489117, 2838063152, 6978489116, 3228010569, 3228010562, 6978489115, 3228211352, 2838063788, 6978489114, 3228010571, 3228025625, 6978489113, 2838063730], "tags": {"highway": "unclassified", "name": "Estrada do Bacabal"}}, {"type": "way", "id": 279578969, "nodes": [2838014002, 3692623985, 2838013984, 2838010099, 2844429462, 4895889212, 2844429461], "tags": {"highway": "residential", "name": "Rua Caure", "oneway": "no"}}, {"type": "way", "id": 279578970, "nodes": [4895889187, 4895889190, 2838014001, 4895889193, 4895889186, 4895889194, 2838016543, 4895889196, 2838013905, 4895889198, 4895889200, 4895889209], "tags": {"highway": "residential", "name": "Rua Gar\u00e7a Real", "oneway": "no"}}, {"type": "way", "id": 279578972, "nodes": [2844358216, 4895889203, 6979782651, 2838013905, 4895889202, 4895889204, 6979782644, 2838013978, 4895889210, 2838013990, 4895889217, 4895889215, 2838010099, 2838013956], "tags": {"highway": "residential", "name": "Rua Araras", "oneway": "no"}}, {"type": "way", "id": 279578973, "nodes": [2838013938, 6978512821, 2838013976, 6978512822, 6978512823, 2838013962, 6978512824, 6978512825, 2838013937, 6978512826, 2838013924, 6978512827, 2838013921, 6978512828, 6978512829, 6979772179, 6978512830, 6978512831, 6979772180, 2838013957, 6979772181, 2838013971, 2838013979, 6978512832, 6978512833, 6978512834, 2838013997, 6979772182, 6978841415, 6978841416, 2838013914], "tags": {"highway": "unclassified"}}, {"type": "way", "id": 279578974, "nodes": [4477281158, 4477281157, 4477281156, 4477281155, 4477281154, 4477281153, 4477281152, 4477281151, 4477281150, 4477281149, 4477281148, 4477281147, 4477281146, 4477281145, 4477281144, 4477281143, 4477281142, 4477281141, 4477281140, 4477281139, 4477281138, 4477281137, 4477281136, 4477281135, 4477281134, 4477281133, 4477281127, 4477281117, 4477281114, 4477281108, 4477281097, 4477281094, 4477281093, 4477281095, 4477281100, 4477281103, 4477281102, 4477281101, 4477281106, 4477281105, 4477281098, 4477281099, 4477281112, 4477281107, 4477281087, 4477281085, 4477281083, 4477281078, 4477281076, 4477281075, 4477281074, 4477281073, 4477281072, 4477281071, 4477281069, 4477281066, 4477281065, 4477281052, 4477281051, 4477281050, 4477281049, 4477281045, 4477281043, 4477281042, 4477281041, 2838013940, 2838013967, 2838013993, 2838013986, 6978512799, 2838013972, 2838013992, 6978512798, 6978512797, 2838013903, 6978512796, 6978512795, 2838013943, 6978512794, 6978512793, 2838010083, 6978512792, 6978512791, 2838013981, 6978512790, 6978512789, 6978512788, 2838013980, 2838010090, 2838010085, 6979811785, 6979772184, 2838013946, 6979772183, 2838013958, 6979811786, 6979811787, 2838010092, 2838013942, 6979811789, 6979811788, 2838013997], "tags": {"highway": "unclassified"}}, {"type": "way", "id": 279578975, "nodes": [2838013945, 2838013918, 2838010091, 4895889173, 2838013978], "tags": {"highway": "residential", "name": "Rua Uirapuru", "oneway": "no"}}, {"type": "way", "id": 279578976, "nodes": [2838013954, 6976850132, 2838013965, 6976850131, 2838013964, 6976850130, 6976850129, 2838013926, 6976850128, 6976850127, 2838013952, 6976850126, 6976850125, 6976850124, 6979782678, 2838013904, 2838013902, 6979782677, 6979782676, 2838010095, 6979782675, 6979782674, 2838013934, 6979782673, 2838013907, 6979782672, 6979782671, 2838013988, 6979782670, 2838013912, 6979782669, 6979782668, 6979782667, 2838013974, 6979782666, 6979782665, 2838010086], "tags": {"highway": "residential"}}, {"type": "way", "id": 279578977, "nodes": [2838013936, 4895889177, 4895889182, 2838013985], "tags": {"highway": "residential", "name": "Rua Gavi\u00e3o Real", "oneway": "no"}}, {"type": "way", "id": 279578978, "nodes": [2838013963, 2838013901, 2838013906, 2838013915, 6979780843, 6979780842, 2838013955, 6979780841, 6979780840, 2838013939, 6979780838, 6979780839, 2838013911, 4895889174, 2838013996, 6979780834, 6979780837, 11023555739, 6979780835, 6979780836, 2838013982, 2838013961, 2838013966, 2844358214, 6979780833, 4895889189, 2838013929, 6979780820, 6979780847, 2838013970, 2838013995, 4895889171, 6979780844, 2838010087, 6979780846, 6979780845, 2838010094, 2838013916], "tags": {"alt_name": "Estrada Guaranipoles", "highway": "residential", "name": "Estrada Guaranopoles"}}, {"type": "way", "id": 279578979, "nodes": [2838013999, 2838013991, 2838014002, 2838013973, 2838013945, 2838013989], "tags": {"highway": "residential", "name": "Rua Jacarand\u00e1", "oneway": "no"}}, {"type": "way", "id": 279579257, "nodes": [2838013936, 2838016518, 2838016540, 2838016525], "tags": {"highway": "residential", "name": "Rua Tucano"}}, {"type": "way", "id": 279579258, "nodes": [2838016512, 2838016538, 2838016529, 6979782682, 6979782681, 6979782680, 2838016542, 6979782679, 2838016522, 6979782684, 2838016524, 6979782683, 2838016516, 2838016528, 2838016539, 6979787187, 2838016537, 6979787186, 6979787185, 2838016525], "tags": {"highway": "residential"}}, {"type": "way", "id": 279579260, "nodes": [2838016530, 2838016511, 6976290005, 6976290004, 2838016513, 6976290003, 6976290002, 6976290001, 2838016515, 6976290000, 6976289999, 2838016535, 6976289998, 6976289997, 6976289996, 2838016536, 2838016534, 6976289995, 6976289994, 2838016523, 2838016517, 6976289993, 6976289992, 2838016526, 6979787191, 6979787190, 6979787189, 2838016519, 2838016520, 6979787188, 2838013966], "tags": {"highway": "residential"}}, {"type": "way", "id": 279579262, "nodes": [2838016518, 4895889178, 4895889183, 2838016533, 2844358212], "tags": {"highway": "residential", "name": "Rua Andorinha", "oneway": "no"}}, {"type": "way", "id": 279585287, "nodes": [2838063188, 6978514351, 6978514352, 6978514353, 6978514354, 6978514355, 6978514356, 6978514357, 6978514358, 2838063774, 6978514359, 6978514360, 6978514361, 2838063765, 6978514362, 6978514363, 2838063763, 6978514364, 6978514365, 6978514366, 6978514367, 6978514368, 6978514369, 6978514370, 2838063180, 6978514371, 6978514372, 6978514373, 6978514374, 2838063741, 6978514375, 6978514376, 6978514377, 6978514378, 6978514379, 6978514380, 6978514381, 6978514382, 6978514383, 6978514384, 6978525385, 6978525386, 6978525387, 6978525388, 2838063191, 6978525389, 6978525390, 6978525391, 6978525392, 3226830438, 6978525393, 3226830440, 6978525394, 6978525395, 6978525396, 6978626256, 2838063169, 6978525397, 6978525398, 6978626255, 6978626254, 6978626253, 3226830432, 3226830442, 2838063791, 6978626252, 6978626251, 3226830425, 6978626250, 6978626257, 3226830422, 2838063771, 6978626258, 6978626259, 2838063784, 2838063770], "tags": {"highway": "unclassified"}}, {"type": "way", "id": 279585293, "nodes": [2838063727, 6978481183, 6978481184, 6978488385, 6978488386, 2838063795, 6978488387, 6978488388, 2838063743, 6978488389, 6978488390, 6978488391, 2838063170, 6978488392, 6978488393, 6978488394, 6978488395, 6978488396, 6978488397, 2838063168, 6978488398, 6978488399, 2838063161, 6978488400, 6978488401, 6978488402, 6978488403, 2838063752, 6978488404, 6978488405, 2838063750, 6978488406, 6978488407, 5092999244, 6978488408, 2838063747, 6978488409, 6978488410, 5092999245, 6978488411, 2838063184, 6978488412, 6978488413, 2838063175, 6978488414, 6978488416, 6978488415, 2838063778, 6978488417, 6978488418, 2838063728, 6978481347, 6978481349, 6978481348, 6978481350, 6978481351, 6978472420, 6978472419, 6978472421, 2838063736, 6978472422, 6978472423, 6978472424, 6978472425, 3226830451, 6978472426, 6978472427, 6978472428, 6978472429, 2838063190, 6978472430, 6978472431, 6978472432, 3226830423, 6978472433, 3226830434, 2838063185, 6978472434, 6978472435, 6978472436, 6978472437, 6978472438, 2838063789, 6978472439, 3226830427, 6978472440, 3226830437, 6978472441, 6978472442, 2838063783, 6978472443, 3226830426, 3226830446, 6978472444, 6978472445, 2838063769, 3226830430, 6978472446, 6978626270, 2838063786, 3226830435, 6978626269, 3226830418, 6978626268, 6978626267, 3226830441, 6978626266, 2838063711, 6978626265, 6978626264, 3226830439, 6978626263, 2838063705, 3226830433, 6978626262, 3226830420, 2838063154, 6978626260, 6978626261, 2838063770], "tags": {"highway": "unclassified"}}, {"type": "way", "id": 280295138, "nodes": [2844358214, 2844358213, 4895889191, 2844358215, 4895889192, 2844358211, 4895889195, 2844358212, 4895889197, 2844358216], "tags": {"highway": "residential", "name": "Rua Beija-flor", "oneway": "no"}}, {"type": "way", "id": 280297662, "nodes": [2838010096, 6979803305, 2838010088, 6979803304, 6979803303, 6979803302, 2838010084, 2844429465, 6979803301, 6979803300, 2838013914], "tags": {"highway": "residential", "name": "Estrada S\u00e3o Paulo"}}, {"type": "way", "id": 280301525, "nodes": [2844429466, 2844429461, 2844429464, 6979782635], "tags": {"highway": "residential"}}, {"type": "way", "id": 280301526, "nodes": [2844429462, 2838013950, 2844429463, 6979782643], "tags": {"highway": "residential", "name": "Rua Juruti", "oneway": "no"}}, {"type": "way", "id": 450822579, "nodes": [2838013986, 6978512819, 6978512820, 6978512818, 6978512817, 4477281025, 6978512816, 6978512815, 4477281024, 6978512814, 6978512813, 6978512812, 4477281023, 6978512811, 6978512810, 4477281022, 6978512809, 4477281021, 6978512808, 4477281020, 6978512807, 4477281019, 6978512806, 6978512805, 4477281018, 6978512804, 4477281017, 6978512803, 6978512802, 4477281016, 6978512801, 4477281015, 6978512800, 4477281014], "tags": {"highway": "unclassified"}}, {"type": "way", "id": 450822581, "nodes": [4477281040, 4477281036, 4477281033, 4477281035, 4477281037, 4477281039, 4477281038, 4477281034, 4477281032, 4477281031, 4477281030, 4477281029, 4477281028, 4477281027, 4477281026, 2838013992], "tags": {"highway": "unclassified"}}, {"type": "way", "id": 450822588, "nodes": [4477281042, 4477281044, 4477281046, 4477281047, 4477281048, 4477281053, 4477281054, 4477281058, 4477281062, 4477281059, 4477281061, 4477281064, 4477281063, 4477281057, 4477281055, 4477281056, 4477281060, 4477281067, 4477281068, 4477281070, 4477281077, 4477281086, 4477281089, 4477281092, 4477281094], "tags": {"highway": "unclassified"}}, {"type": "way", "id": 450822591, "nodes": [4477281114, 4477281109, 4477281111, 4477281113, 4477281115, 4477281119, 4477281121, 4477281122, 4477281124, 4477281126, 4477281129, 4477281131, 4477281132, 4477281130, 4477281128, 4477281125, 4477281123, 4477281120, 4477281118, 4477281116, 4477281110, 4477281104, 4477281096, 4477281091, 4477281090, 4477281088, 4477281084, 4477281081, 4477281079, 4477281080, 4477281082], "tags": {"highway": "unclassified"}}, {"type": "way", "id": 498100483, "nodes": [4895889172, 6979782646, 4895889211, 4895889173], "tags": {"highway": "residential", "name": "Rua Andorinha"}}, {"type": "way", "id": 498100484, "nodes": [4895889175, 4895889176, 4895889177, 4895889178, 4895889179], "tags": {"highway": "residential"}}, {"type": "way", "id": 498100485, "nodes": [4895889180, 4895889181, 4895889182, 4895889183, 4895889184], "tags": {"highway": "residential"}}, {"type": "way", "id": 498100486, "nodes": [2838013947, 2838010091, 2838013941, 2838013984, 2838014000, 2838010093], "tags": {"highway": "residential", "name": "Rua Gavi\u00e3o Real", "oneway": "no"}}, {"type": "way", "id": 498100487, "nodes": [2838016531, 4895889180, 4895889175, 2838016532], "tags": {"highway": "residential", "name": "Rua Jacarand\u00e1", "oneway": "no"}}, {"type": "way", "id": 498100488, "nodes": [4895889188, 6979782634, 4895889189], "tags": {"highway": "residential", "name": "Avenida Gar\u00e7a Real"}}, {"type": "way", "id": 498100489, "nodes": [4895889190, 4895889191], "tags": {"highway": "residential"}}, {"type": "way", "id": 498100490, "nodes": [4895889192, 4895889193], "tags": {"highway": "residential"}}, {"type": "way", "id": 498100491, "nodes": [4895889194, 4895889195], "tags": {"highway": "residential"}}, {"type": "way", "id": 498100492, "nodes": [4895889196, 4895889197], "tags": {"highway": "residential"}}, {"type": "way", "id": 498100493, "nodes": [4895889198, 4895889199], "tags": {"highway": "residential"}}, {"type": "way", "id": 498100494, "nodes": [4895889200, 4895889201], "tags": {"highway": "residential"}}, {"type": "way", "id": 498100495, "nodes": [4895889204, 4895889206, 4895889208, 4895889205], "tags": {"highway": "residential", "name": "Rua E"}}, {"type": "way", "id": 498100496, "nodes": [4895889206, 4895889207], "tags": {"highway": "residential", "name": "Rua 4"}}, {"type": "way", "id": 498100497, "nodes": [4895889208, 4895889209], "tags": {"highway": "residential", "name": "Rua 3"}}, {"type": "way", "id": 498100498, "nodes": [4895889210, 4895889211], "tags": {"highway": "residential"}}, {"type": "way", "id": 498100499, "nodes": [4895889212, 4895889213, 4895889214, 6979782642], "tags": {"highway": "residential"}}, {"type": "way", "id": 498100500, "nodes": [4895889215, 4895889216], "tags": {"highway": "residential"}}, {"type": "way", "id": 498100501, "nodes": [4895889217, 4895889218], "tags": {"highway": "residential"}}, {"type": "way", "id": 523057065, "nodes": [2838063184, 6978481352, 6978481353, 5092999269, 6978481354, 6978481355, 6978481356, 5092999268, 6978481357, 6978481358, 6978481359, 6978481360, 5092999267, 6978481361, 6978481362, 5092999266, 6978481363, 5092999265, 6978481364, 5092999264, 6978481365, 6978481366, 5092999263, 6978481367, 6978481368, 6978481369, 5092999262, 6978481370, 6978481371, 5092999261, 6978481372, 6978481373, 5092999260, 6978481374, 5092999259, 6978481375, 5092999258, 6978481376, 5092999257, 6978481377, 5092999256, 6978481378, 5092999255, 6978481379, 5092999254, 6978481380, 5092999253, 6978481381, 6978481382, 6978481383, 6978481384, 6978493185, 6978493186, 5092999252, 6978493187, 5092999251, 6978493188, 5092999250, 6978493189, 5092999249, 6978493190, 5092999248, 6978493191, 6978493192, 6978493193, 5092999247, 5092999246], "tags": {"highway": "unclassified"}}, {"type": "way", "id": 745325028, "nodes": [2838106356, 6976849327, 6976849326, 6976849325, 6976849324, 6976849323, 6976849322, 6976849321, 6976849320, 6976849319, 6976849318, 6976849317, 6976849316, 6976849315, 6976849314, 6976849313, 6976849312, 6976849311, 6976849310, 6976849309, 6976849308, 6976849307, 6976849306, 6976849305, 6976849304, 6976849329, 6976849303, 6976849328, 6976849331, 6976849302, 6976849301, 6976849330, 6976849300, 6976849299, 6976849298, 6979780832, 6979780831, 6979780830, 6979780821, 6979780829, 6979780828, 6979780827, 6979780826, 6979780825, 6979780824, 6979780823, 6979780822, 6979780833], "tags": {"highway": "unclassified"}}, {"type": "way", "id": 745511706, "nodes": [6978472434, 6978472390, 6978472389, 6978472388, 6978454770, 6978472387, 6978472386, 6978472385, 6978454784, 6978454769, 6978454783, 6978454782, 6978454781, 6978454780, 6978454768, 6978454779, 6978454778, 6978454777, 6978454776, 6978454775, 6978454774, 6978454773, 6978454767, 6978454772, 6978454771, 6978472408, 6978472407, 6978472406, 6978472405, 6978472404, 6978472403, 6978472402, 6978472401, 6978472400, 6978472399, 6978472398, 6978472397, 6978472396, 6978472395, 6978472394, 6978472393, 6978472392, 6978472391, 6978472409, 6978472413, 6978472412, 6978472411, 6978472410, 6978472414, 6978472415, 6978472416, 6978472417, 6978472418], "tags": {"highway": "unclassified"}}, {"type": "way", "id": 745514770, "nodes": [2838013987, 2838013916, 2838013999, 2838013928, 2838010093, 2838013920], "tags": {"highway": "residential", "name": "Estrada dos Moraes", "oneway": "no"}}, {"type": "way", "id": 745703610, "nodes": [2838013989, 6979782634], "tags": {"highway": "residential", "name": "Rua Jacana"}}, {"type": "way", "id": 745703611, "nodes": [6979782644, 6979782643, 6979782642, 6979782637, 6979782638, 6979782639, 6979782640, 6979782641, 6979782636, 6979782645], "tags": {"highway": "residential", "name": "Rua Uirapuru", "oneway": "yes"}}, {"type": "way", "id": 745703612, "nodes": [6979782645, 4895889214, 2844429463, 2838013978], "tags": {"highway": "residential", "name": "Rua Uirapuru", "oneway": "yes"}}, {"type": "way", "id": 745703613, "nodes": [2838013973, 2838013908, 2838013941, 4895889172], "tags": {"highway": "residential", "name": "Rua Japiim", "oneway": "no"}}, {"type": "way", "id": 745706159, "nodes": [4895889186, 2838013947], "tags": {"highway": "residential", "name": "Rua Gavi\u00e3o Real", "oneway": "no"}}, {"type": "way", "id": 745706161, "nodes": [2838013930, 2844358216], "tags": {"highway": "residential", "name": "Rua Araras", "oneway": "no"}}, {"type": "way", "id": 745706162, "nodes": [4895889184, 2838013930], "tags": {"highway": "residential", "name": "Rua Araras", "oneway": "no"}}, {"type": "way", "id": 745706163, "nodes": [2844358213, 2838016531], "tags": {"highway": "residential", "name": "Rua Jacarand\u00e1", "oneway": "no"}}, {"type": "way", "id": 745706164, "nodes": [2838016525, 6979782655, 6979782654, 2838010086, 2838013977, 2838013949, 6979782664, 6979782662, 2838013909, 6979782663, 2838013933, 2838013925, 6979782661, 6979782656, 6979782657, 6979782658, 6979782659, 6979782660, 2838013998, 2838010096], "tags": {"highway": "residential", "name": "Estrada S\u00e3o Paulo"}}, {"type": "way", "id": 745706165, "nodes": [2838016532, 2838016521, 6979782653, 6979782652, 2838016527, 2838013936], "tags": {"highway": "residential", "name": "Rua Tucano"}}, {"type": "way", "id": 745706166, "nodes": [2844358215, 2838016541, 4895889181, 4895889176, 2838016527], "tags": {"highway": "residential", "name": "Rua Acau\u00e3", "oneway": "no"}}, {"type": "way", "id": 745706167, "nodes": [2838016540, 4895889179, 4895889184], "tags": {"highway": "residential", "name": "Rua Araras", "oneway": "no"}}, {"type": "way", "id": 745706168, "nodes": [2844358212, 2838016543], "tags": {"highway": "residential", "name": "Rua Andorinha", "oneway": "no"}}, {"type": "way", "id": 745707135, "nodes": [4895889209, 4895889185, 2838010096], "tags": {"highway": "residential", "name": "Rua Gar\u00e7a Real", "oneway": "no"}}, {"type": "way", "id": 745707136, "nodes": [6979800670, 6979800669, 6979800668, 6979800667, 6979800666, 6979800665, 6979800664, 6978512790], "tags": {"highway": "residential"}}, {"type": "way", "id": 782549765, "nodes": [6979782661, 7307453509, 7307453508], "tags": {"highway": "residential"}}, {"type": "way", "id": 782549766, "nodes": [7307453511, 7307453510], "tags": {"highway": "residential"}}, {"type": "way", "id": 917977894, "nodes": [2838013914, 2844429466, 2838013956, 2838013920], "tags": {"highway": "residential", "name": "Estrada dos Moraes"}}, {"type": "way", "id": 1186983859, "nodes": [4895889213, 2844429464], "tags": {"highway": "residential"}}, {"type": "way", "id": 1186984312, "nodes": [2838014002, 6979780846], "tags": {"highway": "residential", "name": "Rua Caure"}}, {"type": "way", "id": 1186985866, "nodes": [2838013939, 11023555736, 11023555737, 11023555738, 11023555739], "tags": {"alt_name": "Estrada Guaranipoles", "highway": "residential", "name": "Estrada Guaranopoles"}}, {"type": "way", "id": 1186989618, "nodes": [2838013987, 4895889262, 6992473196, 6992473199, 6992473200, 6992473201, 11023673305, 6992473197, 2838013922, 6992473198, 2838108048, 2838106335, 6992473202, 2838013935], "tags": {"highway": "unclassified"}}]}