{"version": 0.6, "generator": "Overpass API 0.7.62.5 1bd436f1", "osm3s": {"timestamp_osm_base": "2025-04-28T01:55:39Z", "copyright": "The data included in this document is from www.openstreetmap.org. The data is made available under ODbL."}, "elements": [{"type": "node", "id": 2631349079, "lat": -8.7443679, "lon": -68.9942829}, {"type": "node", "id": 2631349082, "lat": -8.7441638, "lon": -68.9943955}, {"type": "node", "id": 2631349086, "lat": -8.7439199, "lon": -68.994661}, {"type": "node", "id": 2631349088, "lat": -8.7438774, "lon": -68.9950365}, {"type": "node", "id": 2631349091, "lat": -8.7438509, "lon": -68.9957822}, {"type": "node", "id": 2631349094, "lat": -8.7439357, "lon": -68.9969999}, {"type": "node", "id": 2631349096, "lat": -8.7440338, "lon": -68.9971367}, {"type": "node", "id": 2631349098, "lat": -8.7443334, "lon": -68.9973728}, {"type": "node", "id": 2631349123, "lat": -8.7439875, "lon": -68.9975833}, {"type": "node", "id": 2631349126, "lat": -8.7437219, "lon": -68.9976}, {"type": "node", "id": 2631349128, "lat": -8.7435111, "lon": -68.997714}, {"type": "node", "id": 2631349129, "lat": -8.7431634, "lon": -68.9977726}, {"type": "node", "id": 2631349130, "lat": -8.7428416, "lon": -68.9977237}, {"type": "node", "id": 2631349131, "lat": -8.7424456, "lon": -68.9975186}, {"type": "node", "id": 2631349132, "lat": -8.7421012, "lon": -68.9974567}, {"type": "node", "id": 2631349133, "lat": -8.7416248, "lon": -68.997486}, {"type": "node", "id": 2631349134, "lat": -8.7410197, "lon": -68.9976228}, {"type": "node", "id": 2631349135, "lat": -8.740569, "lon": -68.9976912}, {"type": "node", "id": 2631349136, "lat": -8.7400572, "lon": -68.997968}, {"type": "node", "id": 2631349137, "lat": -8.7397772, "lon": -68.9980331}, {"type": "node", "id": 2631349139, "lat": -8.7396323, "lon": -68.9981569}, {"type": "node", "id": 2631349140, "lat": -8.7394424, "lon": -68.9984663}, {"type": "node", "id": 2631349142, "lat": -8.7393426, "lon": -68.9985705}, {"type": "node", "id": 2631349144, "lat": -8.7390497, "lon": -68.9986584}, {"type": "node", "id": 2631349146, "lat": -8.7388115, "lon": -68.9987822}, {"type": "node", "id": 2631349149, "lat": -8.7386699, "lon": -68.9990134}, {"type": "node", "id": 2631349151, "lat": -8.7380422, "lon": -68.9995996}, {"type": "node", "id": 2631349153, "lat": -8.7379424, "lon": -69.0000132}, {"type": "node", "id": 2631349164, "lat": -8.737643, "lon": -69.0003096}, {"type": "node", "id": 2631349165, "lat": -8.7372857, "lon": -69.0005441}, {"type": "node", "id": 2631349167, "lat": -8.7368222, "lon": -69.0009283}, {"type": "node", "id": 2631349169, "lat": -8.7365132, "lon": -69.0012801}, {"type": "node", "id": 2631349170, "lat": -8.7362009, "lon": -69.0014983}, {"type": "node", "id": 2631349171, "lat": -8.7360915, "lon": -69.0015895}, {"type": "node", "id": 2631349172, "lat": -8.7356859, "lon": -69.0020552}, {"type": "node", "id": 2631349173, "lat": -8.7353447, "lon": -69.0022571}, {"type": "node", "id": 2631349174, "lat": -8.7350421, "lon": -69.0024851}, {"type": "node", "id": 2631349175, "lat": -8.734511, "lon": -69.002827}, {"type": "node", "id": 2631349176, "lat": -8.7342663, "lon": -69.0029931}, {"type": "node", "id": 2631349177, "lat": -8.7341215, "lon": -69.0035663}, {"type": "node", "id": 2631349178, "lat": -8.7340056, "lon": -69.0041265}, {"type": "node", "id": 2631349179, "lat": -8.7337127, "lon": -69.0046736}, {"type": "node", "id": 2631349181, "lat": -8.7335743, "lon": -69.005009}, {"type": "node", "id": 2631349183, "lat": -8.7337062, "lon": -69.0055268}, {"type": "node", "id": 2631349186, "lat": -8.7337932, "lon": -69.0058525}, {"type": "node", "id": 2631349188, "lat": -8.7337545, "lon": -69.0063671}, {"type": "node", "id": 2631349190, "lat": -8.7336161, "lon": -69.0066537}, {"type": "node", "id": 2631349192, "lat": -8.7334552, "lon": -69.0067579}, {"type": "node", "id": 2631349194, "lat": -8.7332427, "lon": -69.0067905}, {"type": "node", "id": 2631349196, "lat": -8.7329112, "lon": -69.0066993}, {"type": "node", "id": 2631349197, "lat": -8.732586, "lon": -69.006696}, {"type": "node", "id": 2631349198, "lat": -8.7322674, "lon": -69.0069012}, {"type": "node", "id": 2631349199, "lat": -8.7319809, "lon": -69.0072431}, {"type": "node", "id": 2631349200, "lat": -8.731836, "lon": -69.0075297}, {"type": "node", "id": 2631349201, "lat": -8.7312598, "lon": -69.0079336}, {"type": "node", "id": 2631349202, "lat": -8.7310345, "lon": -69.008168}, {"type": "node", "id": 2631349203, "lat": -8.7307255, "lon": -69.0087933}, {"type": "node", "id": 3048136811, "lat": -8.7309636, "lon": -69.1006423}, {"type": "node", "id": 4526934870, "lat": -8.6786722, "lon": -69.1226366}, {"type": "node", "id": 4526934871, "lat": -8.6879715, "lon": -69.12261}, {"type": "node", "id": 4526934872, "lat": -8.6947272, "lon": -69.1300771}, {"type": "node", "id": 4526934873, "lat": -8.6841376, "lon": -69.1592559}, {"type": "node", "id": 4526934874, "lat": -8.721188, "lon": -69.2216426}, {"type": "node", "id": 4526934875, "lat": -8.6759146, "lon": -69.1216509}, {"type": "node", "id": 4526934876, "lat": -8.6852272, "lon": -69.1227572}, {"type": "node", "id": 4526934877, "lat": -8.6911749, "lon": -69.1285883}, {"type": "node", "id": 4526934878, "lat": -8.6902647, "lon": -69.146016}, {"type": "node", "id": 4526934879, "lat": -8.7045619, "lon": -69.2047163}, {"type": "node", "id": 4526934880, "lat": -8.682504, "lon": -69.1223256}, {"type": "node", "id": 4526934881, "lat": -8.6894989, "lon": -69.1265156}, {"type": "node", "id": 4526934882, "lat": -8.6962991, "lon": -69.1340585}, {"type": "node", "id": 4526934883, "lat": -8.6923076, "lon": -69.1842363}, {"type": "node", "id": 4526934884, "lat": -8.733507, "lon": -69.258939}, {"type": "node", "id": 4526934885, "lat": -8.6801729, "lon": -69.1220056}, {"type": "node", "id": 4526934886, "lat": -8.6890033, "lon": -69.1246986}, {"type": "node", "id": 4526934887, "lat": -8.6961927, "lon": -69.1312917}, {"type": "node", "id": 4526934888, "lat": -8.6837204, "lon": -69.1641748}, {"type": "node", "id": 4526934989, "lat": -8.7261612, "lon": -69.2318944}, {"type": "node", "id": 4526934991, "lat": -8.6778884, "lon": -69.1226854}, {"type": "node", "id": 4526934992, "lat": -8.6867471, "lon": -69.12283}, {"type": "node", "id": 4526934993, "lat": -8.6929496, "lon": -69.1294079}, {"type": "node", "id": 4526934994, "lat": -8.6869315, "lon": -69.1562269}, {"type": "node", "id": 4526934995, "lat": -8.7147528, "lon": -69.214633}, {"type": "node", "id": 4526934998, "lat": -8.6842136, "lon": -69.1230457}, {"type": "node", "id": 4526934999, "lat": -8.6909172, "lon": -69.1275149}, {"type": "node", "id": 4526935000, "lat": -8.6924753, "lon": -69.1419192}, {"type": "node", "id": 4526935001, "lat": -8.70057, "lon": -69.1974816}, {"type": "node", "id": 4526935002, "lat": -8.7346763, "lon": -69.2707336}, {"type": "node", "id": 4526935004, "lat": -8.6815326, "lon": -69.1216171}, {"type": "node", "id": 4526935005, "lat": -8.6886643, "lon": -69.1263103}, {"type": "node", "id": 4526935006, "lat": -8.6970613, "lon": -69.132033}, {"type": "node", "id": 4526935007, "lat": -8.6883818, "lon": -69.1789113}, {"type": "node", "id": 4526935008, "lat": -8.730966, "lon": -69.2464743}, {"type": "node", "id": 4526935010, "lat": -8.679294, "lon": -69.1222328}, {"type": "node", "id": 4526935012, "lat": -8.6885663, "lon": -69.1232651}, {"type": "node", "id": 4526935013, "lat": -8.6956368, "lon": -69.1303787}, {"type": "node", "id": 4526935014, "lat": -8.683476, "lon": -69.1608152}, {"type": "node", "id": 4526935015, "lat": -8.7234581, "lon": -69.2251672}, {"type": "node", "id": 4526935016, "lat": -8.6762579, "lon": -69.1220102}, {"type": "node", "id": 4526935019, "lat": -8.6857558, "lon": -69.1227839}, {"type": "node", "id": 4526935020, "lat": -8.691849, "lon": -69.128722}, {"type": "node", "id": 4526935021, "lat": -8.6886451, "lon": -69.1499691}, {"type": "node", "id": 4526935022, "lat": -8.7069232, "lon": -69.2066676}, {"type": "node", "id": 4526935023, "lat": -8.7350212, "lon": -69.272636}, {"type": "node", "id": 4526935025, "lat": -8.6832061, "lon": -69.1226265}, {"type": "node", "id": 4526935026, "lat": -8.6900779, "lon": -69.1263117}, {"type": "node", "id": 4526935027, "lat": -8.6954939, "lon": -69.1355111}, {"type": "node", "id": 4526935028, "lat": -8.6952202, "lon": -69.1885227}, {"type": "node", "id": 4526935029, "lat": -8.7341329, "lon": -69.2643868}, {"type": "node", "id": 4526935031, "lat": -8.6887598, "lon": -69.1254607}, {"type": "node", "id": 4526935032, "lat": -8.6965165, "lon": -69.1315582}, {"type": "node", "id": 4526935033, "lat": -8.685083, "lon": -69.1679502}, {"type": "node", "id": 4526935034, "lat": -8.7275269, "lon": -69.2357339}, {"type": "node", "id": 4526935037, "lat": -8.6937492, "lon": -69.1296092}, {"type": "node", "id": 4526935038, "lat": -8.6857958, "lon": -69.1576305}, {"type": "node", "id": 4526935039, "lat": -8.7178495, "lon": -69.2181183}, {"type": "node", "id": 4526935041, "lat": -8.69097, "lon": -69.1283008}, {"type": "node", "id": 4526935042, "lat": -8.6909685, "lon": -69.1447956}, {"type": "node", "id": 4526935043, "lat": -8.7032254, "lon": -69.2020665}, {"type": "node", "id": 4526935044, "lat": -8.7347502, "lon": -69.2712443}, {"type": "node", "id": 4526935046, "lat": -8.6966582, "lon": -69.1330692}, {"type": "node", "id": 4526935047, "lat": -8.6891016, "lon": -69.1798421}, {"type": "node", "id": 4526935048, "lat": -8.7325559, "lon": -69.2534071}, {"type": "node", "id": 4526935050, "lat": -8.6833179, "lon": -69.1618769}, {"type": "node", "id": 4526935051, "lat": -8.7252792, "lon": -69.229487}, {"type": "node", "id": 4526935054, "lat": -8.6806619, "lon": -69.1219789}, {"type": "node", "id": 4526935055, "lat": -8.7105601, "lon": -69.2104354}, {"type": "node", "id": 4526935056, "lat": -8.735359, "lon": -69.2728653}, {"type": "node", "id": 4526935058, "lat": -8.6783179, "lon": -69.1226987}, {"type": "node", "id": 4526935059, "lat": -8.6871792, "lon": -69.1226501}, {"type": "node", "id": 4526935060, "lat": -8.6978759, "lon": -69.1930073}, {"type": "node", "id": 4526935061, "lat": -8.7346463, "lon": -69.2695761}, {"type": "node", "id": 4526935063, "lat": -8.6755254, "lon": -69.1214895}, {"type": "node", "id": 4526935064, "lat": -8.6846762, "lon": -69.1228719}, {"type": "node", "id": 4526935065, "lat": -8.7295104, "lon": -69.2410913}, {"type": "node", "id": 4526935068, "lat": -8.6819952, "lon": -69.121831}, {"type": "node", "id": 4526935069, "lat": -8.6889485, "lon": -69.1265326}, {"type": "node", "id": 4526935072, "lat": -8.6795848, "lon": -69.122039}, {"type": "node", "id": 4526935073, "lat": -8.6887305, "lon": -69.1240873}, {"type": "node", "id": 4526935074, "lat": -8.6959701, "lon": -69.1306694}, {"type": "node", "id": 4526935075, "lat": -8.7349697, "lon": -69.2722366}, {"type": "node", "id": 4526935077, "lat": -8.6773416, "lon": -69.1223177}, {"type": "node", "id": 4526935078, "lat": -8.6861787, "lon": -69.1230112}, {"type": "node", "id": 4526935079, "lat": -8.6923548, "lon": -69.1288598}, {"type": "node", "id": 4526935080, "lat": -8.6875903, "lon": -69.1538791}, {"type": "node", "id": 4526935082, "lat": -8.6748551, "lon": -69.121449}, {"type": "node", "id": 4526935083, "lat": -8.6837877, "lon": -69.1230342}, {"type": "node", "id": 4526935084, "lat": -8.6905603, "lon": -69.1263785}, {"type": "node", "id": 4526935085, "lat": -8.6942986, "lon": -69.1383293}, {"type": "node", "id": 4526935087, "lat": -8.6811163, "lon": -69.1217173}, {"type": "node", "id": 4526935088, "lat": -8.6886313, "lon": -69.1260429}, {"type": "node", "id": 4526935089, "lat": -8.6969687, "lon": -69.1317789}, {"type": "node", "id": 4526935090, "lat": -8.6878786, "lon": -69.1771951}, {"type": "node", "id": 4530244184, "lat": -8.7230369, "lon": -69.1113707}, {"type": "node", "id": 4530244185, "lat": -8.7073717, "lon": -69.1248129}, {"type": "node", "id": 4530244186, "lat": -8.7242995, "lon": -69.1089455}, {"type": "node", "id": 4530244187, "lat": -8.7096308, "lon": -69.1241009}, {"type": "node", "id": 4530244188, "lat": -8.7261319, "lon": -69.1071531}, {"type": "node", "id": 4530244589, "lat": -8.7122025, "lon": -69.1237025}, {"type": "node", "id": 4530244590, "lat": -8.7268989, "lon": -69.1057157}, {"type": "node", "id": 4530244591, "lat": -8.7135806, "lon": -69.122809}, {"type": "node", "id": 4530244592, "lat": -8.727658, "lon": -69.1036893}, {"type": "node", "id": 4530244593, "lat": -8.7152381, "lon": -69.1215381}, {"type": "node", "id": 4530244594, "lat": -8.7299231, "lon": -69.1012582}, {"type": "node", "id": 4530244595, "lat": -8.6979949, "lon": -69.1306828}, {"type": "node", "id": 4530244596, "lat": -8.715448, "lon": -69.1200581}, {"type": "node", "id": 4530244597, "lat": -8.7310484, "lon": -69.1002828}, {"type": "node", "id": 4530244598, "lat": -8.6970571, "lon": -69.1318825}, {"type": "node", "id": 4530244599, "lat": -8.7180123, "lon": -69.1188036}, {"type": "node", "id": 4530244600, "lat": -8.7312702, "lon": -69.0951959}, {"type": "node", "id": 4530244601, "lat": -8.7020958, "lon": -69.12762}, {"type": "node", "id": 4530244602, "lat": -8.7198829, "lon": -69.1172085}, {"type": "node", "id": 4530244604, "lat": -8.7031574, "lon": -69.1274785}, {"type": "node", "id": 4530244605, "lat": -8.7203377, "lon": -69.1154249}, {"type": "node", "id": 4530244606, "lat": -8.7049185, "lon": -69.1266796}, {"type": "node", "id": 4530244607, "lat": -8.7219039, "lon": -69.1136737}, {"type": "node", "id": 4530244608, "lat": -8.7068052, "lon": -69.1254497}, {"type": "node", "id": 4530244609, "lat": -8.7233376, "lon": -69.1104862}, {"type": "node", "id": 4530244610, "lat": -8.708232, "lon": -69.1247315}, {"type": "node", "id": 4530244611, "lat": -8.724859, "lon": -69.1083232}, {"type": "node", "id": 4530244612, "lat": -8.7100574, "lon": -69.1239099}, {"type": "node", "id": 4530244613, "lat": -8.7268739, "lon": -69.1067028}, {"type": "node", "id": 4530244614, "lat": -8.7128655, "lon": -69.1235271}, {"type": "node", "id": 4530244615, "lat": -8.726836, "lon": -69.1051638}, {"type": "node", "id": 4530244616, "lat": -8.7141471, "lon": -69.1225613}, {"type": "node", "id": 4530244617, "lat": -8.7281434, "lon": -69.1028518}, {"type": "node", "id": 4530244618, "lat": -8.6981846, "lon": -69.1302185}, {"type": "node", "id": 4530244619, "lat": -8.7153361, "lon": -69.1209816}, {"type": "node", "id": 4530244620, "lat": -8.7305456, "lon": -69.1009256}, {"type": "node", "id": 4530244621, "lat": -8.6978257, "lon": -69.1311306}, {"type": "node", "id": 4530244622, "lat": -8.7160914, "lon": -69.11986}, {"type": "node", "id": 4530244623, "lat": -8.7313144, "lon": -69.0991463}, {"type": "node", "id": 4530244624, "lat": -8.6986348, "lon": -69.1298029}, {"type": "node", "id": 4530244625, "lat": -8.7190017, "lon": -69.1183397}, {"type": "node", "id": 4530244626, "lat": -8.7310942, "lon": -69.094243}, {"type": "node", "id": 4530244627, "lat": -8.7024595, "lon": -69.1273441}, {"type": "node", "id": 4530244628, "lat": -8.7198411, "lon": -69.116458}, {"type": "node", "id": 4530244630, "lat": -8.70364, "lon": -69.1275705}, {"type": "node", "id": 4530244631, "lat": -8.7207433, "lon": -69.1147577}, {"type": "node", "id": 4530244632, "lat": -8.7056021, "lon": -69.1262989}, {"type": "node", "id": 4530244633, "lat": -8.7227222, "lon": -69.112466}, {"type": "node", "id": 4530244634, "lat": -8.7071409, "lon": -69.1249403}, {"type": "node", "id": 4530244635, "lat": -8.7236072, "lon": -69.1097097}, {"type": "node", "id": 4530244636, "lat": -8.7088335, "lon": -69.12459}, {"type": "node", "id": 4530244637, "lat": -8.7254115, "lon": -69.1077403}, {"type": "node", "id": 4530244638, "lat": -8.7112443, "lon": -69.1236884}, {"type": "node", "id": 4530244639, "lat": -8.7270348, "lon": -69.106257}, {"type": "node", "id": 4530244640, "lat": -8.7132637, "lon": -69.1231712}, {"type": "node", "id": 4530244641, "lat": -8.7272243, "lon": -69.1043403}, {"type": "node", "id": 4530244642, "lat": -8.7148815, "lon": -69.1221863}, {"type": "node", "id": 4530244643, "lat": -8.7286959, "lon": -69.1021442}, {"type": "node", "id": 4530244644, "lat": -8.7153081, "lon": -69.1205571}, {"type": "node", "id": 4530244645, "lat": -8.7308933, "lon": -69.1008156}, {"type": "node", "id": 4530244646, "lat": -8.6975235, "lon": -69.1315383}, {"type": "node", "id": 4530244647, "lat": -8.7169003, "lon": -69.1192848}, {"type": "node", "id": 4530244648, "lat": -8.73183, "lon": -69.0972276}, {"type": "node", "id": 4530244649, "lat": -8.6998005, "lon": -69.1291218}, {"type": "node", "id": 4530244650, "lat": -8.7197291, "lon": -69.1176542}, {"type": "node", "id": 4530244652, "lat": -8.7028092, "lon": -69.1272945}, {"type": "node", "id": 4530244653, "lat": -8.719967, "lon": -69.1161396}, {"type": "node", "id": 4530244655, "lat": -8.7042975, "lon": -69.1273724}, {"type": "node", "id": 4530244656, "lat": -8.7212259, "lon": -69.1144747}, {"type": "node", "id": 4530244657, "lat": -8.7062169, "lon": -69.1258876}, {"type": "node", "id": 4530254124, "lat": -8.6725341, "lon": -69.1207508}, {"type": "node", "id": 4530254125, "lat": -8.6710717, "lon": -69.1199156}, {"type": "node", "id": 4530254126, "lat": -8.6714674, "lon": -69.118395}, {"type": "node", "id": 4530254127, "lat": -8.6713493, "lon": -69.116581}, {"type": "node", "id": 4530254128, "lat": -8.6701289, "lon": -69.1157581}, {"type": "node", "id": 4530254129, "lat": -8.6695422, "lon": -69.1144804}, {"type": "node", "id": 4530254130, "lat": -8.6683348, "lon": -69.1144623}, {"type": "node", "id": 4530254131, "lat": -8.6670227, "lon": -69.114601}, {"type": "node", "id": 4530254132, "lat": -8.665654, "lon": -69.1148675}, {"type": "node", "id": 4530254133, "lat": -8.6746741, "lon": -69.1213703}, {"type": "node", "id": 4530254134, "lat": -8.6735817, "lon": -69.1208137}, {"type": "node", "id": 4530254136, "lat": -8.6717721, "lon": -69.1204636}, {"type": "node", "id": 4530254137, "lat": -8.6711256, "lon": -69.1193942}, {"type": "node", "id": 4530254138, "lat": -8.6715512, "lon": -69.117578}, {"type": "node", "id": 4530254139, "lat": -8.6710208, "lon": -69.1162174}, {"type": "node", "id": 4530254140, "lat": -8.6699254, "lon": -69.1154236}, {"type": "node", "id": 4530254141, "lat": -8.6690698, "lon": -69.114214}, {"type": "node", "id": 4530254142, "lat": -8.6678858, "lon": -69.114438}, {"type": "node", "id": 4530254143, "lat": -8.6664561, "lon": -69.1145647}, {"type": "node", "id": 4530254144, "lat": -8.6650145, "lon": -69.1152792}, {"type": "node", "id": 4530254145, "lat": -8.6744467, "lon": -69.1212674}, {"type": "node", "id": 4530254147, "lat": -8.6731507, "lon": -69.1207895}, {"type": "node", "id": 4530254148, "lat": -8.6683773, "lon": -69.1144346}, {"type": "node", "id": 4530254149, "lat": -8.6712154, "lon": -69.1202093}, {"type": "node", "id": 4530254150, "lat": -8.6712579, "lon": -69.1188794}, {"type": "node", "id": 4530254151, "lat": -8.671499, "lon": -69.1170291}, {"type": "node", "id": 4530254152, "lat": -8.6705659, "lon": -69.1160842}, {"type": "node", "id": 4530254153, "lat": -8.6698116, "lon": -69.1149104}, {"type": "node", "id": 4530254154, "lat": -8.6687166, "lon": -69.114214}, {"type": "node", "id": 4530254155, "lat": -8.6673998, "lon": -69.1144012}, {"type": "node", "id": 4530254156, "lat": -8.6659413, "lon": -69.1145647}, {"type": "node", "id": 4530254158, "lat": -8.6740253, "lon": -69.1209888}, {"type": "node", "id": 8271036347, "lat": -8.6782298, "lon": -69.0253119}, {"type": "node", "id": 8271036348, "lat": -8.6781039, "lon": -69.0253803}, {"type": "node", "id": 8271036349, "lat": -8.6778957, "lon": -69.0255091}, {"type": "node", "id": 8271036350, "lat": -8.6777115, "lon": -69.0256231}, {"type": "node", "id": 8271036351, "lat": -8.6775643, "lon": -69.0257558}, {"type": "node", "id": 8271036352, "lat": -8.6774463, "lon": -69.0258819}, {"type": "node", "id": 8271036353, "lat": -8.6773151, "lon": -69.0261219}, {"type": "node", "id": 8271036354, "lat": -8.6772832, "lon": -69.0263124}, {"type": "node", "id": 8271036355, "lat": -8.6773031, "lon": -69.0264653}, {"type": "node", "id": 8271036356, "lat": -8.6774582, "lon": -69.0268394}, {"type": "node", "id": 8271036357, "lat": -8.6775736, "lon": -69.0271211}, {"type": "node", "id": 8271036358, "lat": -8.6776412, "lon": -69.0273155}, {"type": "node", "id": 8271036359, "lat": -8.6776704, "lon": -69.0274845}, {"type": "node", "id": 8271036360, "lat": -8.677669, "lon": -69.0277715}, {"type": "node", "id": 8271036361, "lat": -8.677612, "lon": -69.0281309}, {"type": "node", "id": 8271036362, "lat": -8.6775643, "lon": -69.0284193}, {"type": "node", "id": 8271036363, "lat": -8.6775073, "lon": -69.0286499}, {"type": "node", "id": 8271036364, "lat": -8.6773694, "lon": -69.0288337}, {"type": "node", "id": 8271036365, "lat": -8.677266, "lon": -69.0289141}, {"type": "node", "id": 8271036366, "lat": -8.6770751, "lon": -69.0290429}, {"type": "node", "id": 8271036367, "lat": -8.6768338, "lon": -69.0291408}, {"type": "node", "id": 8271036368, "lat": -8.6761391, "lon": -69.0293594}, {"type": "node", "id": 8271036369, "lat": -8.6759959, "lon": -69.0293875}, {"type": "node", "id": 8271036370, "lat": -8.6759058, "lon": -69.0294237}, {"type": "node", "id": 8271036371, "lat": -8.6757984, "lon": -69.0294921}, {"type": "node", "id": 8271036372, "lat": -8.6756738, "lon": -69.0296289}, {"type": "node", "id": 8271036373, "lat": -8.6755796, "lon": -69.0298006}, {"type": "node", "id": 8271036374, "lat": -8.6754073, "lon": -69.0300769}, {"type": "node", "id": 8271036375, "lat": -8.6752283, "lon": -69.03027}, {"type": "node", "id": 8271036376, "lat": -8.6747219, "lon": -69.0307018}, {"type": "node", "id": 8271036377, "lat": -8.6745323, "lon": -69.0308319}, {"type": "node", "id": 8271036378, "lat": -8.6742844, "lon": -69.0309633}, {"type": "node", "id": 8271036379, "lat": -8.6740312, "lon": -69.0310505}, {"type": "node", "id": 8271036380, "lat": -8.6737978, "lon": -69.0310612}, {"type": "node", "id": 8271036381, "lat": -8.6736891, "lon": -69.0310411}, {"type": "node", "id": 8271036382, "lat": -8.673591, "lon": -69.0310076}, {"type": "node", "id": 8271036383, "lat": -8.6734677, "lon": -69.0309566}, {"type": "node", "id": 8271036384, "lat": -8.6733457, "lon": -69.0308869}, {"type": "node", "id": 8271036385, "lat": -8.6731933, "lon": -69.03084}, {"type": "node", "id": 8271036386, "lat": -8.6729984, "lon": -69.0308051}, {"type": "node", "id": 8271036387, "lat": -8.672769, "lon": -69.0307622}, {"type": "node", "id": 8271036388, "lat": -8.6726139, "lon": -69.0307233}, {"type": "node", "id": 8271036389, "lat": -8.672484, "lon": -69.0306468}, {"type": "node", "id": 8271036390, "lat": -8.6722573, "lon": -69.0305154}, {"type": "node", "id": 8271036391, "lat": -8.67202, "lon": -69.0303357}, {"type": "node", "id": 8271036392, "lat": -8.6718184, "lon": -69.030156}, {"type": "node", "id": 8271036393, "lat": -8.6716726, "lon": -69.0299883}, {"type": "node", "id": 8271036394, "lat": -8.6715082, "lon": -69.0297604}, {"type": "node", "id": 8271036395, "lat": -8.6714101, "lon": -69.0295914}, {"type": "node", "id": 8271036396, "lat": -8.6713438, "lon": -69.0294975}, {"type": "node", "id": 8271036397, "lat": -8.6712921, "lon": -69.0294197}, {"type": "node", "id": 8271036398, "lat": -8.6711794, "lon": -69.0292937}, {"type": "node", "id": 8271036399, "lat": -8.6709819, "lon": -69.0291448}, {"type": "node", "id": 8271036400, "lat": -8.6704251, "lon": -69.0286928}, {"type": "node", "id": 8271036401, "lat": -8.670262, "lon": -69.0285601}, {"type": "node", "id": 8271036402, "lat": -8.6701161, "lon": -69.0284917}, {"type": "node", "id": 8271036403, "lat": -8.6700194, "lon": -69.0284608}, {"type": "node", "id": 8271036404, "lat": -8.6698364, "lon": -69.0284407}, {"type": "node", "id": 8271036405, "lat": -8.6696946, "lon": -69.0284488}, {"type": "node", "id": 8271036406, "lat": -8.6694281, "lon": -69.0284716}, {"type": "node", "id": 8271036407, "lat": -8.6692663, "lon": -69.0285118}, {"type": "node", "id": 8271036408, "lat": -8.6685809, "lon": -69.028658}, {"type": "node", "id": 8271036409, "lat": -8.6681527, "lon": -69.0287545}, {"type": "node", "id": 8271036410, "lat": -8.6679763, "lon": -69.0288176}, {"type": "node", "id": 8271036411, "lat": -8.6678756, "lon": -69.028886}, {"type": "node", "id": 8271036412, "lat": -8.6677669, "lon": -69.0289705}, {"type": "node", "id": 8271036413, "lat": -8.6673665, "lon": -69.0293795}, {"type": "node", "id": 8271036414, "lat": -8.6672829, "lon": -69.0294546}, {"type": "node", "id": 8271036415, "lat": -8.6671729, "lon": -69.0295163}, {"type": "node", "id": 8271036416, "lat": -8.6667513, "lon": -69.0296571}, {"type": "node", "id": 8271073217, "lat": -8.66627, "lon": -69.0298556}, {"type": "node", "id": 8271073218, "lat": -8.6661056, "lon": -69.0299012}, {"type": "node", "id": 8271073219, "lat": -8.6659519, "lon": -69.0299186}, {"type": "node", "id": 8271073220, "lat": -8.6657119, "lon": -69.029924}, {"type": "node", "id": 8271073221, "lat": -8.6653725, "lon": -69.0298998}, {"type": "node", "id": 8271073222, "lat": -8.6645876, "lon": -69.0298918}, {"type": "node", "id": 8271073223, "lat": -8.6642654, "lon": -69.0299025}, {"type": "node", "id": 8271073224, "lat": -8.6640321, "lon": -69.0299629}, {"type": "node", "id": 8271073225, "lat": -8.6638584, "lon": -69.0300246}, {"type": "node", "id": 8271073226, "lat": -8.6637417, "lon": -69.030093}, {"type": "node", "id": 8271073227, "lat": -8.6636489, "lon": -69.0301962}, {"type": "node", "id": 8271073228, "lat": -8.6635813, "lon": -69.0303411}, {"type": "node", "id": 8271073229, "lat": -8.66347, "lon": -69.0305758}, {"type": "node", "id": 8271073230, "lat": -8.6631571, "lon": -69.0308788}, {"type": "node", "id": 8271073231, "lat": -8.6629609, "lon": -69.0309848}, {"type": "node", "id": 8271073232, "lat": -8.6628097, "lon": -69.0310304}, {"type": "node", "id": 8271073233, "lat": -8.6623523, "lon": -69.0311001}, {"type": "node", "id": 8271073234, "lat": -8.6622409, "lon": -69.0311269}, {"type": "node", "id": 8271073235, "lat": -8.6619227, "lon": -69.0312906}, {"type": "node", "id": 8271073414, "lat": -8.7461136, "lon": -68.9974716}, {"type": "node", "id": 8271073483, "lat": -8.7441563, "lon": -68.9975095}, {"type": "node", "id": 8271073484, "lat": -8.7446653, "lon": -68.9975242}, {"type": "node", "id": 8271073485, "lat": -8.7448336, "lon": -68.9975551}, {"type": "node", "id": 8271073486, "lat": -8.7449767, "lon": -68.9975564}, {"type": "node", "id": 8271073487, "lat": -8.7459749, "lon": -68.9974827}, {"type": "node", "id": 8271073488, "lat": -8.7467317, "lon": -68.9974223}, {"type": "node", "id": 8271073489, "lat": -8.7471904, "lon": -68.9973955}, {"type": "node", "id": 8271073490, "lat": -8.7473083, "lon": -68.9973794}, {"type": "node", "id": 8271073491, "lat": -8.747413, "lon": -68.9973512}, {"type": "node", "id": 8271073492, "lat": -8.7475204, "lon": -68.9972869}, {"type": "node", "id": 8271073493, "lat": -8.7476026, "lon": -68.9972278}, {"type": "node", "id": 8271073494, "lat": -8.7476755, "lon": -68.9971326}, {"type": "node", "id": 8271073495, "lat": -8.7477113, "lon": -68.9970468}, {"type": "node", "id": 8271073496, "lat": -8.747763, "lon": -68.9969502}, {"type": "node", "id": 8271073497, "lat": -8.7478664, "lon": -68.9967853}, {"type": "node", "id": 8271073498, "lat": -8.7480559, "lon": -68.9962569}, {"type": "node", "id": 8271073499, "lat": -8.7481354, "lon": -68.9960396}, {"type": "node", "id": 8271073500, "lat": -8.748264, "lon": -68.9957432}, {"type": "node", "id": 8271073501, "lat": -8.7483422, "lon": -68.9955957}, {"type": "node", "id": 8271073502, "lat": -8.7490911, "lon": -68.9949882}, {"type": "node", "id": 8271073503, "lat": -8.7484284, "lon": -68.995471}, {"type": "node", "id": 8271073504, "lat": -8.7482998, "lon": -68.9953074}, {"type": "node", "id": 8271073505, "lat": -8.7481885, "lon": -68.9952229}, {"type": "node", "id": 8271073506, "lat": -8.7479644, "lon": -68.9950995}, {"type": "node", "id": 8271073507, "lat": -8.7476463, "lon": -68.995015}, {"type": "node", "id": 8271073508, "lat": -8.7475655, "lon": -68.995011}, {"type": "node", "id": 8271073509, "lat": -8.7474873, "lon": -68.9950177}, {"type": "node", "id": 8271073510, "lat": -8.7473309, "lon": -68.9950834}, {"type": "node", "id": 8271073511, "lat": -8.7472473, "lon": -68.9951773}, {"type": "node", "id": 8271073512, "lat": -8.7470286, "lon": -68.9954562}, {"type": "node", "id": 8271073513, "lat": -8.7467198, "lon": -68.9957178}, {"type": "node", "id": 8271073514, "lat": -8.7463261, "lon": -68.9958948}, {"type": "node", "id": 8271073515, "lat": -8.7462347, "lon": -68.9959122}, {"type": "node", "id": 8271073516, "lat": -8.7461512, "lon": -68.9958934}, {"type": "node", "id": 8271073517, "lat": -8.7460769, "lon": -68.9958371}, {"type": "node", "id": 8271073518, "lat": -8.7460146, "lon": -68.9957339}, {"type": "node", "id": 8271073519, "lat": -8.7459802, "lon": -68.9956038}, {"type": "node", "id": 8271073520, "lat": -8.7459205, "lon": -68.9952336}, {"type": "node", "id": 8271073521, "lat": -8.7458171, "lon": -68.9947321}, {"type": "node", "id": 8271073522, "lat": -8.7458092, "lon": -68.9946127}, {"type": "node", "id": 8271073523, "lat": -8.7457774, "lon": -68.9945604}, {"type": "node", "id": 8271073524, "lat": -8.7457018, "lon": -68.9945228}, {"type": "node", "id": 8271073525, "lat": -8.7455547, "lon": -68.9945081}, {"type": "node", "id": 8271073526, "lat": -8.745332, "lon": -68.9944933}, {"type": "node", "id": 8271073527, "lat": -8.7451809, "lon": -68.9944732}, {"type": "node", "id": 8271073528, "lat": -8.7445831, "lon": -68.9943029}, {"type": "node", "id": 8271073529, "lat": -8.744485, "lon": -68.9942828}, {"type": "node", "id": 8271073530, "lat": -8.7445672, "lon": -68.9975014}, {"type": "node", "id": 8271073531, "lat": -8.7439839, "lon": -68.9945349}, {"type": "node", "id": 8271073532, "lat": -8.7438779, "lon": -68.9948675}, {"type": "node", "id": 8271073533, "lat": -8.7438567, "lon": -68.9954174}, {"type": "node", "id": 8271073534, "lat": -8.743862, "lon": -68.9960745}, {"type": "node", "id": 8271073535, "lat": -8.7438249, "lon": -68.9964795}, {"type": "node", "id": 8271073536, "lat": -8.743862, "lon": -68.9967772}, {"type": "node", "id": 8271073537, "lat": -8.7245818, "lon": -69.0103412}, {"type": "node", "id": 8271073538, "lat": -8.7245209, "lon": -69.0103841}, {"type": "node", "id": 8271073539, "lat": -8.7244652, "lon": -69.0104847}, {"type": "node", "id": 8271073540, "lat": -8.7243565, "lon": -69.0106966}, {"type": "node", "id": 8271073541, "lat": -8.7242663, "lon": -69.0108159}, {"type": "node", "id": 8271073542, "lat": -8.7241749, "lon": -69.0109406}, {"type": "node", "id": 8271073543, "lat": -8.7240304, "lon": -69.0109916}, {"type": "node", "id": 8271073544, "lat": -8.7239084, "lon": -69.0109983}, {"type": "node", "id": 8271073545, "lat": -8.7237865, "lon": -69.0110023}, {"type": "node", "id": 8271073546, "lat": -8.7236712, "lon": -69.0109836}, {"type": "node", "id": 8271073547, "lat": -8.7235797, "lon": -69.0109527}, {"type": "node", "id": 8271073548, "lat": -8.7234816, "lon": -69.0108977}, {"type": "node", "id": 8271073549, "lat": -8.7232934, "lon": -69.010769}, {"type": "node", "id": 8271073550, "lat": -8.7229195, "lon": -69.0104887}, {"type": "node", "id": 8271073551, "lat": -8.7226889, "lon": -69.0103774}, {"type": "node", "id": 8271073552, "lat": -8.7223217, "lon": -69.0101025}, {"type": "node", "id": 8271073553, "lat": -8.722034, "lon": -69.009912}, {"type": "node", "id": 8271073554, "lat": -8.721708, "lon": -69.009731}, {"type": "node", "id": 8271073555, "lat": -8.7213766, "lon": -69.0095231}, {"type": "node", "id": 8271073556, "lat": -8.721191, "lon": -69.0094158}, {"type": "node", "id": 8271073557, "lat": -8.7210412, "lon": -69.0093662}, {"type": "node", "id": 8271073558, "lat": -8.7209073, "lon": -69.0093474}, {"type": "node", "id": 8271073559, "lat": -8.7207959, "lon": -69.0093447}, {"type": "node", "id": 8271073560, "lat": -8.7206713, "lon": -69.0094198}, {"type": "node", "id": 8271073561, "lat": -8.720495, "lon": -69.0095486}, {"type": "node", "id": 8271073562, "lat": -8.7203399, "lon": -69.0096813}, {"type": "node", "id": 8271073563, "lat": -8.7201968, "lon": -69.0097846}, {"type": "node", "id": 8271073564, "lat": -8.7200947, "lon": -69.0098423}, {"type": "node", "id": 8271073565, "lat": -8.7197606, "lon": -69.0099616}, {"type": "node", "id": 8271073566, "lat": -8.7195194, "lon": -69.0100783}, {"type": "node", "id": 8271073567, "lat": -8.719298, "lon": -69.0102272}, {"type": "node", "id": 8271073568, "lat": -8.7190408, "lon": -69.0103894}, {"type": "node", "id": 8271073569, "lat": -8.7187863, "lon": -69.0105665}, {"type": "node", "id": 8271073570, "lat": -8.7185994, "lon": -69.0106644}, {"type": "node", "id": 8271073571, "lat": -8.7180228, "lon": -69.0108776}, {"type": "node", "id": 8271073572, "lat": -8.717869, "lon": -69.0109259}, {"type": "node", "id": 8271073573, "lat": -8.7177722, "lon": -69.0109755}, {"type": "node", "id": 8271073574, "lat": -8.7177046, "lon": -69.0110801}, {"type": "node", "id": 8271073575, "lat": -8.7176649, "lon": -69.0112893}, {"type": "node", "id": 8271073576, "lat": -8.7175986, "lon": -69.0115871}, {"type": "node", "id": 8271073577, "lat": -8.7175827, "lon": -69.011701}, {"type": "node", "id": 8271073578, "lat": -8.7176052, "lon": -69.0118043}, {"type": "node", "id": 8271073579, "lat": -8.7177868, "lon": -69.0121651}, {"type": "node", "id": 8271073580, "lat": -8.7178465, "lon": -69.0123394}, {"type": "node", "id": 8271073581, "lat": -8.7178664, "lon": -69.0125258}, {"type": "node", "id": 8271073582, "lat": -8.7178345, "lon": -69.0127458}, {"type": "node", "id": 8271073583, "lat": -8.717763, "lon": -69.0129295}, {"type": "node", "id": 8271073584, "lat": -8.7176582, "lon": -69.0130931}, {"type": "node", "id": 8271073585, "lat": -8.7175495, "lon": -69.0132299}, {"type": "node", "id": 8271073586, "lat": -8.7172301, "lon": -69.0135451}, {"type": "node", "id": 8271073587, "lat": -8.7171333, "lon": -69.0136604}, {"type": "node", "id": 8271073588, "lat": -8.7170856, "lon": -69.0137449}, {"type": "node", "id": 8271073589, "lat": -8.717063, "lon": -69.0139058}, {"type": "node", "id": 8271073590, "lat": -8.717063, "lon": -69.0143538}, {"type": "node", "id": 8271073591, "lat": -8.7170378, "lon": -69.0145187}, {"type": "node", "id": 8271073592, "lat": -8.7169808, "lon": -69.0146971}, {"type": "node", "id": 8271073593, "lat": -8.7168456, "lon": -69.0148607}, {"type": "node", "id": 8271073594, "lat": -8.7166706, "lon": -69.015023}, {"type": "node", "id": 8271073595, "lat": -8.716375, "lon": -69.0151504}, {"type": "node", "id": 8271073596, "lat": -8.716208, "lon": -69.0151879}, {"type": "node", "id": 8271073597, "lat": -8.7160609, "lon": -69.0152282}, {"type": "node", "id": 8271073598, "lat": -8.7159495, "lon": -69.0153033}, {"type": "node", "id": 8271073599, "lat": -8.7158753, "lon": -69.0153958}, {"type": "node", "id": 8271073600, "lat": -8.7157228, "lon": -69.0156828}, {"type": "node", "id": 8271073601, "lat": -8.7156088, "lon": -69.0158853}, {"type": "node", "id": 8271073602, "lat": -8.7155174, "lon": -69.0159899}, {"type": "node", "id": 8271073603, "lat": -8.7153848, "lon": -69.0161227}, {"type": "node", "id": 8271073604, "lat": -8.7153026, "lon": -69.0162219}, {"type": "node", "id": 8271073605, "lat": -8.7152562, "lon": -69.016293}, {"type": "node", "id": 8271073606, "lat": -8.7152271, "lon": -69.0163963}, {"type": "node", "id": 8271073607, "lat": -8.7152098, "lon": -69.0165384}, {"type": "node", "id": 8271073608, "lat": -8.7151767, "lon": -69.0167329}, {"type": "node", "id": 8271073609, "lat": -8.7151237, "lon": -69.0169796}, {"type": "node", "id": 8271073610, "lat": -8.7150216, "lon": -69.0172653}, {"type": "node", "id": 8271073611, "lat": -8.7148665, "lon": -69.0177079}, {"type": "node", "id": 8271073612, "lat": -8.7147843, "lon": -69.017964}, {"type": "node", "id": 8271073613, "lat": -8.7146623, "lon": -69.0183972}, {"type": "node", "id": 8271073614, "lat": -8.714612, "lon": -69.0185688}, {"type": "node", "id": 8271073615, "lat": -8.7145324, "lon": -69.0187351}, {"type": "node", "id": 8271073616, "lat": -8.7144529, "lon": -69.0188558}, {"type": "node", "id": 8271073617, "lat": -8.7143601, "lon": -69.0189645}, {"type": "node", "id": 8271073618, "lat": -8.7142567, "lon": -69.0190436}, {"type": "node", "id": 8271073619, "lat": -8.7140738, "lon": -69.0191227}, {"type": "node", "id": 8271073620, "lat": -8.7138868, "lon": -69.0191898}, {"type": "node", "id": 8271073621, "lat": -8.7137742, "lon": -69.0192541}, {"type": "node", "id": 8271073622, "lat": -8.7136244, "lon": -69.0193681}, {"type": "node", "id": 8271073623, "lat": -8.7134534, "lon": -69.0195465}, {"type": "node", "id": 8271073624, "lat": -8.7132505, "lon": -69.0198375}, {"type": "node", "id": 8271073625, "lat": -8.7131379, "lon": -69.020028}, {"type": "node", "id": 8271073626, "lat": -8.7130928, "lon": -69.0201688}, {"type": "node", "id": 8271073627, "lat": -8.7130742, "lon": -69.0203431}, {"type": "node", "id": 8271073628, "lat": -8.7130862, "lon": -69.0206288}, {"type": "node", "id": 8271073629, "lat": -8.7131312, "lon": -69.0209949}, {"type": "node", "id": 8271073630, "lat": -8.7131829, "lon": -69.0213101}, {"type": "node", "id": 8271073631, "lat": -8.7132002, "lon": -69.0215649}, {"type": "node", "id": 8271073632, "lat": -8.7131856, "lon": -69.0217687}, {"type": "node", "id": 8271073633, "lat": -8.7131273, "lon": -69.0219256}, {"type": "node", "id": 8271073634, "lat": -8.7130384, "lon": -69.0220772}, {"type": "node", "id": 8271073635, "lat": -8.7129019, "lon": -69.0222408}, {"type": "node", "id": 8271073636, "lat": -8.7127415, "lon": -69.0223441}, {"type": "node", "id": 8271073637, "lat": -8.712434, "lon": -69.0225023}, {"type": "node", "id": 8271073638, "lat": -8.7122709, "lon": -69.0225533}, {"type": "node", "id": 8271073639, "lat": -8.7121185, "lon": -69.0225841}, {"type": "node", "id": 8271073640, "lat": -8.712027, "lon": -69.0225814}, {"type": "node", "id": 8271073641, "lat": -8.7119262, "lon": -69.0225653}, {"type": "node", "id": 8271073642, "lat": -8.7117446, "lon": -69.0224648}, {"type": "node", "id": 8271073643, "lat": -8.7110275, "lon": -69.0220866}, {"type": "node", "id": 8271073644, "lat": -8.7107928, "lon": -69.021927}, {"type": "node", "id": 8271073645, "lat": -8.7107027, "lon": -69.0218653}, {"type": "node", "id": 8271073646, "lat": -8.7104362, "lon": -69.0217768}, {"type": "node", "id": 8271073647, "lat": -8.7102414, "lon": -69.0217285}, {"type": "node", "id": 8271073648, "lat": -8.7100571, "lon": -69.0217271}, {"type": "node", "id": 8271073649, "lat": -8.7099603, "lon": -69.0217352}, {"type": "node", "id": 8271073650, "lat": -8.7098569, "lon": -69.021754}, {"type": "node", "id": 8271073651, "lat": -8.7097734, "lon": -69.0217821}, {"type": "node", "id": 8271073652, "lat": -8.7097098, "lon": -69.0218197}, {"type": "node", "id": 8271073653, "lat": -8.7096501, "lon": -69.0219095}, {"type": "node", "id": 8271073654, "lat": -8.7094778, "lon": -69.022281}, {"type": "node", "id": 8271073655, "lat": -8.7094181, "lon": -69.0224232}, {"type": "node", "id": 8271073656, "lat": -8.7093187, "lon": -69.0225868}, {"type": "node", "id": 8271073657, "lat": -8.7092007, "lon": -69.0226753}, {"type": "node", "id": 8271073658, "lat": -8.7089528, "lon": -69.0227947}, {"type": "node", "id": 8271073659, "lat": -8.7083868, "lon": -69.0229784}, {"type": "node", "id": 8271073660, "lat": -8.7079785, "lon": -69.0230776}, {"type": "node", "id": 8271073661, "lat": -8.707838, "lon": -69.0231165}, {"type": "node", "id": 8271073662, "lat": -8.7077081, "lon": -69.0231662}, {"type": "node", "id": 8271073663, "lat": -8.707553, "lon": -69.0232426}, {"type": "node", "id": 8271073664, "lat": -8.707427, "lon": -69.0233566}, {"type": "node", "id": 8271073665, "lat": -8.707317, "lon": -69.0234625}, {"type": "node", "id": 8271073666, "lat": -8.7071765, "lon": -69.0236382}, {"type": "node", "id": 8271073667, "lat": -8.7068212, "lon": -69.0242793}, {"type": "node", "id": 8271073668, "lat": -8.7065296, "lon": -69.0247393}, {"type": "node", "id": 8271073669, "lat": -8.7064328, "lon": -69.0248653}, {"type": "node", "id": 8271073670, "lat": -8.7063692, "lon": -69.0249364}, {"type": "node", "id": 8271073671, "lat": -8.706283, "lon": -69.0249968}, {"type": "node", "id": 8271073672, "lat": -8.7061942, "lon": -69.0250249}, {"type": "node", "id": 8271073673, "lat": -8.7060192, "lon": -69.0250678}, {"type": "node", "id": 8271073674, "lat": -8.7058044, "lon": -69.0251523}, {"type": "node", "id": 8271073675, "lat": -8.705648, "lon": -69.025206}, {"type": "node", "id": 8271073676, "lat": -8.7054863, "lon": -69.0252998}, {"type": "node", "id": 8271073677, "lat": -8.7051177, "lon": -69.0255466}, {"type": "node", "id": 8271073678, "lat": -8.7049428, "lon": -69.0256472}, {"type": "node", "id": 8271073679, "lat": -8.7048036, "lon": -69.0256901}, {"type": "node", "id": 8271073680, "lat": -8.7046405, "lon": -69.0257116}, {"type": "node", "id": 8271073681, "lat": -8.7044231, "lon": -69.0257156}, {"type": "node", "id": 8271073682, "lat": -8.7042706, "lon": -69.0256915}, {"type": "node", "id": 8271073683, "lat": -8.7039061, "lon": -69.0256499}, {"type": "node", "id": 8271073684, "lat": -8.7037682, "lon": -69.0256472}, {"type": "node", "id": 8271073685, "lat": -8.703641, "lon": -69.0256619}, {"type": "node", "id": 8271073686, "lat": -8.7035323, "lon": -69.0257022}, {"type": "node", "id": 8271073687, "lat": -8.7033228, "lon": -69.0257505}, {"type": "node", "id": 8271073688, "lat": -8.7031478, "lon": -69.0257666}, {"type": "node", "id": 8271073689, "lat": -8.702774, "lon": -69.0257598}, {"type": "node", "id": 8271073690, "lat": -8.7025897, "lon": -69.0257867}, {"type": "node", "id": 8271073691, "lat": -8.7024001, "lon": -69.025847}, {"type": "node", "id": 8271073692, "lat": -8.7022265, "lon": -69.0259275}, {"type": "node", "id": 8271073693, "lat": -8.7020647, "lon": -69.0260401}, {"type": "node", "id": 8271073694, "lat": -8.7018699, "lon": -69.0261877}, {"type": "node", "id": 8271073695, "lat": -8.7016578, "lon": -69.0264291}, {"type": "node", "id": 8271073696, "lat": -8.7012534, "lon": -69.027101}, {"type": "node", "id": 8271073697, "lat": -8.7011288, "lon": -69.0272431}, {"type": "node", "id": 8271073698, "lat": -8.7010294, "lon": -69.0273343}, {"type": "node", "id": 8271073699, "lat": -8.7003215, "lon": -69.027683}, {"type": "node", "id": 8271073700, "lat": -8.7001955, "lon": -69.0277299}, {"type": "node", "id": 8271073701, "lat": -8.7000206, "lon": -69.027746}, {"type": "node", "id": 8271073702, "lat": -8.6982707, "lon": -69.0280585}, {"type": "node", "id": 8271073703, "lat": -8.6991244, "lon": -69.0276615}, {"type": "node", "id": 8271073704, "lat": -8.6990223, "lon": -69.0276468}, {"type": "node", "id": 8271073705, "lat": -8.6989348, "lon": -69.0276562}, {"type": "node", "id": 8271073706, "lat": -8.6988208, "lon": -69.0276937}, {"type": "node", "id": 8271073707, "lat": -8.6984921, "lon": -69.0279163}, {"type": "node", "id": 8271073708, "lat": -8.6983847, "lon": -69.0280035}, {"type": "node", "id": 8271073709, "lat": -8.6981076, "lon": -69.0281108}, {"type": "node", "id": 8271073710, "lat": -8.697918, "lon": -69.0281698}, {"type": "node", "id": 8271073711, "lat": -8.6978014, "lon": -69.0282181}, {"type": "node", "id": 8271073712, "lat": -8.6976794, "lon": -69.0282945}, {"type": "node", "id": 8271073713, "lat": -8.6973931, "lon": -69.0285668}, {"type": "node", "id": 8271073714, "lat": -8.6972976, "lon": -69.0286352}, {"type": "node", "id": 8271073715, "lat": -8.6971916, "lon": -69.0286888}, {"type": "node", "id": 8271073716, "lat": -8.6969622, "lon": -69.0287679}, {"type": "node", "id": 8271073717, "lat": -8.6967156, "lon": -69.0288337}, {"type": "node", "id": 8271073718, "lat": -8.6965685, "lon": -69.0288524}, {"type": "node", "id": 8271073719, "lat": -8.6964319, "lon": -69.0288457}, {"type": "node", "id": 8271073720, "lat": -8.6962543, "lon": -69.0288015}, {"type": "node", "id": 8271073721, "lat": -8.6958248, "lon": -69.0286231}, {"type": "node", "id": 8271073722, "lat": -8.6957134, "lon": -69.0285695}, {"type": "node", "id": 8271073723, "lat": -8.695618, "lon": -69.0285064}, {"type": "node", "id": 8271073724, "lat": -8.6955411, "lon": -69.0284407}, {"type": "node", "id": 8271073725, "lat": -8.6954443, "lon": -69.028324}, {"type": "node", "id": 8271073726, "lat": -8.6953727, "lon": -69.0282489}, {"type": "node", "id": 8271073727, "lat": -8.6952972, "lon": -69.0281725}, {"type": "node", "id": 8271073728, "lat": -8.6951898, "lon": -69.0281175}, {"type": "node", "id": 8271073729, "lat": -8.695085, "lon": -69.028084}, {"type": "node", "id": 8271073730, "lat": -8.6948941, "lon": -69.0280505}, {"type": "node", "id": 8271073731, "lat": -8.6947921, "lon": -69.0280156}, {"type": "node", "id": 8271073732, "lat": -8.6946754, "lon": -69.0279378}, {"type": "node", "id": 8271073733, "lat": -8.6946051, "lon": -69.0278788}, {"type": "node", "id": 8271073734, "lat": -8.694511, "lon": -69.0277433}, {"type": "node", "id": 8271073735, "lat": -8.69445, "lon": -69.0275569}, {"type": "node", "id": 8271073736, "lat": -8.6944341, "lon": -69.0273504}, {"type": "node", "id": 8271073737, "lat": -8.694397, "lon": -69.0271828}, {"type": "node", "id": 8271073738, "lat": -8.694336, "lon": -69.0270446}, {"type": "node", "id": 8271073739, "lat": -8.694291, "lon": -69.0269601}, {"type": "node", "id": 8271073740, "lat": -8.6942074, "lon": -69.026818}, {"type": "node", "id": 8271073741, "lat": -8.6941252, "lon": -69.0267362}, {"type": "node", "id": 8271073742, "lat": -8.6940205, "lon": -69.0266544}, {"type": "node", "id": 8271073743, "lat": -8.6938826, "lon": -69.0265994}, {"type": "node", "id": 8271073744, "lat": -8.6937103, "lon": -69.0265927}, {"type": "node", "id": 8271073745, "lat": -8.6933948, "lon": -69.026657}, {"type": "node", "id": 8271073746, "lat": -8.6928075, "lon": -69.026826}, {"type": "node", "id": 8271073747, "lat": -8.6927067, "lon": -69.0268341}, {"type": "node", "id": 8271073748, "lat": -8.6926153, "lon": -69.0268233}, {"type": "node", "id": 8271073749, "lat": -8.6925119, "lon": -69.0267858}, {"type": "node", "id": 8271073750, "lat": -8.6923674, "lon": -69.0266584}, {"type": "node", "id": 8271073751, "lat": -8.6921897, "lon": -69.0265417}, {"type": "node", "id": 8271073752, "lat": -8.6918901, "lon": -69.0263821}, {"type": "node", "id": 8271073753, "lat": -8.6917589, "lon": -69.0263231}, {"type": "node", "id": 8271073754, "lat": -8.6916621, "lon": -69.0262587}, {"type": "node", "id": 8271073755, "lat": -8.691271, "lon": -69.0259436}, {"type": "node", "id": 8271073756, "lat": -8.6911636, "lon": -69.0258551}, {"type": "node", "id": 8271073757, "lat": -8.6909568, "lon": -69.0257317}, {"type": "node", "id": 8271073758, "lat": -8.6902675, "lon": -69.0253173}, {"type": "node", "id": 8271073759, "lat": -8.690123, "lon": -69.0252355}, {"type": "node", "id": 8271073760, "lat": -8.6899798, "lon": -69.0251751}, {"type": "node", "id": 8271073761, "lat": -8.6898194, "lon": -69.0251322}, {"type": "node", "id": 8271073762, "lat": -8.6897239, "lon": -69.0251268}, {"type": "node", "id": 8271073763, "lat": -8.6896192, "lon": -69.0251362}, {"type": "node", "id": 8271073764, "lat": -8.6894707, "lon": -69.0251631}, {"type": "node", "id": 8271073765, "lat": -8.689187, "lon": -69.0252972}, {"type": "node", "id": 8271073766, "lat": -8.6889908, "lon": -69.0254205}, {"type": "node", "id": 8271073767, "lat": -8.6887535, "lon": -69.0255345}, {"type": "node", "id": 8271073768, "lat": -8.6882457, "lon": -69.0257438}, {"type": "node", "id": 8271073769, "lat": -8.6880562, "lon": -69.0258443}, {"type": "node", "id": 8271073770, "lat": -8.6878653, "lon": -69.02602}, {"type": "node", "id": 8271073771, "lat": -8.6877486, "lon": -69.0260965}, {"type": "node", "id": 8271073772, "lat": -8.6876121, "lon": -69.026138}, {"type": "node", "id": 8271073773, "lat": -8.6871507, "lon": -69.0261783}, {"type": "node", "id": 8271073774, "lat": -8.6869704, "lon": -69.0262038}, {"type": "node", "id": 8271073775, "lat": -8.6868378, "lon": -69.0262266}, {"type": "node", "id": 8271073776, "lat": -8.6866734, "lon": -69.0262601}, {"type": "node", "id": 8271073777, "lat": -8.6864786, "lon": -69.0263405}, {"type": "node", "id": 8271073778, "lat": -8.6861604, "lon": -69.0265404}, {"type": "node", "id": 8271073779, "lat": -8.6859986, "lon": -69.0266383}, {"type": "node", "id": 8271073780, "lat": -8.685813, "lon": -69.0268408}, {"type": "node", "id": 8271073781, "lat": -8.6856977, "lon": -69.0270419}, {"type": "node", "id": 8271073782, "lat": -8.6855293, "lon": -69.0273209}, {"type": "node", "id": 8271073783, "lat": -8.685475, "lon": -69.0274939}, {"type": "node", "id": 8271073784, "lat": -8.6853451, "lon": -69.0281336}, {"type": "node", "id": 8271073785, "lat": -8.6852722, "lon": -69.0283361}, {"type": "node", "id": 8271073786, "lat": -8.6851754, "lon": -69.0284394}, {"type": "node", "id": 8271073787, "lat": -8.6850866, "lon": -69.0284809}, {"type": "node", "id": 8271073788, "lat": -8.6849354, "lon": -69.028493}, {"type": "node", "id": 8271073789, "lat": -8.684726, "lon": -69.0284783}, {"type": "node", "id": 8271073790, "lat": -8.6845881, "lon": -69.0284447}, {"type": "node", "id": 8271073791, "lat": -8.6844118, "lon": -69.0283522}, {"type": "node", "id": 8271073792, "lat": -8.6843335, "lon": -69.0282691}, {"type": "node", "id": 8271073793, "lat": -8.6841254, "lon": -69.0279928}, {"type": "node", "id": 8271073794, "lat": -8.6840273, "lon": -69.0278775}, {"type": "node", "id": 8271073795, "lat": -8.6838284, "lon": -69.0277031}, {"type": "node", "id": 8271073796, "lat": -8.6835938, "lon": -69.0275583}, {"type": "node", "id": 8271073797, "lat": -8.683273, "lon": -69.0273866}, {"type": "node", "id": 8271073798, "lat": -8.6830728, "lon": -69.0272807}, {"type": "node", "id": 8271073799, "lat": -8.6829137, "lon": -69.0272391}, {"type": "node", "id": 8271073800, "lat": -8.6825809, "lon": -69.027164}, {"type": "node", "id": 8271073801, "lat": -8.6820679, "lon": -69.0269709}, {"type": "node", "id": 8271073802, "lat": -8.6819406, "lon": -69.0268931}, {"type": "node", "id": 8271073803, "lat": -8.6818597, "lon": -69.0268274}, {"type": "node", "id": 8271073804, "lat": -8.6818014, "lon": -69.0267536}, {"type": "node", "id": 8271073805, "lat": -8.6817576, "lon": -69.0266731}, {"type": "node", "id": 8271073806, "lat": -8.6816675, "lon": -69.0264237}, {"type": "node", "id": 8271073807, "lat": -8.68158, "lon": -69.0262614}, {"type": "node", "id": 8271073808, "lat": -8.6814753, "lon": -69.0261514}, {"type": "node", "id": 8271073809, "lat": -8.6813917, "lon": -69.0260844}, {"type": "node", "id": 8271073810, "lat": -8.6813095, "lon": -69.0260442}, {"type": "node", "id": 8271073811, "lat": -8.6812287, "lon": -69.026016}, {"type": "node", "id": 8271073812, "lat": -8.6810245, "lon": -69.0259932}, {"type": "node", "id": 8271073813, "lat": -8.6808522, "lon": -69.0259784}, {"type": "node", "id": 8271073814, "lat": -8.6807196, "lon": -69.0259489}, {"type": "node", "id": 8271073815, "lat": -8.6804823, "lon": -69.0258604}, {"type": "node", "id": 8271073816, "lat": -8.6799666, "lon": -69.0255667}, {"type": "node", "id": 8271073817, "lat": -8.6796179, "lon": -69.0253374}, {"type": "node", "id": 8271073818, "lat": -8.6794005, "lon": -69.0252422}, {"type": "node", "id": 8271073819, "lat": -8.6792321, "lon": -69.0251979}, {"type": "node", "id": 8271073820, "lat": -8.6789603, "lon": -69.0251711}, {"type": "node", "id": 8271073821, "lat": -8.6787946, "lon": -69.0251818}, {"type": "node", "id": 8271073822, "lat": -8.6786183, "lon": -69.0252033}, {"type": "node", "id": 8271073823, "lat": -8.6783478, "lon": -69.025277}, {"type": "node", "id": 8271074385, "lat": -8.7306503, "lon": -69.008925}, {"type": "node", "id": 8271074386, "lat": -8.7305297, "lon": -69.0090738}, {"type": "node", "id": 8271074387, "lat": -8.7303932, "lon": -69.0091798}, {"type": "node", "id": 8271074388, "lat": -8.7301506, "lon": -69.0093139}, {"type": "node", "id": 8271074389, "lat": -8.7300565, "lon": -69.0093635}, {"type": "node", "id": 8271074390, "lat": -8.7299345, "lon": -69.0094011}, {"type": "node", "id": 8271074391, "lat": -8.7294016, "lon": -69.0094681}, {"type": "node", "id": 8271074392, "lat": -8.7292293, "lon": -69.0094788}, {"type": "node", "id": 8271074393, "lat": -8.7290013, "lon": -69.0095486}, {"type": "node", "id": 8271074394, "lat": -8.7288754, "lon": -69.0095995}, {"type": "node", "id": 8271074395, "lat": -8.7281278, "lon": -69.010246}, {"type": "node", "id": 8271074396, "lat": -8.7277274, "lon": -69.0106054}, {"type": "node", "id": 8271074397, "lat": -8.7275525, "lon": -69.0108025}, {"type": "node", "id": 8271074398, "lat": -8.7274636, "lon": -69.0108615}, {"type": "node", "id": 8271074399, "lat": -8.7274332, "lon": -69.0108736}, {"type": "node", "id": 8271074400, "lat": -8.7272303, "lon": -69.010891}, {"type": "node", "id": 8271074401, "lat": -8.7270355, "lon": -69.0108521}, {"type": "node", "id": 8271074402, "lat": -8.7267969, "lon": -69.0107583}, {"type": "node", "id": 8271074403, "lat": -8.7266312, "lon": -69.0106992}, {"type": "node", "id": 8271074404, "lat": -8.7263886, "lon": -69.0105557}, {"type": "node", "id": 8271074405, "lat": -8.7256688, "lon": -69.0099818}, {"type": "node", "id": 8271074406, "lat": -8.7255734, "lon": -69.0099174}, {"type": "node", "id": 8271074407, "lat": -8.7254846, "lon": -69.0099053}, {"type": "node", "id": 8271074408, "lat": -8.725405, "lon": -69.0099241}, {"type": "node", "id": 8271074409, "lat": -8.7253096, "lon": -69.0099657}, {"type": "node", "id": 8271074410, "lat": -8.7251532, "lon": -69.0100756}, {"type": "node", "id": 8271074411, "lat": -8.7247528, "lon": -69.0102835}, {"type": "node", "id": 12623617441, "lat": -8.6415467, "lon": -69.0301841}, {"type": "node", "id": 12623617442, "lat": -8.6606389, "lon": -69.0311819}, {"type": "node", "id": 12623617443, "lat": -8.6490803, "lon": -69.0295672}, {"type": "node", "id": 12623617444, "lat": -8.6303588, "lon": -69.0385151}, {"type": "node", "id": 12623617445, "lat": -8.6228381, "lon": -69.042635}, {"type": "node", "id": 12623617446, "lat": -8.6226153, "lon": -69.0434933}, {"type": "node", "id": 12623617447, "lat": -8.6303667, "lon": -69.039529}, {"type": "node", "id": 12623617448, "lat": -8.6302527, "lon": -69.0388906}, {"type": "node", "id": 12623617449, "lat": -8.6386616, "lon": -69.0307528}, {"type": "node", "id": 12623617450, "lat": -8.6240473, "lon": -69.0421736}, {"type": "node", "id": 12623617451, "lat": -8.6470013, "lon": -69.0295029}, {"type": "node", "id": 12623617452, "lat": -8.6500853, "lon": -69.0327269}, {"type": "node", "id": 12623617453, "lat": -8.6370413, "lon": -69.0313804}, {"type": "node", "id": 12623617454, "lat": -8.640181, "lon": -69.0296638}, {"type": "node", "id": 12623617455, "lat": -8.6291283, "lon": -69.0436757}, {"type": "node", "id": 12623617456, "lat": -8.622732, "lon": -69.0444374}, {"type": "node", "id": 12623617457, "lat": -8.6200589, "lon": -69.0431714}, {"type": "node", "id": 12623617458, "lat": -8.6301148, "lon": -69.0418947}, {"type": "node", "id": 12623617459, "lat": -8.6188602, "lon": -69.0419912}, {"type": "node", "id": 12623617460, "lat": -8.6526972, "lon": -69.0329576}, {"type": "node", "id": 12623617461, "lat": -8.6196558, "lon": -69.0429568}, {"type": "node", "id": 12623617462, "lat": -8.6502258, "lon": -69.0320671}, {"type": "node", "id": 12623617463, "lat": -8.661498, "lon": -69.0313965}, {"type": "node", "id": 12623617464, "lat": -8.6301678, "lon": -69.0426672}, {"type": "node", "id": 12623617465, "lat": -8.6378793, "lon": -69.0315628}, {"type": "node", "id": 12623617466, "lat": -8.6388313, "lon": -69.0303987}, {"type": "node", "id": 12623617467, "lat": -8.6390249, "lon": -69.0297711}, {"type": "node", "id": 12623617468, "lat": -8.6407432, "lon": -69.0298033}, {"type": "node", "id": 12623617469, "lat": -8.6349093, "lon": -69.0322387}, {"type": "node", "id": 12623617470, "lat": -8.6506183, "lon": -69.0334618}, {"type": "node", "id": 12623617471, "lat": -8.6302315, "lon": -69.0431607}, {"type": "node", "id": 12623617472, "lat": -8.6301572, "lon": -69.040736}, {"type": "node", "id": 12623617473, "lat": -8.6494833, "lon": -69.0299642}, {"type": "node", "id": 12623617474, "lat": -8.6455376, "lon": -69.029696}, {"type": "node", "id": 12623617475, "lat": -8.6611719, "lon": -69.0313911}, {"type": "node", "id": 12623617476, "lat": -8.6354396, "lon": -69.031713}, {"type": "node", "id": 12623617477, "lat": -8.6285741, "lon": -69.0435845}, {"type": "node", "id": 12623617478, "lat": -8.6564519, "lon": -69.0326679}, {"type": "node", "id": 12623617479, "lat": -8.6597585, "lon": -69.0315896}, {"type": "node", "id": 12623617480, "lat": -8.6209605, "lon": -69.0442765}, {"type": "node", "id": 12623617481, "lat": -8.6243655, "lon": -69.0423131}, {"type": "node", "id": 12623617482, "lat": -8.6329337, "lon": -69.0331346}, {"type": "node", "id": 12623617483, "lat": -8.649897, "lon": -69.0306401}, {"type": "node", "id": 12623617484, "lat": -8.6441136, "lon": -69.0291005}, {"type": "node", "id": 12623617485, "lat": -8.6339095, "lon": -69.0326625}, {"type": "node", "id": 12623617486, "lat": -8.6234003, "lon": -69.0422702}, {"type": "node", "id": 12623617487, "lat": -8.6537685, "lon": -69.0323997}, {"type": "node", "id": 12623617488, "lat": -8.6295526, "lon": -69.0436542}, {"type": "node", "id": 12623617489, "lat": -8.6477862, "lon": -69.0295351}, {"type": "node", "id": 12623617490, "lat": -8.6541185, "lon": -69.0323889}, {"type": "node", "id": 12623617491, "lat": -8.6517744, "lon": -69.0330863}, {"type": "node", "id": 12623617492, "lat": -8.6327242, "lon": -69.0352106}, {"type": "node", "id": 12623617493, "lat": -8.635917, "lon": -69.0313053}, {"type": "node", "id": 12623617494, "lat": -8.6321169, "lon": -69.037469}, {"type": "node", "id": 12623617495, "lat": -8.6593369, "lon": -69.0324855}, {"type": "node", "id": 12623617496, "lat": -8.6317881, "lon": -69.037748}, {"type": "node", "id": 12623617497, "lat": -8.6585308, "lon": -69.0338051}, {"type": "node", "id": 12623617498, "lat": -8.6376459, "lon": -69.0315628}, {"type": "node", "id": 12623617499, "lat": -8.6594324, "lon": -69.0319812}, {"type": "node", "id": 12623617500, "lat": -8.6326473, "lon": -69.036718}, {"type": "node", "id": 12623621301, "lat": -8.6591566, "lon": -69.0332794}, {"type": "node", "id": 12623621302, "lat": -8.644933, "lon": -69.0293634}, {"type": "node", "id": 12623621303, "lat": -8.6181893, "lon": -69.0416533}, {"type": "node", "id": 12623621304, "lat": -8.6325651, "lon": -69.0371311}, {"type": "node", "id": 12623621305, "lat": -8.6423661, "lon": -69.029932}, {"type": "node", "id": 12623621306, "lat": -8.6485711, "lon": -69.0295029}, {"type": "node", "id": 12623621307, "lat": -8.6432783, "lon": -69.0289342}, {"type": "node", "id": 12623621308, "lat": -8.6421089, "lon": -69.0301627}, {"type": "node", "id": 12623621309, "lat": -8.6411357, "lon": -69.0301251}, {"type": "node", "id": 12623621310, "lat": -8.6532593, "lon": -69.0326786}, {"type": "node", "id": 12623621311, "lat": -8.6398946, "lon": -69.0294814}, {"type": "node", "id": 12623621312, "lat": -8.6382611, "lon": -69.0313268}, {"type": "node", "id": 12623621313, "lat": -8.6248933, "lon": -69.0429837}, {"type": "node", "id": 12623621314, "lat": -8.6502788, "lon": -69.0331614}, {"type": "node", "id": 12623621315, "lat": -8.6315468, "lon": -69.0381932}, {"type": "node", "id": 12623621316, "lat": -8.6549458, "lon": -69.0327108}, {"type": "node", "id": 12623621317, "lat": -8.6581278, "lon": -69.0338373}, {"type": "node", "id": 12623621318, "lat": -8.6553701, "lon": -69.0326786}, {"type": "node", "id": 12623621319, "lat": -8.622244, "lon": -69.0448451}, {"type": "node", "id": 12623621320, "lat": -8.6266992, "lon": -69.0437186}, {"type": "node", "id": 12623621321, "lat": -8.6225198, "lon": -69.0447593}, {"type": "node", "id": 12623621322, "lat": -8.6300167, "lon": -69.043445}, {"type": "node", "id": 12623621323, "lat": -8.6226896, "lon": -69.042989}, {"type": "node", "id": 12623621324, "lat": -8.658963, "lon": -69.0335101}, {"type": "node", "id": 12623621325, "lat": -8.6603127, "lon": -69.0312302}, {"type": "node", "id": 12623621326, "lat": -8.6280967, "lon": -69.0436703}, {"type": "node", "id": 12623621327, "lat": -8.6326605, "lon": -69.0345776}, {"type": "node", "id": 12623621328, "lat": -8.6427241, "lon": -69.0293366}, {"type": "node", "id": 12623621329, "lat": -8.6274841, "lon": -69.0436113}, {"type": "node", "id": 12623621330, "lat": -8.6395658, "lon": -69.0295243}, {"type": "node", "id": 12623621331, "lat": -8.6499394, "lon": -69.0315628}, {"type": "node", "id": 12623621332, "lat": -8.6327984, "lon": -69.0334833}, {"type": "node", "id": 12623621333, "lat": -8.6184757, "lon": -69.0417498}, {"type": "node", "id": 12623621334, "lat": -8.6325226, "lon": -69.0358973}, {"type": "node", "id": 12623621335, "lat": -8.6568656, "lon": -69.0327001}, {"type": "node", "id": 12623621336, "lat": -8.6510637, "lon": -69.0333331}, {"type": "node", "id": 12623621337, "lat": -8.6499606, "lon": -69.0311015}, {"type": "node", "id": 12623621338, "lat": -8.6227638, "lon": -69.0442014}, {"type": "node", "id": 12623621339, "lat": -8.62165, "lon": -69.0447807}, {"type": "node", "id": 12623621340, "lat": -8.6578308, "lon": -69.0336335}, {"type": "node", "id": 12623621341, "lat": -8.6572448, "lon": -69.0329844}, {"type": "node", "id": 12623621342, "lat": -8.6257763, "lon": -69.0436113}, {"type": "node", "id": 12623621343, "lat": -8.6306955, "lon": -69.0383273}, {"type": "node", "id": 12623621344, "lat": -8.645877, "lon": -69.0297389}, {"type": "node", "id": 12623621345, "lat": -8.6300167, "lon": -69.0402371}, {"type": "way", "id": 257648008, "nodes": [8271073503, 8271073504, 8271073505, 8271073506, 8271073507, 8271073508, 8271073509, 8271073510, 8271073511, 8271073512, 8271073513, 8271073514, 8271073515, 8271073516, 8271073517, 8271073518, 8271073519, 8271073520, 8271073521, 8271073522, 8271073523, 8271073524, 8271073525, 8271073526, 8271073527, 8271073528, 8271073529, 2631349079, 2631349082, 8271073531, 2631349086, 8271073532, 2631349088, 8271073533, 2631349091, 8271073534, 8271073535, 8271073536, 2631349094, 2631349096, 2631349098, 8271073530], "tags": {"highway": "residential"}}, {"type": "way", "id": 257648010, "nodes": [12623621303, 12623621333, 12623617459, 12623617461, 12623617457, 12623617480, 12623621339, 12623621319, 12623621321, 12623617456, 12623621338, 12623617446, 12623621323, 12623617445, 12623617486, 12623617450, 12623617481, 12623621313, 12623621342, 12623621320, 12623621329, 12623621326, 12623617477, 12623617455, 12623617488, 12623621322, 12623617471, 12623617464, 12623617458, 12623617472, 12623621345, 12623617447, 12623617448, 12623617444, 12623621343, 12623621315, 12623617496, 12623617494, 12623621304, 12623617500, 12623621334, 12623617492, 12623621327, 12623621332, 12623617482, 12623617485, 12623617469, 12623617476, 12623617493, 12623617453, 12623617498, 12623617465, 12623621312, 12623617449, 12623617466, 12623617467, 12623621330, 12623621311, 12623617454, 12623617468, 12623621309, 12623617441, 12623621308, 12623621305, 12623621328, 12623621307, 12623617484, 12623621302, 12623617474, 12623621344, 12623617451, 12623617489, 12623621306, 12623617443, 12623617473, 12623617483, 12623621337, 12623621331, 12623617462, 12623617452, 12623621314, 12623617470, 12623621336, 12623617491, 12623617460, 12623621310, 12623617487, 12623617490, 12623621316, 12623621318, 12623617478, 12623621335, 12623621341, 12623621340, 12623621317, 12623617497, 12623621324, 12623621301, 12623617495, 12623617499, 12623617479, 12623621325, 12623617442, 12623617475, 12623617463, 8271073235, 8271073234, 8271073233, 8271073232, 8271073231, 8271073230, 8271073229, 8271073228, 8271073227, 8271073226, 8271073225, 8271073224, 8271073223, 8271073222, 8271073221, 8271073220, 8271073219, 8271073218, 8271073217, 8271036416, 8271036415, 8271036414, 8271036413, 8271036412, 8271036411, 8271036410, 8271036409, 8271036408, 8271036407, 8271036406, 8271036405, 8271036404, 8271036403, 8271036402, 8271036401, 8271036400, 8271036399, 8271036398, 8271036397, 8271036396, 8271036395, 8271036394, 8271036393, 8271036392, 8271036391, 8271036390, 8271036389, 8271036388, 8271036387, 8271036386, 8271036385, 8271036384, 8271036383, 8271036382, 8271036381, 8271036380, 8271036379, 8271036378, 8271036377, 8271036376, 8271036375, 8271036374, 8271036373, 8271036372, 8271036371, 8271036370, 8271036369, 8271036368, 8271036367, 8271036366, 8271036365, 8271036364, 8271036363, 8271036362, 8271036361, 8271036360, 8271036359, 8271036358, 8271036357, 8271036356, 8271036355, 8271036354, 8271036353, 8271036352, 8271036351, 8271036350, 8271036349, 8271036348, 8271036347, 8271073823, 8271073822, 8271073821, 8271073820, 8271073819, 8271073818, 8271073817, 8271073816, 8271073815, 8271073814, 8271073813, 8271073812, 8271073811, 8271073810, 8271073809, 8271073808, 8271073807, 8271073806, 8271073805, 8271073804, 8271073803, 8271073802, 8271073801, 8271073800, 8271073799, 8271073798, 8271073797, 8271073796, 8271073795, 8271073794, 8271073793, 8271073792, 8271073791, 8271073790, 8271073789, 8271073788, 8271073787, 8271073786, 8271073785, 8271073784, 8271073783, 8271073782, 8271073781, 8271073780, 8271073779, 8271073778, 8271073777, 8271073776, 8271073775, 8271073774, 8271073773, 8271073772, 8271073771, 8271073770, 8271073769, 8271073768, 8271073767, 8271073766, 8271073765, 8271073764, 8271073763, 8271073762, 8271073761, 8271073760, 8271073759, 8271073758, 8271073757, 8271073756, 8271073755, 8271073754, 8271073753, 8271073752, 8271073751, 8271073750, 8271073749, 8271073748, 8271073747, 8271073746, 8271073745, 8271073744, 8271073743, 8271073742, 8271073741, 8271073740, 8271073739, 8271073738, 8271073737, 8271073736, 8271073735, 8271073734, 8271073733, 8271073732, 8271073731, 8271073730, 8271073729, 8271073728, 8271073727, 8271073726, 8271073725, 8271073724, 8271073723, 8271073722, 8271073721, 8271073720, 8271073719, 8271073718, 8271073717, 8271073716, 8271073715, 8271073714, 8271073713, 8271073712, 8271073711, 8271073710, 8271073709, 8271073702, 8271073708, 8271073707, 8271073706, 8271073705, 8271073704, 8271073703, 8271073701, 8271073700, 8271073699, 8271073698, 8271073697, 8271073696, 8271073695, 8271073694, 8271073693, 8271073692, 8271073691, 8271073690, 8271073689, 8271073688, 8271073687, 8271073686, 8271073685, 8271073684, 8271073683, 8271073682, 8271073681, 8271073680, 8271073679, 8271073678, 8271073677, 8271073676, 8271073675, 8271073674, 8271073673, 8271073672, 8271073671, 8271073670, 8271073669, 8271073668, 8271073667, 8271073666, 8271073665, 8271073664, 8271073663, 8271073662, 8271073661, 8271073660, 8271073659, 8271073658, 8271073657, 8271073656, 8271073655, 8271073654, 8271073653, 8271073652, 8271073651, 8271073650, 8271073649, 8271073648, 8271073647, 8271073646, 8271073645, 8271073644, 8271073643, 8271073642, 8271073641, 8271073640, 8271073639, 8271073638, 8271073637, 8271073636, 8271073635, 8271073634, 8271073633, 8271073632, 8271073631, 8271073630, 8271073629, 8271073628, 8271073627, 8271073626, 8271073625, 8271073624, 8271073623, 8271073622, 8271073621, 8271073620, 8271073619, 8271073618, 8271073617, 8271073616, 8271073615, 8271073614, 8271073613, 8271073612, 8271073611, 8271073610, 8271073609, 8271073608, 8271073607, 8271073606, 8271073605, 8271073604, 8271073603, 8271073602, 8271073601, 8271073600, 8271073599, 8271073598, 8271073597, 8271073596, 8271073595, 8271073594, 8271073593, 8271073592, 8271073591, 8271073590, 8271073589, 8271073588, 8271073587, 8271073586, 8271073585, 8271073584, 8271073583, 8271073582, 8271073581, 8271073580, 8271073579, 8271073578, 8271073577, 8271073576, 8271073575, 8271073574, 8271073573, 8271073572, 8271073571, 8271073570, 8271073569, 8271073568, 8271073567, 8271073566, 8271073565, 8271073564, 8271073563, 8271073562, 8271073561, 8271073560, 8271073559, 8271073558, 8271073557, 8271073556, 8271073555, 8271073554, 8271073553, 8271073552, 8271073551, 8271073550, 8271073549, 8271073548, 8271073547, 8271073546, 8271073545, 8271073544, 8271073543, 8271073542, 8271073541, 8271073540, 8271073539, 8271073538, 8271073537, 8271074411, 8271074410, 8271074409, 8271074408, 8271074407, 8271074406, 8271074405, 8271074404, 8271074403, 8271074402, 8271074401, 8271074400, 8271074399, 8271074398, 8271074397, 8271074396, 8271074395, 8271074394, 8271074393, 8271074392, 8271074391, 8271074390, 8271074389, 8271074388, 8271074387, 8271074386, 8271074385, 2631349203, 2631349202, 2631349201, 2631349200, 2631349199, 2631349198, 2631349197, 2631349196, 2631349194, 2631349192, 2631349190, 2631349188, 2631349186, 2631349183, 2631349181, 2631349179, 2631349178, 2631349177, 2631349176, 2631349175, 2631349174, 2631349173, 2631349172, 2631349171, 2631349170, 2631349169, 2631349167, 2631349165, 2631349164, 2631349153, 2631349151, 2631349149, 2631349146, 2631349144, 2631349142, 2631349140, 2631349139, 2631349137, 2631349136, 2631349135, 2631349134, 2631349133, 2631349132, 2631349131, 2631349130, 2631349129, 2631349128, 2631349126, 2631349123, 8271073483, 2631349098], "tags": {"highway": "unclassified"}}, {"type": "way", "id": 456434781, "nodes": [4530254144, 4530254132, 4530254156, 4530254143, 4530254131, 4530254155, 4530254142, 4530254130, 4530254148, 4530254154, 4530254141, 4530254129, 4530254153, 4530254140, 4530254128, 4530254152, 4530254139, 4530254127, 4530254151, 4530254138, 4530254126, 4530254150, 4530254137, 4530254125, 4530254149, 4530254136, 4530254124, 4530254147, 4530254134, 4530254158, 4530254145, 4530254133, 4526935082, 4526935063, 4526934875, 4526935016, 4526935077, 4526934991, 4526935058, 4526934870, 4526935010, 4526935072, 4526934885, 4526935054, 4526935087, 4526935004, 4526935068, 4526934880, 4526935025, 4526935083, 4526934998, 4526935064, 4526934876, 4526935019, 4526935078, 4526934992, 4526935059, 4526934871, 4526935012, 4526935073, 4526934886, 4526935031, 4526935088, 4526935005, 4526935069, 4526934881, 4526935026, 4526935084, 4526934999, 4526935041, 4526934877, 4526935020, 4526935079, 4526934993, 4526935037, 4526934872, 4526935013, 4526935074, 4526934887, 4526935032, 4526935089, 4530244598, 4526935006, 4526935046, 4526934882, 4526935027, 4526935085, 4526935000, 4526935042, 4526934878, 4526935021, 4526935080, 4526934994, 4526935038, 4526934873, 4526935014, 4526935050, 4526934888, 4526935033, 4526935090, 4526935007, 4526935047, 4526934883, 4526935028, 4526935060, 4526935001, 4526935043, 4526934879, 4526935022, 4526935055, 4526934995, 4526935039, 4526934874, 4526935015, 4526935051, 4526934989, 4526935034, 4526935065, 4526935008, 4526935048, 4526934884, 4526935029, 4526935061, 4526935002, 4526935044, 4526935075, 4526935023, 4526935056], "tags": {"highway": "unclassified"}}, {"type": "way", "id": 456784959, "nodes": [4530244626, 4530244600, 4530244648, 4530244623, 4530244597, 3048136811, 4530244645, 4530244620, 4530244594, 4530244643, 4530244617, 4530244592, 4530244641, 4530244615, 4530244590, 4530244639, 4530244613, 4530244188, 4530244637, 4530244611, 4530244186, 4530244635, 4530244609, 4530244184, 4530244633, 4530244607, 4530244656, 4530244631, 4530244605, 4530244653, 4530244628, 4530244602, 4530244650, 4530244625, 4530244599, 4530244647, 4530244622, 4530244596, 4530244644, 4530244619, 4530244593, 4530244642, 4530244616, 4530244591, 4530244640, 4530244614, 4530244589, 4530244638, 4530244612, 4530244187, 4530244636, 4530244610, 4530244185, 4530244634, 4530244608, 4530244657, 4530244632, 4530244606, 4530244655, 4530244630, 4530244604, 4530244652, 4530244627, 4530244601, 4530244649, 4530244624, 4530244618, 4530244595, 4530244621, 4530244646, 4530244598], "tags": {"highway": "unclassified"}}, {"type": "way", "id": 889698923, "nodes": [8271073502, 8271073503, 8271073501, 8271073500, 8271073499, 8271073498, 8271073497, 8271073496, 8271073495, 8271073494, 8271073493, 8271073492, 8271073491, 8271073490, 8271073489, 8271073488, 8271073414, 8271073487, 8271073486, 8271073485, 8271073484, 8271073530], "tags": {"highway": "residential"}}]}